Workbook
Name Celdap39: 'OPI Constr'!$O$39
Name Celda39: 'OPI Rentas'!$A$38:$C$39
Name objetivi: 'OPI Constr'!$F$308
Name Celdap39: 'OPI Rentas'!$O$39
Name objetivi: 'OPI Rentas'!$F$381
Name Celda39: 'OPI Constr'!$A$38:$C$39

Sheet Fotos
A1: Nombre Imagen | B1: Link | C1: id | D1: URL | E1: Foto
A2: 2.jpg | B2: https://drive.google.com/uc?export=download&id= | C2: 1uCi2KXuJ7zjI3RAMnn9V5LcBtN9V-fhU | D2: {=IF(A2:A996="",,B2:B996&C2:C996)} -> https://drive.google.com/uc?export=download&id=1uCi2KXuJ7zjI3RAMnn9V5LcBtN9V-fhU | E2: {=IF(A2:A996="",,IMAGE(B2:B996&C2:C996,2))}
A3: 3.jpg | B3: https://drive.google.com/uc?export=download&id= | C3: 10Xv2lp7_p27VDrtWaA6ZguMhaq65APMW | D3: https://drive.google.com/uc?export=download&id=10Xv2lp7_p27VDrtWaA6ZguMhaq65APMW
A4: 18.jpeg | B4: https://drive.google.com/uc?export=download&id= | C4: 18Ncfra8WvnT1pAQVfZL0qdWOaxqr3NEN | D4: https://drive.google.com/uc?export=download&id=18Ncfra8WvnT1pAQVfZL0qdWOaxqr3NEN
A5: 17.jpeg | B5: https://drive.google.com/uc?export=download&id= | C5: 1yQIm9vwB0ttAv5TzuPLErZ2lxJ0EmEsM | D5: https://drive.google.com/uc?export=download&id=1yQIm9vwB0ttAv5TzuPLErZ2lxJ0EmEsM
A6: 15.jpeg | B6: https://drive.google.com/uc?export=download&id= | C6: 1g3-ALO6-_lRCAA68D2pb0vcRQkIiu3x6 | D6: https://drive.google.com/uc?export=download&id=1g3-ALO6-_lRCAA68D2pb0vcRQkIiu3x6
A7: 16.jpeg | B7: https://drive.google.com/uc?export=download&id= | C7: 135Fkj9z2TAiLqjt-NHW8slfpiGZoRHWw | D7: https://drive.google.com/uc?export=download&id=135Fkj9z2TAiLqjt-NHW8slfpiGZoRHWw
A8: 14.jpeg | B8: https://drive.google.com/uc?export=download&id= | C8: 1LSXqfxmYaSy4W8tmyN2ZIYpDY4HVW3Bc | D8: https://drive.google.com/uc?export=download&id=1LSXqfxmYaSy4W8tmyN2ZIYpDY4HVW3Bc
A9: 13.jpeg | B9: https://drive.google.com/uc?export=download&id= | C9: 1ootI2reS3zOEWwIDIPj52NqKyaiTqx-q | D9: https://drive.google.com/uc?export=download&id=1ootI2reS3zOEWwIDIPj52NqKyaiTqx-q
A10: 12.jpeg | B10: https://drive.google.com/uc?export=download&id= | C10: 1CxxSnrpMvDrmMtRuHFHboBjLdqGTGWD0 | D10: https://drive.google.com/uc?export=download&id=1CxxSnrpMvDrmMtRuHFHboBjLdqGTGWD0
A11: 11.jpeg | B11: https://drive.google.com/uc?export=download&id= | C11: 1Jry7NLsYl5OzJ_2uhRhdpLNckGrBjjeq | D11: https://drive.google.com/uc?export=download&id=1Jry7NLsYl5OzJ_2uhRhdpLNckGrBjjeq
A12: 10.jpeg | B12: https://drive.google.com/uc?export=download&id= | C12: 1VBqnJWPA6cKSsxaS8TywQ-nRxJrWW4RO | D12: https://drive.google.com/uc?export=download&id=1VBqnJWPA6cKSsxaS8TywQ-nRxJrWW4RO
A13: 9.jpeg | B13: https://drive.google.com/uc?export=download&id= | C13: 1706_ks01TI4s7uCDGnSTFNha80pyfeHo | D13: https://drive.google.com/uc?export=download&id=1706_ks01TI4s7uCDGnSTFNha80pyfeHo
A14: 8.jpeg | B14: https://drive.google.com/uc?export=download&id= | C14: 1HDGcYiNVXfchE1ro_AZYfBomR95IOoWA | D14: https://drive.google.com/uc?export=download&id=1HDGcYiNVXfchE1ro_AZYfBomR95IOoWA
... A22: Fototeca - 12 de 21.jpeg | B22: https://drive.google.com/uc?export=download&id= | C22: 13nd0w41CZpT4qpTbInVaF-5ydZmdQrQM | D22: https://drive.google.com/uc?export=download&id=13nd0w41CZpT4qpTbInVaF-5ydZmdQrQM

Sheet Base Datos Avaluo
A1: Folio | B1: Fecha | C1: Visito | D1: Capturo | E1: Reviso | F1: Tipo Propiedad | G1: Municipio | H1: Colonia | I1: Dirección | J1: Latitud | K1: Longitud | L1: Ubicación GPS | M1: Vida Util Ponderada | N1: Edad ponderada | O1: M2 Terreno | P1: M2 Construccion | Q1: M2 Accesoria | R1: PU Terreno | S1: PU construcc | T1: Valor Terreno | U1: Valor Constr | V1: Valor Instalaciones | W1: Valor Fisico | X1: Valor de Mercado venta | Y1: % dif Fisico/Mercado | Z1: Valor mercado Renta | AA1: Renta factorada
A2: =Query_Formato!B4 -> 450814fd | B2: ='OPI Constr'!AG6 -> 46202 | C2: =Query_Formato!B6 -> 2c214683 | F2: ='OPI Constr'!E8 -> Casa Habitación | G2: ='OPI Constr'!AB72 -> Guadalajara | H2: ='OPI Constr'!AG74 -> San Elías | I2: ='OPI Constr'!E10 -> Pascal 2164, San Elías, 44246 Guadalajara, Jal. | L2: =Query_Formato!B10 | M2: ='OPI Constr'!I86 -> 49 | N2: ='OPI Constr'!A86 -> 21 | O2: ='OPI Constr'!C111 -> 91.97 | P2: ='OPI Constr'!K123 -> 74.2 | Q2: ='OPI Constr'!K135 -> 0 | R2: ='OPI Constr'!AC111 -> 10500 | S2: ='OPI Constr'!AL209 -> 32793.328 | T2: ='OPI Constr'!AJ111 -> 965685 | U2: ='OPI Constr'!AJ123+'OPI Constr'!AJ135 -> 835989.01 | V2: ='OPI Constr'!AJ157 -> 8472.6096 | W2: ='OPI Constr'!AJ159 -> 1810146.6 | X2: ='OPI Constr'!AJ161 -> 2433265 | Y2: ='OPI Constr'!AP161 -> 0.25608323 | AA2: ='OPI Constr'!AI166 -> 9732

Sheet OPI Loc Com b
AF1: 3314189492 | AI1: 3336320507
AF2: avaluos@avaluosyarquitectura.com.mx
AF3: avaluosyarquitectura2@gmail.com
O4: OPINIÓN DE VALOR | AF4: www.avaluosyarquitectura.com.mx
AF7: Fecha: | AH7: =TODAY() -> 46202
A9: OPINIÓN DE VALOR DE:
A11: UBICACIÓN:
A14: SOLICITANTE:
A16: PROPIETARIO:
F19: =VLOOKUP("1.jp*g",Fotos!$A$2:$E506,5,FALSE)
C23: =Query_Formato!B11 -> Intermedia
C25: =Query_Formato!B11 -> Intermedia
F45: =VLOOKUP("2.jp*g",Fotos!$A$2:$E506,5,FALSE)
AB74: El valor POR LOCAL corresponde comparando venta de locales | AD74: =+ROUND(AI164,-3) -> #DIV/0!
AB76: El valor POR LOCAL corresponde comparando renta de locales | AD76: =ROUND(AJ162,-3) -> #DIV/0!
A79: ANTECEDENTES
A81: SOLICITANTE: | K81: =O14
A83: UBICACIÓN: | K83: =O11
A85: CUENTA PREDIAL: | S85: CLAVE CATASTRAL:
A87: INMUEBLE: | K87: =O9
A88: PROPIETARIO: | K88: =O16
A90: OBJETO DEL ANÁLISIS: | X90: RÉGIMEN DE PROP:
A92: CARACTERÍSTICAS URBANAS Y DEL INMUEBLE
A94: SERVICIOS: | K94: =+CONCATENATE(AS105," ",AT105,", ",AS106," ",AT106,", ",AS107," ",AT107,", ",AS108," ",AT108,", ",AS109," ",AT109,", ",AS110," ",AT110,", ",AS111," ",AT111,", ",AS112," ",AT112,", ",AS113," ",AT113,".", ) -> SERVICIOS BÁSICOS: , AGUA POTABLE: , DRENAJE: , ENERGÍA ELÉCTRICA: , GAS: , ALUMBRADO EXTERIOR: , LÍNEAS TELEFÓNICAS: , VIALIDADES: , TRANSPORTE: .
A97: CLASIFICACIÓN DE LA ZONA: | AR97: AÑO ACTUAL | AS97: 2023
V99: C.O.S. | X99: C.U.S. | Z99: Fr Min | AC99: M2 Min. Lote | AF99: N° Est. | AH99: % Edif. Zona | AK99: Niveles | AN99: Niv. Ubicación | AR99: AÑO CONSTR.
A100: USO DEL SUELO: | F100: H1-U | K100: =UPPER(CONCATENATE(VLOOKUP(F100,'catalogo 2'!L15:N113,2,0)," ",(VLOOKUP(F100,'catalogo 2'!L15:N113,3,0)))) -> HABITACIONAL DENSIDAD MÍNIMA UNIFAMILIAR | V100: =VLOOKUP(F100,'catalogo 2'!L15:AE114,14,0) -> 0.4 | X100: =VLOOKUP(F100,'catalogo 2'!L15:AF114,16,0) -> 0.8 | Z100: =VLOOKUP(F100,'catalogo 2'!L15:AF114,11,0) -> 20 | AC100: =VLOOKUP(F100,'catalogo 2'!L15:AF114,10,0) -> 600 m2 | AF100: =VLOOKUP(F100,'catalogo 2'!L15:AF114,18,0) -> 4 | AH100: =+'OPI Constr'!AH100 | AN100: 0 - P.BAJA | AR100: EDAD | AS100: =AS97-AS99 -> 2023
A102: EDAD APROX. | F102: VIDA ÚTIL | I102: ED. REMANENTE | M102: EDAD TIPO | R102: CALIDAD | V102: CONSERVACIÓN | AA102: PROYECTO: | AH102: CLAVE | AL102: % EDIF. SUJETO
A103: =+AS100 -> 2023 | F103: =IF(OR(R103="MEDIO",R103="SUPERIOR",R103="LUJO"),70,60) -> 60 | I103: =IF(OR(R103="MEDIO",R103="SUPERIOR",R103="LUJO"),70,60)-A103 -> -1963 | M103: =VLOOKUP(A103,'catalogo 2'!C137:F142,4) -> #N/A | AG103: =+CONCATENATE(VLOOKUP(M103,'catalogo 2'!E144:F149,2,FALSE),".",VLOOKUP('OPI Loc Com b'!R103,'catalogo 2'!G144:H149,2,FALSE),".",VLOOKUP('OPI Loc Com b'!V103,'catalogo 2'!I144:J152,2,FALSE),".",VLOOKUP('OPI Loc Com b'!Z103,'catalogo 2'!L144:M153,2,FALSE)) -> #N/A
A105: MEDIDAS Y LINDEROS SEGÚN: | V105: =VLOOKUP("3.jp*g",Fotos!$A$2:$E506,5,FALSE) | AS105: SERVICIOS BÁSICOS:
AS106: AGUA POTABLE:
A107: Norte | AS107: DRENAJE:
A108: =IF($A$107="norte","Sur","Sureste") -> Sur | E108: =IF(E107<>"", E107, "") | AS108: ENERGÍA ELÉCTRICA:
A109: =IF($A$107="norte","Este","Noroeste") -> Este | AS109: GAS:
A110: =IF($A$107="norte","Oeste","Suroeste") -> Oeste | E110: =IF(E109<>"", E109, "") | AS110: ALUMBRADO EXTERIOR:
AS111: LÍNEAS TELEFÓNICAS:
A112: DESCRIPCIÓN DEL INMUEBLE | AS112: VIALIDADES:
A113: =+'OPI Constr'!$S$81 | AS113: TRANSPORTE:
A120: AVALÚO FÍSICO
C121: A) DEL TERRENO: | P121: LOTE TIPO: | Q121: VARIABLE
A122: FRACC. | C122: SUPERFICIE: | G122: VALOR UNITARIO | K122: FACTORES DE EFICIENCIA DE SUELO: | AC122: V. TERRENO | AG122: INDIVISO: | AJ122: VALOR
K123: ZONA | M123: UBICACIÓN | P123: FRENTE | R123: FORMA | T123: SUPERFICIE | X123: OTRO | Z123: FAC.RE. | AC123: RESULTANTE: | AJ123: RESULTANTE:
A124: 1 | K124: 1 | M124: 1 | P124: 1 | R124: 1 | T124: 1 | X124: 1 | Z124: =ROUND(K124*M124*P124*R124*T124*X124,2) -> 1 | AC124: =+Z124*G124 -> 0 | AG124: 1 | AJ124: =C124*AC124*AG124 -> 0
A125: 2 | K125: 1 | M125: 1 | P125: 1 | R125: 1 | T125: 1 | X125: 1 | Z125: =ROUND(K125*M125*P125*R125*T125*X125,2) -> 1 | AC125: =+Z125*G125 -> 0 | AG125: 1 | AJ125: =+AC125*C125*AG125 -> 0
A126: 3 | G126: 0 | AC126: =+Z126*G126 -> 0 | AG126: 1 | AJ126: =+AC126*C126*AG126 -> 0
A127: T | C127: =SUM(C124:F126) -> 0 | G127: OTRO: | K127: =+'OPI Constr'!$K$122 -> #REF! | AH127: VALOR DEL TERRENO: | AJ127: =SUM(AJ124:AO126) -> 0 | AR127: MOVER EDAD MANUALMENTE CUANDO HAY MEJORAS O AMPLIACIONES
C129: B) DE LAS CONSTRUCCIONES: | N129: VALOR NUEVO | Q129: DEMÉRITO: | AC129: VALOR | AG129: INDIVISO: | AJ129: VALOR
A130: TIPO: | C130: DESCRIPCIÓN | K130: SUPERFICIE: | Q130: ACABADOS | T130: CONSERV | X130: PROYECTO | Z130: EDAD | AC130: USADO | AJ130: RESULTANTE: | AR130: =+F103 -> 60 | AS130: EDAD | AT130: REMANENTE
A131: I.- | Q131: 1 | T131: 0.85 | X131: 1 | Z131: =IF(AU131<0.2,"0.20",AU131) -> 0.20 | AC131: =Z131*X131*T131*P131 -> 0 | AG131: =AG124 -> 1 | AJ131: =K131*AC131*AG131 -> 0 | AR131: 60 | AS131: =+A103 -> 2023 | AT131: =AR130-AS131 -> -1963 | AU131: =ROUND(((0.1*AR130)+(0.9*AT131))/AR130,2) -> -29.35
A132: II.- | Q132: 1 | T132: 0 | X132: 1 | Z132: =IF(AU132<0.6,"0.60",AU132) -> 0.60 | AC132: =Z132*X132*T132*P132 -> 0 | AG132: 1 | AJ132: =K132*AC132*AG132 -> 0 | AR132: =+AR130 -> 60 | AS132: =+AS131 -> 2023 | AT132: =AR132-AS132 -> -1963 | AU132: =ROUND(((0.1*AR132)+(0.9*AT132))/AR132,2) -> -29.35
A133: III.- | Q133: 1 | T133: 0 | X133: 1 | Z133: =IF(AU133<0.6,"0.60",AU133) -> 0.60 | AC133: =Z133*X133*T133*P133 -> 0 | AG133: 1 | AJ133: =K133*AC133*AG133 -> 0 | AR133: =+AR132 -> 60 | AS133: =+AS132 -> 2023 | AT133: =AR133-AS133 -> -1963 | AU133: =ROUND(((0.1*AR133)+(0.9*AT133))/AR133,2) -> -29.35
A134: IV.- | Q134: 1 | T134: 1 | X134: 1 | Z134: =IF(AU134<0.6,"0.60",AU134) -> 0.60 | AC134: =Z134*X134*T134*P134 -> 0 | AG134: 1 | AJ134: =K134*AC134*AG134 -> 0 | AR134: =+AR133 -> 60 | AS134: =+AS133 -> 2023 | AT134: =AR134-AS134 -> -1963 | AU134: =ROUND(((0.1*AR134)+(0.9*AT134))/AR134,2) -> -29.35
A135: V.- | Q135: 1 | T135: 1 | X135: 1 | Z135: =IF(AU135<0.6,"0.60",AU135) -> 0.60 | AC135: =Z135*X135*T135*P135 -> 0 | AG135: 1 | AJ135: =K135*AC135*AG135 -> 0 | AR135: =+AR134 -> 60 | AS135: =+AS134 -> 2023 | AT135: =AR135-AS135 -> -1963 | AU135: =ROUND(((0.1*AR135)+(0.9*AT135))/AR135,2) -> -29.35
A136: VI.- | Q136: 1 | T136: 1 | X136: 1 | Z136: =IF(AU136<0.6,"0.60",AU136) -> 0.60 | AC136: =Z136*X136*T136*P136 -> 0 | AG136: 1 | AJ136: =K136*AC136*AG136 -> 0 | AR136: =+AR135 -> 60 | AS136: =+AS135 -> 2023 | AT136: =AR136-AS136 -> -1963 | AU136: =ROUND(((0.1*AR136)+(0.9*AT136))/AR136,2) -> -29.35
A137: VII.- | Q137: 1 | T137: 1 | X137: 1 | Z137: =IF(AU137<0.6,"0.60",AU137) -> 0.60 | AC137: =Z137*X137*T137*P137 -> 0 | AG137: 1 | AJ137: =K137*AC137*AG137 -> 0 | AR137: =+AR136 -> 60 | AS137: =+AS136 -> 2023 | AT137: =AR137-AS137 -> -1963 | AU137: =ROUND(((0.1*AR137)+(0.9*AT137))/AR137,2) -> -29.35
A138: VIII.- | Q138: 1 | T138: 1 | X138: 1 | Z138: =IF(AU138<0.6,"0.60",AU138) -> 0.60 | AC138: =Z138*X138*T138*P138 -> 0 | AG138: 1 | AJ138: =K138*AC138*AG138 -> 0 | AR138: =+AR137 -> 60 | AS138: =+AS137 -> 2023 | AT138: =AR138-AS138 -> -1963 | AU138: =ROUND(((0.1*AR138)+(0.9*AT138))/AR138,2) -> -29.35
C139: TOTAL: | K139: =SUM(K131:K138) -> 0 | AH139: VALOR DE LAS CONSTRUCCIONES: | AJ139: =SUM(AJ131:AJ138) -> 0
AR140: MOVER EDAD MANUALMENTE CUANDO HAY MEJORAS O AMPLIACIONES
C141: C)INSTALACIONES ADICIONALES, ACCESORIAS O ESPECIALES:
A142: CONCEPTO: | J142: CANTIDAD: | M142: UNIDAD: | P142: VALOR | T142: DEMÉRITO: | AC142: VALOR | AG142: INDIVISO: | AJ142: VALOR
P143: NUEVO | T143: CONSERVACIÓN | Y143: EDAD | AC143: USADO | AJ143: RESULTANTE: | AR143: NUEVA | AS143: EDAD | AT143: REMANENTE
A144: I.- | T144: 1 | Y144: =+AU144 -> 0.46 | AC144: =P144*T144*Y144 -> 0 | AG144: 1 | AJ144: =J144*AC144*AG144 -> 0 | AR144: 50 | AS144: 30 | AT144: =AR144-AS144 -> 20 | AU144: =ROUND(((0.1*AR144)+(0.9*AT144))/AR144,2) -> 0.46
A145: II.- | T145: 1 | AC145: =P145*T145*Y145 -> 0 | AG145: 1 | AJ145: =J145*AC145*AG145 -> 0 | AR145: 45 | AS145: 12 | AT145: =AR145-AS145 -> 33 | AU145: =ROUND(((0.1*AR145)+(0.9*AT145))/AR145,2) -> 0.76
A146: III.- | T146: 1 | Y146: =+AU146 -> 0.76 | AC146: =P146*T146*Y146 -> 0 | AG146: 1 | AJ146: =J146*AC146*AG146 -> 0 | AR146: 45 | AS146: =+AS145 -> 12 | AT146: =AR146-AS146 -> 33 | AU146: =ROUND(((0.1*AR146)+(0.9*AT146))/AR146,2) -> 0.76
A147: IV.- | T147: 1 | Y147: =+AU147 -> 0.85 | AC147: =P147*T147*Y147 -> 0 | AG147: 1 | AJ147: =J147*AC147*AG147 -> 0 | AR147: 70 | AS147: =+AS146 -> 12 | AT147: =AR147-AS147 -> 58 | AU147: =ROUND(((0.1*AR147)+(0.9*AT147))/AR147,2) -> 0.85
A148: V.- | T148: 1 | Y148: 1 | AC148: =P148*T148*Y148 -> 0 | AG148: 1 | AJ148: =J148*AC148*AG148 -> 0 | AR148: 71 | AS148: =+AS147 -> 12 | AT148: =AR148-AS148 -> 59 | AU148: =ROUND(((0.1*AR148)+(0.9*AT148))/AR148,2) -> 0.85
A149: V.- | T149: 1 | Y149: =+AU149 -> 0.85 | AC149: =P149*T149*Y149 -> 0 | AG149: 1 | AJ149: =J149*AC149*AG149 -> 0 | AR149: 72 | AS149: =+AS148 -> 12 | AT149: =AR149-AS149 -> 60 | AU149: =ROUND(((0.1*AR149)+(0.9*AT149))/AR149,2) -> 0.85
A150: V.- | T150: 1 | Y150: =+AU150 -> 0.85 | AC150: =P150*T150*Y150 -> 0 | AG150: 1 | AJ150: =J150*AC150*AG150 -> 0 | AR150: 73 | AS150: =+AS149 -> 12 | AT150: =AR150-AS150 -> 61 | AU150: =ROUND(((0.1*AR150)+(0.9*AT150))/AR150,2) -> 0.85
A151: V.- | T151: 1 | Y151: =+AU151 -> 0.85 | AC151: =P151*T151*Y151 -> 0 | AG151: 1 | AJ151: =J151*AC151*AG151 -> 0 | AR151: 74 | AS151: =+AS150 -> 12 | AT151: =AR151-AS151 -> 62 | AU151: =ROUND(((0.1*AR151)+(0.9*AT151))/AR151,2) -> 0.85
A152: V.- | T152: 1 | Y152: =+AU152 -> 0.86 | AC152: =P152*T152*Y152 -> 0 | AG152: 1 | AJ152: =J152*AC152*AG152 -> 0 | AR152: 75 | AS152: =+AS151 -> 12 | AT152: =AR152-AS152 -> 63 | AU152: =ROUND(((0.1*AR152)+(0.9*AT152))/AR152,2) -> 0.86
A153: V.- | T153: 1 | Y153: =+AU153 -> 0.86 | AC153: =P153*T153*Y153 -> 0 | AG153: 1 | AJ153: =J153*AC153*AG153 -> 0 | AR153: 76 | AS153: =+AS152 -> 12 | AT153: =AR153-AS153 -> 64 | AU153: =ROUND(((0.1*AR153)+(0.9*AT153))/AR153,2) -> 0.86
A154: V.- | T154: 1 | Y154: =+AU154 -> 0.86 | AC154: =P154*T154*Y154 -> 0 | AG154: 1 | AJ154: =J154*AC154*AG154 -> 0 | AR154: 77 | AS154: =+AS153 -> 12 | AT154: =AR154-AS154 -> 65 | AU154: =ROUND(((0.1*AR154)+(0.9*AT154))/AR154,2) -> 0.86
A155: V.- | T155: 1 | Y155: =+AU155 -> 0.86 | AC155: =P155*T155*Y155 -> 0 | AG155: 1 | AJ155: =J155*AC155*AG155 -> 0 | AR155: 78 | AS155: =+AS154 -> 12 | AT155: =AR155-AS155 -> 66 | AU155: =ROUND(((0.1*AR155)+(0.9*AT155))/AR155,2) -> 0.86
AH156: VALOR DE LAS INST. ESPECIALES: | AJ156: =SUM(AJ144:AO155) -> 0
A158: INFORMACIÓN PROPORCIONADA POR: | AA158: VALOR FÍSICO O DIRECTO: | AJ158: =SUM(AJ127,AJ139,AJ156) -> 0 | AR158: =AJ161/K139 -> #DIV/0! | AS158: RANGO A BUSCAR
A159: SUPERFICIES
A160: DE TERRENO SEGÚN: | Q160: V.-CONCLUSIONES: | AI160: VALOR POR COMPARACIÓN: | AJ160: =AJ216 -> #DIV/0! | AR160: =+(AJ160-AJ161)/AJ160 -> #DIV/0! | AS160: DIFERENCIA FÍSICO/MERCADO
A161: CONSTRUCCIÓN SEGÚN: | AI161: VALOR FÍSICO O DIRECTO ACTUAL: | AJ161: =AJ158 -> 0
AI162: POR VALOR DE CAPITALIZACIÓN DE RENTA COMPARABLE: | AJ162: =AJ274 -> #DIV/0! | AR162: =AI164/K139 -> #DIV/0! | AS162: precio x m2
A164: NOTA IMPORTANTE: ESTE ANÁLISIS DE MERCADO NO CUMPLE CON EL FORMATO DE ELABORACIÓN DE AVALÚOS AUTORIZADO POR LA C.N.B. y de V. En la Circular No.-1462 De FEBRERO 14 Del 2000 DEBIDO A QUE ES UN INSTRUMENTO DE NEGOCIACIÓN Y DECISIÓN EN UNA OPERACIÓN DE COMPRA VENTA Y NO UN CERTIFICADO DE VALOR DE USO ABIERTO (NO ES EL VALOR CATASTRAL O DE DACIÓN EN PAGO) | AH164: VALOR COMERCIAL ESTIMADO: | AI164: =ROUND(AJ160,-3) -> #DIV/0!
AH165: VALOR ESTIMADO DE RENTA POR FACTOR: | AI165: =AI164*AR165 -> #DIV/0! | AR165: 0.006 | AS165: FACTOR PARA RENTA
AH166: VALOR ESTIMADO DE RENTA POR COMPARACIÓN: | AI166: =+AJ273 -> #DIV/0!
Q167: =AS398 -> #DIV/0!
Q168: SE ESTIMA QUE EL VALOR COMERCIAL DEL INMUEBLE SEA IGUAL AL OBTENIDO POR EL AVALÚO DE MERCADO.
O170: ARQ. MVII. PEDRO VERGARA ESPINOSA
N171: CÉDULA FEDERAL 5685854 | O171: CÉDULA FEDERAL 5685855 | V171: CÉDULA ESTATAL100795
A173: PREMISAS
A174: A) NO FUE MATERIA DE ESTE ANÁLISIS EL VERIFICAR LA PROPIEDAD LEGAL, NI LA EXISTENCIA DE RESERVAS DE DOMINIO O GRAVÁMENES SOBRE EL INMUEBLE, ASÍ COMO ALGÚN PROBLEMA EN CUANTO A SUS LINDEROS
A176: B) QUE LOS DATOS APORTADOS POR TERCERAS PERSONAS SON CIERTOS Y CORRECTOS.
A177: C) QUE EL VALUADOR NO TIENE NINGÚN INTERÉS MANIFIESTO SOBRE EL INMUEBLE.
A178: D) QUE NO SE HAN DESCARTADO NI SOBREESTIMADO DATOS IMPORTANTES.
A179: E) EL PROCEDIMIENTO PARA ENCONTRAR EL VALOR Y SUS PARÁMETROS SON LOS COMUNES PARA ESTE TIPO DE DICTÁMENES.
A180: F) ESTE ANÁLISIS ES UN INSTRUMENTO DE NEGOCIACIÓN Y DECISIÓN EN UNA OPERACIÓN DE COMPRA VENTA, Y NO UN CERTIFICADO DE VALOR DE USO ABIERTO.
A183: INVESTIGACIÓN DE MERCADO DE VENTA
C185: Tipo | H185: C A L L E: | O185: COLONIA/ZONA | U185: Edad | W185: C A R A C T E R Í S T I C A S: | AJ185: FUENTE/TELÉFONO
A186: 1 | C186: =+Mercado!C30 -> Casa Habitación | H186: =UPPER(+Mercado!F30) -> AVENIDA FIDEL VELAZQUEZ 380 | O186: =UPPER(+Mercado!E30) -> SAN ELIAS | U186: =+Mercado!L30 -> 40 | W186: =PROPER(+Mercado!G30) -> 1 Nivel 3 Recamaras Con Closet Cocina Con Alacenas Estufas Área Sala-Comedor 1 Baño Completo Patio Amplio Con Jardín | AJ186: =UPPER(CONCATENATE(Mercado!M30,Mercado!N30)) -> GPM BIENES RAICES 33 1305 0083 | AR186: PU físico | AS186: % | AT186: PU mercado | AU186: % | AW186: PU físico | AX186: % | AZ186: PU mercado | BA186: %
A187: 2 | C187: =+Mercado!C31 -> Casa Habitación | H187: =UPPER(+Mercado!F31) -> PLATÓN S/N | O187: =UPPER(+Mercado!E31) -> INDEPENDENCIA | U187: =+Mercado!L31 -> 30 | W187: =PROPER(+Mercado!G31) -> 3 Recámaras 2 1/2 Baños 3 Cocheras Terraza Al Ingreso De La Casa 1 Área De Lavado Local Comercial Al Frente De 35.00 Mts Con Medio Baño. | AJ187: =UPPER(CONCATENATE(Mercado!M31,Mercado!N31)) -> IMPACTO INMOBILIARIA33 3485 2244 | AQ187: T | AR187: =+AC124 -> 0 | AS187: =+AR187/$AR$189 -> #DIV/0! | AT187: =+AC124 -> 0 | AU187: =+AT187/$AT$189 -> #DIV/0! | AV187: Terreno | AW187: =+AJ127 -> 0 | AX187: =+AW187/$AW$190 -> #DIV/0! | AY187: Terreno | AZ187: =+AW187 -> 0 | BA187: =+AZ187/$AZ$190 -> #DIV/0!
A188: 3 | C188: =+Mercado!C32 -> Casa Habitación | H188: =UPPER(+Mercado!F32) -> MONUMENTAL S/N | O188: =UPPER(+Mercado!E32) -> MONUMENTAL | U188: =+Mercado!L32 -> 6 | W188: =PROPER(+Mercado!G32) -> Cochera Un Auto, Jardín Exterior, Sala Comedor, Cocina, Patio De Servicio, Pasillo Distribuidor, Dos Recámara Secundarias Cada Una Con Su Clóset Que Comparten Un Baño Completo Y Otra Principal Con Baño Completo, Jardín Interior. | AJ188: =UPPER(CONCATENATE(Mercado!M32,Mercado!N32)) -> ENF COMERCIALIZADORA5664068640 | AQ188: C | AR188: =+AC131 -> 0 | AS188: =+AR188/$AR$189 -> #DIV/0! | AT188: =+AL210-AT187 -> #DIV/0! | AU188: =+AT188/$AT$189 -> #DIV/0! | AV188: Construcción | AW188: =+AJ139 -> 0 | AX188: =+AW188/$AW$190 -> #DIV/0! | AY188: Construcción | AZ188: =+AJ216-AZ187 -> #DIV/0! | BA188: =+AZ188/$AZ$190 -> #DIV/0!
A189: 4 | C189: =+Mercado!C33 -> Casa Habitación | H189: =UPPER(+Mercado!F33) -> AVENIDA DE LOS MAESTROS 576 | O189: =UPPER(+Mercado!E33) -> ALCALDE BARRANQUITAS | U189: =+Mercado!L33 -> 40 | W189: =PROPER(+Mercado!G33) -> 4 Recámaras, 2 Baños Uso De Suelo Mixto, Comercial Y Habitacional, Cuarto De Servicio Con Baño, Área De Lavandería | AJ189: =UPPER(CONCATENATE(Mercado!M33,Mercado!N33)) -> IAD INMOBILIARIA5513289530 | AQ189: tot | AR189: =SUM(AR187:AR188) -> 0 | AS189: =+AR189/$AR$189 -> #DIV/0! | AT189: =SUM(AT187:AT188) -> #DIV/0! | AU189: =+AT189/$AT$189 -> #DIV/0! | AV189: Acabados Esp. | AW189: =+AJ156 -> 0 | AX189: =+AW189/$AW$190 -> #DIV/0! | BA189: =+AZ189/$AZ$190 -> #DIV/0!
A190: 5 | C190: =+Mercado!C34 -> Casa Habitación | H190: =UPPER(+Mercado!F34) -> LOS ALPES 1548 | O190: =UPPER(+Mercado!E34) -> INDEPENDENCIA ORIENTE | U190: =+Mercado!L34 -> 40 | W190: =PROPER(+Mercado!G34) -> Sala Y Comedor Cocina Integral 5 Recámaras, 2 Baños Completos, Jardín Lateral, Espacio Para 1 Auto | AJ190: =UPPER(CONCATENATE(Mercado!M34,Mercado!N34)) -> CASA ADMINISTRACIONES33 3040 8700 | AV190: tot | AW190: =SUM(AW187:AW188) -> 0 | AX190: =+AW190/$AW$190 -> #DIV/0! | AZ190: =SUM(AZ187:AZ188) -> #DIV/0! | BA190: =+AZ190/$AZ$190 -> #DIV/0!
...

Sheet Query_Formato
A1: Atributo | B1: Valor | C1: Plantilla
A2: =IFERROR(__xludf.DUMMYFUNCTION("TRANSPOSE(QUERY(IMPORTRANGE(""1aF3RXZCNy_CKBDFezcCT7265looJ5_hSeKa4_qe8HZA"",""Visitas!A:EW""),""SELECT * WHERE Col3 ='450814fd'"",1))"),"ID") -> ID | B2: =IFERROR(__xludf.DUMMYFUNCTION("""COMPUTED_VALUE"""),"ba277a4d") -> ba277a4d | C2: ID
A3: =IFERROR(__xludf.DUMMYFUNCTION("""COMPUTED_VALUE"""),"Cliente") -> Cliente | B3: =IFERROR(__xludf.DUMMYFUNCTION("""COMPUTED_VALUE"""),"ba44bb30") -> ba44bb30 | C3: Cliente
A4: =IFERROR(__xludf.DUMMYFUNCTION("""COMPUTED_VALUE"""),"Avaluo") -> Avaluo | B4: =IFERROR(__xludf.DUMMYFUNCTION("""COMPUTED_VALUE"""),"450814fd") -> 450814fd | C4: Avaluo
A5: =IFERROR(__xludf.DUMMYFUNCTION("""COMPUTED_VALUE"""),"Fecha") -> Fecha | B5: =IFERROR(__xludf.DUMMYFUNCTION("""COMPUTED_VALUE"""),45975.0) -> 45975 | C5: Fecha
A6: =IFERROR(__xludf.DUMMYFUNCTION("""COMPUTED_VALUE"""),"Visitador") -> Visitador | B6: =IFERROR(__xludf.DUMMYFUNCTION("""COMPUTED_VALUE"""),"2c214683") -> 2c214683 | C6: Visitador
A7: =IFERROR(__xludf.DUMMYFUNCTION("""COMPUTED_VALUE"""),"Tipo de Avaluo") -> Tipo de Avaluo | B7: =IFERROR(__xludf.DUMMYFUNCTION("""COMPUTED_VALUE"""),"OPI") -> OPI | C7: Tipo de Avaluo
A8: =IFERROR(__xludf.DUMMYFUNCTION("""COMPUTED_VALUE"""),"SECCIÓN CARACTERÍSTICAS URBANAS") -> SECCIÓN CARACTERÍSTICAS URBANAS | C8: SECCIÓN CARACTERÍSTICAS URBANAS
A9: =IFERROR(__xludf.DUMMYFUNCTION("""COMPUTED_VALUE"""),"Direccion") -> Direccion | B9: =IFERROR(__xludf.DUMMYFUNCTION("""COMPUTED_VALUE"""),"Pascal 2164 Colonia San Elias Guadalajara Jalisco 44240") -> Pascal 2164 Colonia San Elias Guadalajara Jalisco 44240 | C9: Direccion
A10: =IFERROR(__xludf.DUMMYFUNCTION("""COMPUTED_VALUE"""),"Ubicacion GPS") -> Ubicacion GPS | C10: Ubicacion GPS
A11: =IFERROR(__xludf.DUMMYFUNCTION("""COMPUTED_VALUE"""),"Referencia Proximidad Urbana") -> Referencia Proximidad Urbana | B11: =IFERROR(__xludf.DUMMYFUNCTION("""COMPUTED_VALUE"""),"Intermedia") -> Intermedia | C11: Referencia Proximidad Urbana
A12: =IFERROR(__xludf.DUMMYFUNCTION("""COMPUTED_VALUE"""),"Nivel de Infraestructura") -> Nivel de Infraestructura | C12: Nivel de Infraestructura
A13: =IFERROR(__xludf.DUMMYFUNCTION("""COMPUTED_VALUE"""),"Agua Potable") -> Agua Potable | C13: Agua Potable
A14: =IFERROR(__xludf.DUMMYFUNCTION("""COMPUTED_VALUE"""),"Drenaje") -> Drenaje | B14: =IFERROR(__xludf.DUMMYFUNCTION("""COMPUTED_VALUE"""),"Entubado") -> Entubado | C14: Drenaje
A15: =IFERROR(__xludf.DUMMYFUNCTION("""COMPUTED_VALUE"""),"Electrificación") -> Electrificación | B15: =IFERROR(__xludf.DUMMYFUNCTION("""COMPUTED_VALUE"""),"Con Cableado Aereo") -> Con Cableado Aereo | C15: Electrificación
A16: =IFERROR(__xludf.DUMMYFUNCTION("""COMPUTED_VALUE"""),"Alumbrado Publico") -> Alumbrado Publico | B16: =IFERROR(__xludf.DUMMYFUNCTION("""COMPUTED_VALUE"""),"Con Cableado Aereo") -> Con Cableado Aereo | C16: Alumbrado Público
A17: =IFERROR(__xludf.DUMMYFUNCTION("""COMPUTED_VALUE"""),"Vialidades") -> Vialidades | B17: =IFERROR(__xludf.DUMMYFUNCTION("""COMPUTED_VALUE"""),"Asfalto") -> Asfalto | C17: Vialidades
A18: =IFERROR(__xludf.DUMMYFUNCTION("""COMPUTED_VALUE"""),"Señalización") -> Señalización | B18: =IFERROR(__xludf.DUMMYFUNCTION("""COMPUTED_VALUE"""),"Existe") -> Existe | C18: Señalización
A19: =IFERROR(__xludf.DUMMYFUNCTION("""COMPUTED_VALUE"""),"Transporte publico") -> Transporte publico | B19: =IFERROR(__xludf.DUMMYFUNCTION("""COMPUTED_VALUE"""),"Urbano") -> Urbano | C19: Transporte Público
A20: =IFERROR(__xludf.DUMMYFUNCTION("""COMPUTED_VALUE"""),"Clasificacion de la zona") -> Clasificacion de la zona | C20: Clasificacion de la zona
A21: =IFERROR(__xludf.DUMMYFUNCTION("""COMPUTED_VALUE"""),"Nivel de Equipamiento") -> Nivel de Equipamiento | C21: Nivel de Equipamiento
A22: =IFERROR(__xludf.DUMMYFUNCTION("""COMPUTED_VALUE"""),"Construcciones Predominantes") -> Construcciones Predominantes | B22: =IFERROR(__xludf.DUMMYFUNCTION("""COMPUTED_VALUE"""),"Casas Habitación") -> Casas Habitación | C22: Construcciones Predominantes
A23: =IFERROR(__xludf.DUMMYFUNCTION("""COMPUTED_VALUE"""),"Calidad de las Construcciones") -> Calidad de las Construcciones | C23: Calidad de las Construcciones
A24: =IFERROR(__xludf.DUMMYFUNCTION("""COMPUTED_VALUE"""),"Recoleccion de Basura") -> Recoleccion de Basura | B24: =IFERROR(__xludf.DUMMYFUNCTION("""COMPUTED_VALUE"""),"Municipal") -> Municipal | C24: Recoleccion de Basura
A25: =IFERROR(__xludf.DUMMYFUNCTION("""COMPUTED_VALUE"""),"Nivel socioeconómico") -> Nivel socioeconómico | B25: =IFERROR(__xludf.DUMMYFUNCTION("""COMPUTED_VALUE"""),"Medio-Medio") -> Medio-Medio | C25: Nivel socioeconómico
A26: =IFERROR(__xludf.DUMMYFUNCTION("""COMPUTED_VALUE"""),"Indice de Saturación en la zona") -> Indice de Saturación en la zona | C26: Indice de Saturación en la zona
A27: =IFERROR(__xludf.DUMMYFUNCTION("""COMPUTED_VALUE"""),"Densidaad de Población") -> Densidaad de Población | C27: Densidaad de Población
A28: =IFERROR(__xludf.DUMMYFUNCTION("""COMPUTED_VALUE"""),"Vias de Acceso") -> Vias de Acceso | C28: Vias de Acceso
A29: =IFERROR(__xludf.DUMMYFUNCTION("""COMPUTED_VALUE"""),"SECCIÓN GENERALES") -> SECCIÓN GENERALES | C29: SECCIÓN GENERALES
A30: =IFERROR(__xludf.DUMMYFUNCTION("""COMPUTED_VALUE"""),"Clave catastral") -> Clave catastral | C30: Clave catastral
A31: =IFERROR(__xludf.DUMMYFUNCTION("""COMPUTED_VALUE"""),"Num Predial") -> Num Predial | C31: Num Predial
A32: =IFERROR(__xludf.DUMMYFUNCTION("""COMPUTED_VALUE"""),"Tipo doc. referencia legal") -> Tipo doc. referencia legal | C32: Tipo doc. referencia legal
A33: =IFERROR(__xludf.DUMMYFUNCTION("""COMPUTED_VALUE"""),"Num Escritura") -> Num Escritura | C33: Num Escritura
A34: =IFERROR(__xludf.DUMMYFUNCTION("""COMPUTED_VALUE"""),"Notaria") -> Notaria | C34: Notaria
A35: =IFERROR(__xludf.DUMMYFUNCTION("""COMPUTED_VALUE"""),"Municipio") -> Municipio | C35: Municipio
A36: =IFERROR(__xludf.DUMMYFUNCTION("""COMPUTED_VALUE"""),"Regimen de Propiedad") -> Regimen de Propiedad | C36: Régimen de Propiedad
A37: =IFERROR(__xludf.DUMMYFUNCTION("""COMPUTED_VALUE"""),"Nombre Lic") -> Nombre Lic | C37: Nombre Lic
A38: =IFERROR(__xludf.DUMMYFUNCTION("""COMPUTED_VALUE"""),"Año de Construcción") -> Año de Construcción | C38: Año de Construcción
A39: =IFERROR(__xludf.DUMMYFUNCTION("""COMPUTED_VALUE"""),"Edad de las construcciones") -> Edad de las construcciones | C39: Edad de las construcciones
A40: =IFERROR(__xludf.DUMMYFUNCTION("""COMPUTED_VALUE"""),"Año Remodelación") -> Año Remodelación | B40: =IFERROR(__xludf.DUMMYFUNCTION("""COMPUTED_VALUE"""),2022.0) -> 2022 | C40: Año Remodelación
A41: =IFERROR(__xludf.DUMMYFUNCTION("""COMPUTED_VALUE"""),"Edad de las Remodelaciones") -> Edad de las Remodelaciones | B41: =IFERROR(__xludf.DUMMYFUNCTION("""COMPUTED_VALUE"""),3.0) -> 3 | C41: Edad de las Remodelaciones
A42: =IFERROR(__xludf.DUMMYFUNCTION("""COMPUTED_VALUE"""),"Nivel de Ubicación") -> Nivel de Ubicación | C42: Nivel de Ubicación
A43: =IFERROR(__xludf.DUMMYFUNCTION("""COMPUTED_VALUE"""),"Num de niveles") -> Num de niveles | B43: =IFERROR(__xludf.DUMMYFUNCTION("""COMPUTED_VALUE"""),1.0) -> 1 | C43: Num de niveles
A44: =IFERROR(__xludf.DUMMYFUNCTION("""COMPUTED_VALUE"""),"Tipo de propiedad") -> Tipo de propiedad | B44: =IFERROR(__xludf.DUMMYFUNCTION("""COMPUTED_VALUE"""),"Casa Habitación") -> Casa Habitación | C44: Tipo de propiedad
A45: =IFERROR(__xludf.DUMMYFUNCTION("""COMPUTED_VALUE"""),"Unidades Rentables") -> Unidades Rentables | B45: =IFERROR(__xludf.DUMMYFUNCTION("""COMPUTED_VALUE"""),1.0) -> 1 | C45: Unidades Rentables
A46: =IFERROR(__xludf.DUMMYFUNCTION("""COMPUTED_VALUE"""),"Estado de Conservación") -> Estado de Conservación | B46: =IFERROR(__xludf.DUMMYFUNCTION("""COMPUTED_VALUE"""),"Bueno") -> Bueno | C46: Estado de Conservación
A47: =IFERROR(__xludf.DUMMYFUNCTION("""COMPUTED_VALUE"""),"Uso actual") -> Uso actual | C47: Uso actual
A48: =IFERROR(__xludf.DUMMYFUNCTION("""COMPUTED_VALUE"""),"Clasificación de las Construcciones") -> Clasificación de las Construcciones | C48: Clasificación de las Construcciones
A49: =IFERROR(__xludf.DUMMYFUNCTION("""COMPUTED_VALUE"""),"Avance de las construcciones") -> Avance de las construcciones | C49: Avance de las construcciones
A50: =IFERROR(__xludf.DUMMYFUNCTION("""COMPUTED_VALUE"""),"SUBSECCIÓN EQUIPAMIENTO") -> SUBSECCIÓN EQUIPAMIENTO | C50: SUBSECCIÓN EQUIPAMIENTO
A51: =IFERROR(__xludf.DUMMYFUNCTION("""COMPUTED_VALUE"""),"Guarderia") -> Guarderia | C51: Guarderia
A52: =IFERROR(__xludf.DUMMYFUNCTION("""COMPUTED_VALUE"""),"Escuelas Primarias") -> Escuelas Primarias | C52: Escuelas Primarias
A53: =IFERROR(__xludf.DUMMYFUNCTION("""COMPUTED_VALUE"""),"Escuelas Secundarias") -> Escuelas Secundarias | C53: Escuelas Secundarias
A54: =IFERROR(__xludf.DUMMYFUNCTION("""COMPUTED_VALUE"""),"Escuelas Preparatorias") -> Escuelas Preparatorias | C54: Escuelas Preparatorias
A55: =IFERROR(__xludf.DUMMYFUNCTION("""COMPUTED_VALUE"""),"Escuelas Universitarias") -> Escuelas Universitarias | C55: Escuelas Universitarias
A56: =IFERROR(__xludf.DUMMYFUNCTION("""COMPUTED_VALUE"""),"Otras escuelas") -> Otras escuelas | C56: Otras escuelas
A57: =IFERROR(__xludf.DUMMYFUNCTION("""COMPUTED_VALUE"""),"Distancia Transporte publico") -> Distancia Transporte publico | C57: Distancia Transporte Público
A58: =IFERROR(__xludf.DUMMYFUNCTION("""COMPUTED_VALUE"""),"Iglesias") -> Iglesias | C58: Iglesias
A59: =IFERROR(__xludf.DUMMYFUNCTION("""COMPUTED_VALUE"""),"Parques") -> Parques | C59: Parques
A60: =IFERROR(__xludf.DUMMYFUNCTION("""COMPUTED_VALUE"""),"Hospitales") -> Hospitales | C60: Hospitales
A61: =IFERROR(__xludf.DUMMYFUNCTION("""COMPUTED_VALUE"""),"Clinicas medicas") -> Clinicas medicas | C61: Clinicas medicas
A62: =IFERROR(__xludf.DUMMYFUNCTION("""COMPUTED_VALUE"""),"Mercado") -> Mercado | C62: Mercado
A63: =IFERROR(__xludf.DUMMYFUNCTION("""COMPUTED_VALUE"""),"Supermercado") -> Supermercado | C63: Supermercado
A64: =IFERROR(__xludf.DUMMYFUNCTION("""COMPUTED_VALUE"""),"Tipo de calle") -> Tipo de calle | B64: =IFERROR(__xludf.DUMMYFUNCTION("""COMPUTED_VALUE"""),"Calle Local") -> Calle Local | C64: Tipo de calle
A65: =IFERROR(__xludf.DUMMYFUNCTION("""COMPUTED_VALUE"""),"SUBSECCIÓN TERRENO") -> SUBSECCIÓN TERRENO | C65: SUBSECCIÓN TERRENO
A66: =IFERROR(__xludf.DUMMYFUNCTION("""COMPUTED_VALUE"""),"Vistas") -> Vistas | B66: =IFERROR(__xludf.DUMMYFUNCTION("""COMPUTED_VALUE"""),"Paisaje Urbano") -> Paisaje Urbano | C66: Vistas
A67: =IFERROR(__xludf.DUMMYFUNCTION("""COMPUTED_VALUE"""),"Topografía") -> Topografía | B67: =IFERROR(__xludf.DUMMYFUNCTION("""COMPUTED_VALUE"""),"Plana") -> Plana | C67: Topografía
A68: =IFERROR(__xludf.DUMMYFUNCTION("""COMPUTED_VALUE"""),"Forma del Terreno") -> Forma del Terreno | B68: =IFERROR(__xludf.DUMMYFUNCTION("""COMPUTED_VALUE"""),"Regular") -> Regular | C68: Forma del Terreno
A69: =IFERROR(__xludf.DUMMYFUNCTION("""COMPUTED_VALUE"""),"Lados de terreno") -> Lados de terreno | B69: =IFERROR(__xludf.DUMMYFUNCTION("""COMPUTED_VALUE"""),4.0) -> 4 | C69: Lados de terreno
A70: =IFERROR(__xludf.DUMMYFUNCTION("""COMPUTED_VALUE"""),"Frentes a calle") -> Frentes a calle | B70: =IFERROR(__xludf.DUMMYFUNCTION("""COMPUTED_VALUE"""),1.0) -> 1 | C70: Frentes a calle
A71: =IFERROR(__xludf.DUMMYFUNCTION("""COMPUTED_VALUE"""),"Ubicación en Manzana") -> Ubicación en Manzana | B71: =IFERROR(__xludf.DUMMYFUNCTION("""COMPUTED_VALUE"""),"Medianero") -> Medianero | C71: Ubicación en Manzana
A72: =IFERROR(__xludf.DUMMYFUNCTION("""COMPUTED_VALUE"""),"Uso de Suelo") -> Uso de Suelo | C72: Uso de Suelo
A73: =IFERROR(__xludf.DUMMYFUNCTION("""COMPUTED_VALUE"""),"Tipo de uso de suelo") -> Tipo de uso de suelo | C73: Tipo de uso de suelo
A74: =IFERROR(__xludf.DUMMYFUNCTION("""COMPUTED_VALUE"""),"Densidad de poblacion") -> Densidad de poblacion | C74: Densidad de poblacion
A75: =IFERROR(__xludf.DUMMYFUNCTION("""COMPUTED_VALUE"""),"Densidad de urbanización") -> Densidad de urbanización | C75: Densidad de urbanización
A76: =IFERROR(__xludf.DUMMYFUNCTION("""COMPUTED_VALUE"""),"Servidumbres o Restricciones") -> Servidumbres o Restricciones | C76: Servidumbres o Restricciones
A77: =IFERROR(__xludf.DUMMYFUNCTION("""COMPUTED_VALUE"""),"SECCIÓN CARACTERISTICAS DEL INMUEBLE") -> SECCIÓN CARACTERISTICAS DEL INMUEBLE | C77: SECCIÓN CARACTERISTICAS DEL INMUEBLE
A78: =IFERROR(__xludf.DUMMYFUNCTION("""COMPUTED_VALUE"""),"SUBSECCION DATOS") -> SUBSECCION DATOS | C78: SUBSECCION DATOS
A79: =IFERROR(__xludf.DUMMYFUNCTION("""COMPUTED_VALUE"""),"Superficie de Terreno") -> Superficie de Terreno | B79: =IFERROR(__xludf.DUMMYFUNCTION("""COMPUTED_VALUE"""),98.0) -> 98 | C79: Superficie de Terreno
A80: =IFERROR(__xludf.DUMMYFUNCTION("""COMPUTED_VALUE"""),"Colindancia") -> Colindancia | C80: Colindancia
A81: =IFERROR(__xludf.DUMMYFUNCTION("""COMPUTED_VALUE"""),"Cantidad") -> Cantidad | C81: Cantidad
A82: =IFERROR(__xludf.DUMMYFUNCTION("""COMPUTED_VALUE"""),"Lindero con") -> Lindero con | C82: Lindero con
A83: =IFERROR(__xludf.DUMMYFUNCTION("""COMPUTED_VALUE"""),"Superficie de Construcciones") -> Superficie de Construcciones | C83: Superficie de Construcciones
A84: =IFERROR(__xludf.DUMMYFUNCTION("""COMPUTED_VALUE"""),"Superficie accesoria") -> Superficie accesoria | C84: Superficie accesoria
A85: =IFERROR(__xludf.DUMMYFUNCTION("""COMPUTED_VALUE"""),"Indiviso") -> Indiviso | C85: Indiviso
A86: =IFERROR(__xludf.DUMMYFUNCTION("""COMPUTED_VALUE"""),"SUBSECCION ESPACIOS") -> SUBSECCION ESPACIOS | C86: SUBSECCION ESPACIOS
A87: =IFERROR(__xludf.DUMMYFUNCTION("""COMPUTED_VALUE"""),"Estacionamientos descubiertos") -> Estacionamientos descubiertos | C87: Estacionamientos descubiertos
A88: =IFERROR(__xludf.DUMMYFUNCTION("""COMPUTED_VALUE"""),"Estacionamientos cubiertos") -> Estacionamientos cubiertos | C88: Estacionamientos cubiertos
A89: =IFERROR(__xludf.DUMMYFUNCTION("""COMPUTED_VALUE"""),"Recamaras") -> Recamaras | B89: =IFERROR(__xludf.DUMMYFUNCTION("""COMPUTED_VALUE"""),3.0) -> 3 | C89: Recamaras
A90: =IFERROR(__xludf.DUMMYFUNCTION("""COMPUTED_VALUE"""),"1/2 baño") -> 1/2 baño | B90: =IFERROR(__xludf.DUMMYFUNCTION("""COMPUTED_VALUE"""),1.0) -> 1 | C90: 1/2 baño
A91: =IFERROR(__xludf.DUMMYFUNCTION("""COMPUTED_VALUE"""),"Baños") -> Baños | B91: =IFERROR(__xludf.DUMMYFUNCTION("""COMPUTED_VALUE"""),1.0) -> 1 | C91: Baños
A92: =IFERROR(__xludf.DUMMYFUNCTION("""COMPUTED_VALUE"""),"Patio Servicio") -> Patio Servicio | B92: =IFERROR(__xludf.DUMMYFUNCTION("""COMPUTED_VALUE"""),1.0) -> 1 | C92: Patio Servicio
A93: =IFERROR(__xludf.DUMMYFUNCTION("""COMPUTED_VALUE"""),"Cuarto de Servicio") -> Cuarto de Servicio | C93: Cuarto de Servicio
A94: =IFERROR(__xludf.DUMMYFUNCTION("""COMPUTED_VALUE"""),"Terraza") -> Terraza | C94: Terraza
A95: =IFERROR(__xludf.DUMMYFUNCTION("""COMPUTED_VALUE"""),"Sotano") -> Sotano | C95: Sotano
A96: =IFERROR(__xludf.DUMMYFUNCTION("""COMPUTED_VALUE"""),"Patios") -> Patios | C96: Patios
A97: =IFERROR(__xludf.DUMMYFUNCTION("""COMPUTED_VALUE"""),"Otros Espacios") -> Otros Espacios | C97: Otros Espacios
A98: =IFERROR(__xludf.DUMMYFUNCTION("""COMPUTED_VALUE"""),"Descripción del inmueble") -> Descripción del inmueble | C98: Descripción del inmueble
A99: =IFERROR(__xludf.DUMMYFUNCTION("""COMPUTED_VALUE"""),"SUBSECCION INSTALACIONES ESPECIALES") -> SUBSECCION INSTALACIONES ESPECIALES | C99: SUBSECCION INSTALACIONES ESPECIALES
A100: =IFERROR(__xludf.DUMMYFUNCTION("""COMPUTED_VALUE"""),"Muebles cocina") -> Muebles cocina | C100: Muebles cocina
...

Sheet OPI Loc Com 
AF1: 3314189492 | AI1: 3336320507
O2: OPINIÓN DE VALOR | AF2: avaluos@avaluosyarquitectura.com.mx
AF3: avaluosyarquitectura2@gmail.com
AF4: www.avaluosyarquitectura.com.mx
A6: FOLIO | E6: =Query_Formato!B168 -> OPI-25-11-07-OF | AF6: Fecha: | AG6: =TODAY() -> 46202
A8: TIPO DE PROPIEDAD: | Z8: SOLICITANTE: | AA8: =Query_Formato!B156 -> Federico Arellano
A10: UBICACIÓN: | E10: =Query_Formato!B9 -> Pascal 2164 Colonia San Elias Guadalajara Jalisco 44240 | Z10: PROPIETARIO:
A12: =VLOOKUP("1.jp*g",Fotos!$A$2:$E399,5,FALSE) | W12: =VLOOKUP("2.jp*g",Fotos!$A$2:$E399,5,FALSE)
A33: RESUMEN
F34: VALORES DE VENTA SEGUN ANALISIS DE MERCADO DE VENTAS
A36: VALOR VENTA ESTIMADO PROMEDIO | N36: VALOR DE RENTA ESTIMADO PROMEDIO FACTORIZADO | AB36: REPRESENTATIVA DEL VALOR FÍSICO
A38: MÁXIMO sugerido | D38: =D40*1.1 -> #DIV/0! | N38: MÁXIMO | Q38: =Q40*1.1 -> #DIV/0! | AB38: TERRENO | AI38: =AP111 -> #DIV/0!
AB39: CONSTRUCCIONES | AI39: =AP123 -> #DIV/0!
A40: MEDIO o justo | D40: =ROUND(AJ200,-3) -> #DIV/0! | N40: MEDIO | Q40: =ROUND(AI149,-3) -> #DIV/0! | AB40: CONSTR. ACCESORIAS | AI40: =AP140 -> #DIV/0!
A42: MÍNIMO sugerido | D42: =D40*0.9 -> #DIV/0! | N42: MÍNIMO | Q42: =Q40*0.9 -> #DIV/0! | AB42: INSTALACIONES ACCESORIAS | AI42: =AN141
AI43: tot | AJ43: =SUM(AI38:AI43) -> #DIV/0!
A46: UNIDADES RENTABLES | K46: =AG87 | N46: TASA RENTA ANUAL SEGUN VALOR DE VENTA | W46: =AR149*10 -> 0.08 | AB46: CALIFICA CRÉDITO
A48: NIVELES | I48: =AK84 | N48: ESTADO DE CONSERVACIÓN | X48: =V87
A49: NIVEL UBICACIÓN | H49: =AN84 | N49: EDAD PONDERADA APROX | W49: =A87 -> 2026 | AB49: PLUSVALÍA ANUAL ESTIMADA
A50: TERRENO | H50: =C111 -> 0 | N50: EDAD REMANENTE | W50: =I87 -> -1966 | AB50: CERCANÍA
A51: CONSTRUCCIONES | H51: =K123 -> 0 | N51: AVANCE DE OBRA | W51: =AL87 -> 1 | AB51: DEMANDA DE LA ZONA
A52: DIFERENCIA ÷ VALOR DE VENTA Y CAPITALIZACIÓN DE RENTA | AB52: DIFERENCIA ÷ VALOR DE LAS CONSTRUCCIONES Y VALOR DE MERCADO DE LA PROPIEDAD
A54: =AJ144/AJ146/100 -> #DIV/0! | AB54: =$AR$144 -> #DIV/0!
A55: ESTO QUIERE DECIR QUE AL VENDER LA PROPIEDAD EXISTE UNA | AB55: ESTO QUIERE DECIR QUE AL VENDER LA PROPIEDAD EXISTE UNA
E59: VALORES DE RENTA SEGUN ANALISIS DE MERCADO DE RENTAS
A61: VALOR VENTA ESTIMADO ANALISIS DE MERCADO | N61: VALOR RENTA ESTIMADO ANALISIS DE MERCADO | AB61: TASA RENTA ANUAL SEGUN VALOR DE RENTA | AK61: =AR150*10 -> #DIV/0!
A63: MÁXIMO sugerido | D63: =D65*1.1 -> #DIV/0! | N63: MÁXIMO sugerido | Q63: =Q65*1.1 -> #DIV/0! | AB63: COSTO RENTA X M2 | AK63: =AL242 -> #DIV/0!
A65: MEDIO o justo | D65: =AJ146 -> #DIV/0! | N65: MEDIO o justo | Q65: =AI150 -> #DIV/0! | AB65: AL VENDER LA PROPIEDAD TIENE
A67: MÍNIMO sugerido | D67: =D65*0.9 -> #DIV/0! | N67: MÍNIMO sugerido | Q67: =Q65*0.9 -> #DIV/0!
A70: ANTECEDENTES
A72: CUENTA PREDIAL: | S72: CLAVE CATASTRAL:
A75: OBJETO DEL ANÁLISIS: | X75: RÉGIMEN DE PROP:
A78: SERVICIOS: | K78: =+CONCATENATE(AS89," ",AT89,", ",AS90," ",AT90,", ",AS91," ",AT91,", ",AS92," ",AT92,", ",AS93," ",AT93,", ",AS94," ",AT94,", ",AS95," ",AT95,", ",AS96," ",AT96,", ",AS97," ",AT97,".", ) -> SERVICIOS BÁSICOS: , AGUA POTABLE: , DRENAJE: , ENERGÍA ELÉCTRICA: , GAS: , ALUMBRADO EXTERIOR: , LÍNEAS TELEFÓNICAS: , VIALIDADES: , TRANSPORTE: .
A81: CLASIFICACIÓN DE LA ZONA: | AR81: AÑO ACTUAL | AS81: =YEAR(TODAY()) -> 2026
V83: C.O.S. | X83: C.U.S. | AA83: Fr Min | AC83: M2 Min. Lote | AF83: N° Est. | AH83: % Edif. Zona | AK83: Niveles | AN83: Niv. Ubicación | AR83: AÑO CONSTR.
A84: USO DEL SUELO: | K84: =UPPER(CONCATENATE(VLOOKUP(F84,'catalogo 2'!L15:N113,2,0)," ",(VLOOKUP(F84,'catalogo 2'!L15:N113,3,0)))) -> #N/A | V84: =VLOOKUP(F84,'catalogo 2'!M5:AJ85,14,0) -> #N/A | X84: =VLOOKUP(F84,'catalogo 2'!M5:AJ85,16,0) -> #N/A | AA84: =VLOOKUP(F84,'catalogo 2'!M5:AJ85,11,0) -> #N/A | AC84: =VLOOKUP(F84,'catalogo 2'!M5:AJ85,10,0) -> #N/A | AF84: =VLOOKUP(F84,'catalogo 2'!M5:AJ85,18,0) -> #N/A | AR84: EDAD | AS84: =AS81-AS83 -> 2026
A86: EDAD APROX. | F86: VIDA ÚTIL | I86: ED. REMANENTE | M86: EDAD TIPO | R86: CALIDAD | V86: CONSERVACIÓN | AA86: PROYECTO: | AG86: UNID. RENTABLES | AL86: % EDIF. SUJETO
A87: =+AS84 -> 2026 | F87: =IF(OR(R87="MEDIO",R87="SUPERIOR",R87="LUJO"),70,60) -> 60 | I87: =IF(OR(R87="MEDIO",R87="SUPERIOR",R87="LUJO"),70,60)-A87 -> -1966 | AL87: 1
A89: MEDIDAS Y LINDEROS SEGÚN: | I89: Medición del terreno | X89: =VLOOKUP("3.jp*g",Fotos!$A$2:$E399,5,FALSE) | AS89: SERVICIOS BÁSICOS:
AS90: AGUA POTABLE:
A91: Norte | AS91: DRENAJE:
A92: =IF($A$91="norte","Sur","Sureste") -> Sur | AS92: ENERGÍA ELÉCTRICA:
A93: =IF($A$91="norte","Este","Noroeste") -> Este | AS93: GAS:
A94: =IF($A$91="norte","Oeste","Suroeste") -> Oeste | AS94: ALUMBRADO EXTERIOR:
AS95: LÍNEAS TELEFÓNICAS:
A96: DESCRIPCIÓN DEL INMUEBLE | AS96: VIALIDADES:
AS97: TRANSPORTE:
A104: AVALÚO FÍSICO
C105: A) DEL TERRENO: | P105: LOTE TIPO: | Q105: VARIABLE
A106: FRACC. | C106: SUPERFICIE: | G106: VALOR UNITARIO | K106: FACTORES DE EFICIENCIA DE SUELO: | AC106: V. TERRENO | AG106: INDIVISO: | AJ106: VALOR
K107: ZONA | M107: UBICACIÓN | P107: FRENTE | R107: FORMA | T107: SUPERFICIE | X107: OTRO | Z107: FAC.RE. | AC107: RESULTANTE: | AJ107: RESULTANTE:
A108: 1 | K108: 1 | M108: 1 | P108: 1 | R108: 1 | T108: 1 | X108: 1 | Z108: =ROUND(K108*M108*P108*R108*T108*X108,2) -> 1 | AC108: =+Z108*G108 -> 0 | AG108: 1 | AJ108: =C108*AC108*AG108 -> 0
A109: 2 | C109: 0 | G109: 1 | K109: 1 | M109: 1 | P109: 1 | R109: 1 | T109: 1 | X109: 1 | Z109: =ROUND(K109*M109*P109*R109*T109*X109,2) -> 1 | AC109: =+Z109*G109 -> 1 | AG109: 1 | AJ109: =+AC109*C109*AG109 -> 0
A110: 3 | G110: 0 | AC110: =+Z110*G110 -> 0 | AG110: 1 | AJ110: =+AC110*C110*AG110 -> 0
A111: T | C111: =SUM(C108:F110) -> 0 | G111: OTRO: | AH111: VALOR DEL TERRENO: | AJ111: =SUM(AJ108:AO110) -> 0 | AP111: =AJ111/$AJ$142 -> #DIV/0! | AR111: MOVER EDAD MANUALMENTE CUANDO HAY MEJORAS O AMPLIACIONES
C113: B) DE LAS CONSTRUCCIONES: | P113: VALOR NUEVO | T113: DEMÉRITO: | AC113: VALOR | AG113: INDIVISO: | AJ113: VALOR
A114: TIPO: | C114: DESCRIPCIÓN | K114: SUPERFICIE: | T114: CONSERV | X114: PROYECTO | Z114: EDAD | AC114: USADO | AJ114: RESULTANTE: | AR114: =+F87 -> 60 | AS114: EDAD | AT114: REMANENTE
A115: I.- | P115: 18000 | T115: 0.85 | X115: 1 | Z115: =IF(AU115<0.2,"0.20",AU115) -> 0.20 | AC115: =Z115*X115*T115*P115 -> 3060 | AG115: =AG108 -> 1 | AJ115: =K115*AC115*AG115 -> 0 | AR115: 70 | AS115: =+A87 -> 2026 | AT115: =AR114-AS115 -> -1966 | AU115: =ROUND(((0.1*AR114)+(0.9*AT115))/AR114,2) -> -29.39
A116: II.- | P116: 1 | T116: 0.85 | X116: 1 | Z116: =IF(AU116<0.2,"0.20",AU116) -> 0.20 | AC116: =Z116*X116*T116*P116 -> 0.17 | AG116: 1 | AJ116: =K116*AC116*AG116 -> 0 | AR116: =+AR114 -> 60 | AS116: =+AS115 -> 2026 | AT116: =AR116-AS116 -> -1966 | AU116: =ROUND(((0.1*AR116)+(0.9*AT116))/AR116,2) -> -29.39
A117: III.- | P117: 1 | T117: 1 | X117: 1 | Z117: =IF(AU117<0.2,"0.20",AU117) -> 0.20 | AC117: =Z117*X117*T117*P117 -> 0.2 | AG117: 1 | AJ117: =K117*AC117*AG117 -> 0 | AR117: =+AR116 -> 60 | AS117: =+AS116 -> 2026 | AT117: =AR117-AS117 -> -1966 | AU117: =ROUND(((0.1*AR117)+(0.9*AT117))/AR117,2) -> -29.39
A118: IV.- | K118: 0 | P118: 0 | T118: 1 | X118: 1 | Z118: =IF(AU118<0.6,"0.60",AU118) -> 0.60 | AC118: =Z118*X118*T118*P118 -> 0 | AG118: 1 | AJ118: =K118*AC118*AG118 -> 0 | AR118: =+AR117 -> 60 | AS118: =+AS117 -> 2026 | AT118: =AR118-AS118 -> -1966 | AU118: =ROUND(((0.1*AR118)+(0.9*AT118))/AR118,2) -> -29.39
A119: V.- | K119: 0 | P119: 0 | T119: 1 | X119: 1 | Z119: =IF(AU119<0.6,"0.60",AU119) -> 0.60 | AC119: =Z119*X119*T119*P119 -> 0 | AG119: 1 | AJ119: =K119*AC119*AG119 -> 0 | AR119: =+AR118 -> 60 | AS119: =+AS118 -> 2026 | AT119: =AR119-AS119 -> -1966 | AU119: =ROUND(((0.1*AR119)+(0.9*AT119))/AR119,2) -> -29.39
A120: VI.- | K120: 0 | P120: 0 | T120: 1 | X120: 1 | Z120: =IF(AU120<0.6,"0.60",AU120) -> 0.60 | AC120: =Z120*X120*T120*P120 -> 0 | AG120: 1 | AJ120: =K120*AC120*AG120 -> 0 | AR120: =+AR119 -> 60 | AS120: =+AS119 -> 2026 | AT120: =AR120-AS120 -> -1966 | AU120: =ROUND(((0.1*AR120)+(0.9*AT120))/AR120,2) -> -29.39
A121: VII.- | K121: 0 | P121: 0 | T121: 1 | X121: 1 | Z121: =IF(AU121<0.6,"0.60",AU121) -> 0.60 | AC121: =Z121*X121*T121*P121 -> 0 | AG121: 1 | AJ121: =K121*AC121*AG121 -> 0 | AR121: =+AR120 -> 60 | AS121: =+AS120 -> 2026 | AT121: =AR121-AS121 -> -1966 | AU121: =ROUND(((0.1*AR121)+(0.9*AT121))/AR121,2) -> -29.39
A122: VIII.- | K122: 0 | P122: 0 | T122: 1 | X122: 1 | Z122: =IF(AU122<0.6,"0.60",AU122) -> 0.60 | AC122: =Z122*X122*T122*P122 -> 0 | AG122: 1 | AJ122: =K122*AC122*AG122 -> 0 | AR122: =+AR121 -> 60 | AS122: =+AS121 -> 2026 | AT122: =AR122-AS122 -> -1966 | AU122: =ROUND(((0.1*AR122)+(0.9*AT122))/AR122,2) -> -29.39
C123: TOTAL: | K123: =SUM(K115:K122) -> 0 | AH123: VALOR DE LAS CONSTRUCCIONES: | AJ123: =SUM(AJ115:AJ122) -> 0 | AP123: =AJ123/$AJ$142 -> #DIV/0!
AR124: MOVER EDAD MANUALMENTE CUANDO HAY MEJORAS O AMPLIACIONES
C125: C)INSTALACIONES ADICIONALES, ACCESORIAS O ESPECIALES:
A126: CONCEPTO: | J126: CANTIDAD: | M126: UNIDAD: | P126: VALOR | T126: DEMÉRITO: | AC126: VALOR | AG126: INDIVISO: | AJ126: VALOR
P127: NUEVO | T127: CONSERVACIÓN | Y127: EDAD | AC127: USADO | AJ127: RESULTANTE: | AR127: NUEVA | AS127: EDAD | AT127: REMANENTE
A128: I.- | T128: 0.95 | Y128: =+AU128 -> 0.73 | AC128: =P128*T128*Y128 -> 0 | AG128: 1 | AJ128: =J128*AC128*AG128 -> 0 | AR128: 50 | AS128: 15 | AT128: =AR128-AS128 -> 35 | AU128: =ROUND(((0.1*AR128)+(0.9*AT128))/AR128,2) -> 0.73
A129: II.- | T129: 1 | Y129: =+AU129 -> 0.76 | AC129: =P129*T129*Y129 -> 0 | AG129: 1 | AJ129: =J129*AC129*AG129 -> 0 | AR129: 45 | AS129: 12 | AT129: =AR129-AS129 -> 33 | AU129: =ROUND(((0.1*AR129)+(0.9*AT129))/AR129,2) -> 0.76
A130: III.- | T130: 1 | Y130: =+AU130 -> 0.76 | AC130: =P130*T130*Y130 -> 0 | AG130: 1 | AJ130: =J130*AC130*AG130 -> 0 | AR130: 45 | AS130: =+AS129 -> 12 | AT130: =AR130-AS130 -> 33 | AU130: =ROUND(((0.1*AR130)+(0.9*AT130))/AR130,2) -> 0.76
A131: IV.- | T131: 1 | Y131: =+AU131 -> 0.85 | AC131: =P131*T131*Y131 -> 0 | AG131: 1 | AJ131: =J131*AC131*AG131 -> 0 | AR131: 70 | AS131: =+AS130 -> 12 | AT131: =AR131-AS131 -> 58 | AU131: =ROUND(((0.1*AR131)+(0.9*AT131))/AR131,2) -> 0.85
A132: V.- | T132: 1 | Y132: 1 | AC132: =P132*T132*Y132 -> 0 | AG132: 1 | AJ132: =J132*AC132*AG132 -> 0 | AR132: 71 | AS132: =+AS131 -> 12 | AT132: =AR132-AS132 -> 59 | AU132: =ROUND(((0.1*AR132)+(0.9*AT132))/AR132,2) -> 0.85
A133: V.- | T133: 1 | Y133: =+AU133 -> 0.85 | AC133: =P133*T133*Y133 -> 0 | AG133: 1 | AJ133: =J133*AC133*AG133 -> 0 | AR133: 72 | AS133: =+AS132 -> 12 | AT133: =AR133-AS133 -> 60 | AU133: =ROUND(((0.1*AR133)+(0.9*AT133))/AR133,2) -> 0.85
A134: V.- | T134: 1 | Y134: =+AU134 -> 0.85 | AC134: =P134*T134*Y134 -> 0 | AG134: 1 | AJ134: =J134*AC134*AG134 -> 0 | AR134: 73 | AS134: =+AS133 -> 12 | AT134: =AR134-AS134 -> 61 | AU134: =ROUND(((0.1*AR134)+(0.9*AT134))/AR134,2) -> 0.85
A135: V.- | T135: 1 | Y135: =+AU135 -> 0.85 | AC135: =P135*T135*Y135 -> 0 | AG135: 1 | AJ135: =J135*AC135*AG135 -> 0 | AR135: 74 | AS135: =+AS134 -> 12 | AT135: =AR135-AS135 -> 62 | AU135: =ROUND(((0.1*AR135)+(0.9*AT135))/AR135,2) -> 0.85
A136: V.- | T136: 1 | Y136: =+AU136 -> 0.86 | AC136: =P136*T136*Y136 -> 0 | AG136: 1 | AJ136: =J136*AC136*AG136 -> 0 | AR136: 75 | AS136: =+AS135 -> 12 | AT136: =AR136-AS136 -> 63 | AU136: =ROUND(((0.1*AR136)+(0.9*AT136))/AR136,2) -> 0.86
A137: V.- | T137: 1 | Y137: =+AU137 -> 0.86 | AC137: =P137*T137*Y137 -> 0 | AG137: 1 | AJ137: =J137*AC137*AG137 -> 0 | AR137: 76 | AS137: =+AS136 -> 12 | AT137: =AR137-AS137 -> 64 | AU137: =ROUND(((0.1*AR137)+(0.9*AT137))/AR137,2) -> 0.86
A138: V.- | T138: 1 | Y138: =+AU138 -> 0.86 | AC138: =P138*T138*Y138 -> 0 | AG138: 1 | AJ138: =J138*AC138*AG138 -> 0 | AR138: 77 | AS138: =+AS137 -> 12 | AT138: =AR138-AS138 -> 65 | AU138: =ROUND(((0.1*AR138)+(0.9*AT138))/AR138,2) -> 0.86
A139: V.- | T139: 1 | Y139: =+AU139 -> 0.86 | AC139: =P139*T139*Y139 -> 0 | AG139: 1 | AJ139: =J139*AC139*AG139 -> 0 | AR139: 78 | AS139: =+AS138 -> 12 | AT139: =AR139-AS139 -> 66 | AU139: =ROUND(((0.1*AR139)+(0.9*AT139))/AR139,2) -> 0.86
AI140: VALOR DE LAS INST. ESPECIALES: | AJ140: =SUM(AJ128:AO139) -> 0 | AP140: =AJ140/$AJ$142 -> #DIV/0!
A142: INFORMACIÓN PROPORCIONADA POR: | AA142: VALOR FÍSICO O DIRECTO: | AJ142: =SUM(AJ111,AJ123,AJ140) -> 0 | AR142: =AJ145/K123 -> #DIV/0! | AS142: RANGO A BUSCAR
A143: SUPERFICIES
A144: DE TERRENO SEGÚN: | Q144: V.-CONCLUSIONES: | AI144: VALOR POR COMPARACIÓN: | AJ144: =AJ200 -> #DIV/0! | AR144: =+(AJ144-AJ145)/AJ144 -> #DIV/0! | AS144: DIFERENCIA FÍSICO/MERCADO
A145: CONSTRUCCIÓN SEGÚN: | AI145: VALOR FÍSICO O DIRECTO ACTUAL: | AJ145: =AJ142 -> 0
AI146: POR VALOR DE CAPITALIZACIÓN DE RENTA COMPARABLE: | AJ146: =AJ258 -> #DIV/0! | AR146: =AI148/K123 -> #DIV/0! | AS146: precio x m2
A148: NOTA IMPORTANTE: ESTE ANÁLISIS DE MERCADO NO CUMPLE CON EL FORMATO DE ELABORACIÓN DE AVALÚOS AUTORIZADO POR LA C.N.B. y de V. En la Circular No.-1462 De FEBRERO 14 Del 2000 DEBIDO A QUE ES UN INSTRUMENTO DE NEGOCIACIÓN Y DECISIÓN EN UNA OPERACIÓN DE COMPRA VENTA Y NO UN CERTIFICADO DE VALOR DE USO ABIERTO (NO ES EL VALOR CATASTRAL O DE DACIÓN EN PAGO) | AH148: VALOR COMERCIAL ESTIMADO: | AI148: =ROUND(AJ144,-3) -> #DIV/0!
AH149: VALOR ESTIMADO DE RENTA POR FACTOR: | AI149: =AJ144*AR149 -> #DIV/0! | AR149: 0.008 | AS149: FACTOR PARA RENTA
AH150: VALOR ESTIMADO DE RENTA POR COMPARACIÓN: | AI150: =+AJ257 -> #DIV/0! | AR150: =AI150/AJ146 -> #DIV/0! | AS150: FACTOR SOBRE ANALISIS DE RENTAS
Q151: =AS381 -> #DIV/0!
Q152: SE ESTIMA QUE EL VALOR COMERCIAL DEL INMUEBLE SEA IGUAL AL OBTENIDO POR EL AVALÚO DE MERCADO.
P154: ARQ. MVII. PEDRO VERGARA ESPINOSA
P155: CÉDULA FEDERAL 5685855 | V155: CÉDULA ESTATAL100795
A157: PREMISAS
A158: A) NO FUE MATERIA DE ESTE ANÁLISIS EL VERIFICAR LA PROPIEDAD LEGAL, NI LA EXISTENCIA DE RESERVAS DE DOMINIO O GRAVÁMENES SOBRE EL INMUEBLE, ASÍ COMO ALGÚN PROBLEMA EN CUANTO A SUS LINDEROS
A160: B) QUE LOS DATOS APORTADOS POR TERCERAS PERSONAS SON CIERTOS Y CORRECTOS.
A161: C) QUE EL VALUADOR NO TIENE NINGÚN INTERÉS MANIFIESTO SOBRE EL INMUEBLE.
A162: D) QUE NO SE HAN DESCARTADO NI SOBREESTIMADO DATOS IMPORTANTES.
...

Sheet OPI Terreno
AF1: 3314189492 | AI1: 3336320507
O2: OPINIÓN DE VALOR | AF2: avaluos@avaluosyarquitectura.com.mx
AF3: avaluosyarquitectura2@gmail.com
AF4: www.avaluosyarquitectura.com.mx
A6: FOLIO | E6: =Query_Formato!B168 -> OPI-25-11-07-OF | AF6: Fecha: | AG6: =TODAY() -> 46202
A8: TIPO DE PROPIEDAD: | Y8: SOLICITANTE: | Z8: =Query_Formato!B156 -> Federico Arellano
A10: UBICACIÓN: | D10: =Query_Formato!B9 -> Pascal 2164 Colonia San Elias Guadalajara Jalisco 44240 | Y10: PROPIETARIO:
A12: =VLOOKUP("1.jp*g",Fotos!$A$2:$E395,5,FALSE) | V12: =VLOOKUP("2.jp*g",Fotos!$A$2:$E395,5,FALSE)
A33: RESUMEN
A35: VALOR VENTA ESTIMADO PROMEDIO SOLO TERRENO | N35: VALOR VENTA ESTIMADO PROMEDIO CON CONSTRUCCIONES | AB35: VALOR VENTA ESTIMADO PROMEDIO CON CONSTRUCCIONES Y C. ACCESORIAS
A37: MÁXIMO sugerido | D37: =D39*1.1 -> #VALUE! | N37: MÁXIMO | Q37: =IF(EXACT(Q39, "N/A"), Q39, Q39*1.1) -> N/A | AB37: MÁXIMO sugerido | AE37: =IF(EXACT(AE39, "N/A"), AE39, AE39*1.1) -> N/A
A39: MEDIO o justo | D39: =ROUND(AI150,-3) -> #VALUE! | N39: MEDIO | Q39: =IF(K115=0, "N/A", ROUND(AJ111+AJ123+AJ148, -3)) -> N/A | AB39: MEDIO o justo | AE39: =IF(J145=0, "N/A", ROUND(AJ111+AJ123+AJ145+AJ148, -3)) -> N/A
A41: MÍNIMO sugerido | D41: =D39*0.9 -> #VALUE! | N41: MÍNIMO | Q41: =IF(EXACT(Q39, "N/A"), Q39, Q39*0.9) -> N/A | AB41: MÍNIMO sugerido | AE41: =IF(EXACT(AE39, "N/A"), AE39, AE39*0.9) -> N/A
A45: FORMA | N45: USO DE SUELO | T45: =UPPER(K85) -> HABITACIONAL DENSIDAD MÍNIMA UNIFAMILIAR | AB45: CALIFICA CRÉDITO
AB46: para bancos, infonavit, fovisste
A47: TOPOGRAFÍA | N47: UBICACIÓN EN MANZANA | R47: =V92
A49: FRENTES A CALLE | G49: =Query_Formato!B70 -> 1 | N49: VISTAS | AB49: PLUSVALÍA ANUAL
A51: SUP. TERRENO | I51: =G111 -> 0 | N51: TIPO DE TERRENO | AB51: CERCANÍA
A53: SUP. CONSTRUCCIONES | I53: =K123 -> 0 | N53: NUM. LADOS | S53: =Query_Formato!B69 -> 4 | AB53: DEMANDA DE LA ZONA
A54: vendibles
N55: VALOR RENTA ESTIMADO CON CONSTRUCCIONES
A56: TASA RENTA ANUAL | I56: =(AP152*10)/1 -> 0.04
N57: MÁXIMO | Q57: =Q59*1.1 -> #DIV/0!
A58: VALOR ESTIMADO POR M2 TERRENO | I58: =AC108 -> #DIV/0!
N59: MEDIO | Q59: =AJ152 -> #DIV/0!
N61: MÍNIMO | Q61: =Q59*0.9 -> #DIV/0!
A73: CARACTERÍSTICAS URBANAS Y DEL INMUEBLE
A75: CUENTA PREDIAL: | S75: CLAVE CATASTRAL:
A77: OBJETO DEL ANÁLISIS: | X77: RÉGIMEN DE PROP:
A79: SERVICIOS: | K79: =+CONCATENATE(AQ90," ",AR90,", ",AQ91," ",AR91,", ",AQ92," ",AR92,", ",AQ93," ",AR93,", ",AQ94," ",AR94,", ",AQ95," ",AR95,", ",AQ96," ",AR96,", ",AQ97," ",AR97,", ",AQ98," ",AR98,".", ) -> SERVICIOS BÁSICOS: , AGUA POTABLE: , DRENAJE: , ENERGÍA ELÉCTRICA: , GAS: , ALUMBRADO EXTERIOR: , LÍNEAS TELEFÓNICAS: , VIALIDADES: , TRANSPORTE: .
A82: CLASIFICACIÓN DE LA ZONA:
V84: C.O.S. | X84: C.U.S. | AA84: Fr Min | AC84: M2 Min. Lote | AF84: N° Est. | AH84: % Edif. Zona | AK84: % EDIF. SUJETO | AP84: AÑO DE CONSTR. | AQ84: 1995
A85: USO DEL SUELO: | F85: H1-U | K85: =UPPER(CONCATENATE(VLOOKUP(F85,'catalogo 2'!L5:N103,2,0)," ",(VLOOKUP(F85,'catalogo 2'!L5:N103,3,0)))) -> HABITACIONAL DENSIDAD MÍNIMA UNIFAMILIAR | V85: =VLOOKUP(F85,'catalogo 2'!L4:AI84,14,0) -> 0.4 | X85: =VLOOKUP(F85,'catalogo 2'!L4:AI84,16,0) -> 0.8 | AA85: =VLOOKUP(F85,'catalogo 2'!L4:AI84,11,0) -> 20 | AC85: =VLOOKUP(F85,'catalogo 2'!L4:AI84,10,0) -> 600 m2 | AF85: =VLOOKUP(F85,'catalogo 2'!L4:AI84,18,0) -> 4
A87: EDAD APROX. | F87: VIDA ÚTIL | I87: ED. REMANENTE | M87: EDAD TIPO | R87: CALIDAD | V87: CONSERVACIÓN | AA87: TOPOGRAFIA | AH87: CLAVE | AL87: % EDIF.
A88: =YEAR(TODAY()) - AQ84 -> 31 | F88: 60 | I88: =+F88-A88 -> 29 | M88: =VLOOKUP(A88,'catalogo 2'!C113:F118,4) -> #N/A | AG88: =+CONCATENATE(VLOOKUP(M88,'catalogo 2'!E120:F125,2,FALSE),".",VLOOKUP('OPI Constr'!R80,'catalogo 2'!G120:H125,2,FALSE),".",VLOOKUP('OPI Constr'!V80,'catalogo 2'!I120:J128,2,FALSE),".",VLOOKUP('OPI Constr'!Z80,'catalogo 2'!L120:M129,2,FALSE)) -> #N/A | AO88: SELECCIONAR SERVICIOS DE LA ZONA
A90: MEDIDAS Y LINDEROS SEGÚN: | Z90: =VLOOKUP("3.jp*g",Fotos!$A$2:$E395,5,FALSE) | AQ90: SERVICIOS BÁSICOS:
AQ91: AGUA POTABLE:
A92: Norte | AQ92: DRENAJE:
A93: =IF($A$92="norte","Sur","Sureste") -> Sur | E93: =IF(E92<>"", E92, "") | AQ93: ENERGÍA ELÉCTRICA:
A94: =IF($A$92="norte","Este","Noroeste") -> Este | AQ94: GAS:
A95: =IF($A$92="norte","Oeste","Suroeste") -> Oeste | E95: =IF(E94<>"", E94, "") | AQ95: ALUMBRADO EXTERIOR:
AQ96: LÍNEAS TELEFÓNICAS:
A97: DESCRIPCIÓN DEL INMUEBLE | AQ97: VIALIDADES:
AQ98: TRANSPORTE:
A104: AVALÚO FÍSICO
C105: A) DEL TERRENO: | P105: LOTE TIPO: | Q105: VARIABLE
A106: FRACC. | C106: SECCIÓN DEL TERRENO | G106: SUPERFICIE M2 | K106: VALOR UNITARIO | L106: FACTORES DE EFICIENCIA DE SUELO: | AC106: V. X M2 TERRENO | AG106: INDIVISO: | AJ106: VALOR
L107: ZONA | N107: UBICA | P107: FRENTE | R107: FORMA | T107: SUPERFICIE | X107: TOPOGRAF. | Z107: FAC.RE. | AC107: RESULTANTE: | AJ107: RESULTANTE:
A108: 1 | K108: =+AL208 -> #DIV/0! | L108: 1 | N108: 1 | P108: 1 | R108: 1 | T108: 1 | X108: 1 | Z108: =ROUND(N108*L108*P108*R108*T108*X108,2) -> 1 | AC108: =+Z108*K108 -> #DIV/0! | AG108: 1 | AJ108: =G108*AC108*AG108 -> #DIV/0!
A109: 2 | K109: =+K108 -> #DIV/0! | L109: 1 | N109: 1 | P109: 1 | R109: 1 | T109: 1 | X109: 1 | Z109: =ROUND(N109*L109*P109*R109*T109*X109,2) -> 1 | AC109: =+Z109*K109 -> #DIV/0! | AG109: 1 | AJ109: =+AC109*G109*AG109 -> #DIV/0!
A110: 3 | K110: =+K109 -> #DIV/0! | L110: 1 | N110: 1 | P110: 1 | R110: 1 | T110: 1 | X110: 1 | Z110: =ROUND(N110*L110*P110*R110*T110*X110,2) -> 1 | AC110: =+Z110*K110 -> #DIV/0! | AG110: 1 | AJ110: =+AC110*G110*AG110 -> #DIV/0!
A111: T | G111: =SUM(G108:J110) -> 0 | K111: OTRO: | AC111: =AVERAGE(AC108:AF110) -> #DIV/0! | AG111: VALOR DEL TERRENO: | AJ111: =SUM(AJ108:AM110) -> #DIV/0! | AP111: MOVER EDAD MANUALMENTE CUANDO HAY MEJORAS O AMPLIACIONES
C113: B) DE LAS CONSTRUCCIONES: | N113: VALOR NUEVO | Q113: DEMÉRITO: | AC113: VALOR | AG113: INDIVISO: | AJ113: VALOR | BL113: COMENTARIOS: | BN113: A PESAR DE QUE SE TRATA DE UN LOTE EN CONDOMINIO HORIZONTAL, ESTE SE COMERCIALIZA COMO SI FUERA UN LOTE INDIVIDUAL.
A114: TIPO: | C114: DESCRIPCIÓN | K114: SUPERFICIE: | Q114: ACABADOS | T114: CONSERV | X114: PROYECTO | Z114: EDAD | AC114: USADO | AJ114: RESULTANTE: | AR114: REMANENTE | BL114: EJIDAL | BN114: LA PROPIEDAD NO ESTÁ REGULARIZADA (EJIDAL) POR LO QUE ESTÁ OPINION DE VALOR REFLEJA EL VALOR EN QUE SE COMERCIALIZAN.
A115: I.- | Q115: 1 | T115: 0.85 | X115: 1 | Z115: =IF(AS115<0.2,"0.20",AS115) -> 0.7 | AC115: =Z115*X115*T115*N115*Q115 -> 0 | AG115: =AG108 -> 1 | AJ115: =K115*AC115*AG115 -> 0 | AP115: 60 | AQ115: 20 | AR115: =AP115-AQ115 -> 40 | AS115: =ROUND(((0.1*AP115)+(0.9*AR115))/AP115,2) -> 0.7 | BL115: NORMAL | BN115: ='OPI Terreno'!A147 -> INFORMACIÓN PROPORCIONADA POR:
A116: II.- | Q116: 1 | T116: 0 | X116: 1 | Z116: =IF(AS116<0.2,"0.20",AS116) -> 1 | AC116: =Z116*X116*T116*N116*Q116 -> 0 | AG116: 1 | AJ116: =K116*AC116*AG116 -> 0 | AP116: 60 | AR116: =AP116-AQ116 -> 60 | AS116: =ROUND(((0.1*AP116)+(0.9*AR116))/AP116,2) -> 1 | BN116: SUPERFICIE DE TERRENO SEGÚN DATOS PROPORCIONADOS Y DE CONSTRUCCIÓN SEGÚN MEDIDAS.
A117: III.- | Q117: 1 | T117: 0 | X117: 1 | Z117: =IF(AS117<0.2,"0.20",AS117) -> 1 | AC117: =Z117*X117*T117*N117*Q117 -> 0 | AG117: 1 | AJ117: =K117*AC117*AG117 -> 0 | AP117: 60 | AR117: =AP117-AQ117 -> 60 | AS117: =ROUND(((0.1*AP117)+(0.9*AR117))/AP117,2) -> 1 | BF117: =AP117-AQ117 -> 60 | BG117: =ROUND(((0.1*AP117)+(0.9*BF117))/AP117,2) -> 1
A118: IV.- | Q118: 1 | T118: 0 | X118: 1 | Z118: =IF(AS118<0.2,"0.20",AS118) -> 1 | AC118: =Z118*X118*T118*N118*Q118 -> 0 | AG118: 1 | AJ118: =K118*AC118*AG118 -> 0 | AP118: 60 | AR118: =AP118-AQ118 -> 60 | AS118: =ROUND(((0.1*AP118)+(0.9*AR118))/AP118,2) -> 1 | BF118: =AP118-AQ118 -> 60 | BG118: =ROUND(((0.1*AP118)+(0.9*BF118))/AP118,2) -> 1
A119: V.- | Q119: 1 | T119: 0 | X119: 1 | Z119: =IF(AS119<0.2,"0.20",AS119) -> 1 | AC119: =Z119*X119*T119*N119*Q119 -> 0 | AG119: 1 | AJ119: =K119*AC119*AG119 -> 0 | AP119: 60 | AR119: =AP119-AQ119 -> 60 | AS119: =ROUND(((0.1*AP119)+(0.9*AR119))/AP119,2) -> 1 | BF119: =AP119-AQ119 -> 60 | BG119: =ROUND(((0.1*AP119)+(0.9*BF119))/AP119,2) -> 1
A120: VI.- | Q120: 1 | T120: 0 | X120: 1 | Z120: =IF(AS120<0.2,"0.20",AS120) -> 1 | AC120: =Z120*X120*T120*N120*Q120 -> 0 | AG120: 1 | AJ120: =K120*AC120*AG120 -> 0 | AP120: 60 | AR120: =AP120-AQ120 -> 60 | AS120: =ROUND(((0.1*AP120)+(0.9*AR120))/AP120,2) -> 1 | BF120: =AP120-AQ120 -> 60 | BG120: =ROUND(((0.1*AP120)+(0.9*BF120))/AP120,2) -> 1
A121: VII.- | Q121: 1 | T121: 0 | X121: 1 | Z121: =IF(AS121<0.2,"0.20",AS121) -> 1 | AC121: =Z121*X121*T121*N121*Q121 -> 0 | AG121: 1 | AJ121: =K121*AC121*AG121 -> 0 | AP121: 60 | AR121: =AP121-AQ121 -> 60 | AS121: =ROUND(((0.1*AP121)+(0.9*AR121))/AP121,2) -> 1 | BF121: =AP121-AQ121 -> 60 | BG121: =ROUND(((0.1*AP121)+(0.9*BF121))/AP121,2) -> 1
A122: VIII.- | Q122: 1 | T122: 0 | X122: 1 | Z122: =IF(AS122<0.2,"0.20",AS122) -> 1 | AC122: =Z122*X122*T122*N122*Q122 -> 0 | AG122: 1 | AJ122: =K122*AC122*AG122 -> 0 | AP122: 60 | AR122: =AP122-AQ122 -> 60 | AS122: =ROUND(((0.1*AP122)+(0.9*AR122))/AP122,2) -> 1 | BF122: =AP122-AQ122 -> 60 | BG122: =ROUND(((0.1*AP122)+(0.9*BF122))/AP122,2) -> 1
C123: TOTAL: | K123: =SUM(K115:K122) -> 0 | AH123: VALOR DE LAS CONSTRUCCIONES: | AJ123: =SUM(AJ115:AJ122) -> 0
AP124: MOVER EDAD MANUALMENTE CUANDO HAY MEJORAS O AMPLIACIONES
C125: C)INSTALACIONES ADICIONALES, ACCESORIAS O ESPECIALES:
A126: CONCEPTO: | J126: CANTIDAD: | M126: UNIDAD: | P126: VALOR | T126: DEMÉRITO: | AC126: VALOR | AG126: INDIVISO: | AJ126: VALOR
P127: NUEVO | T127: CONSERVACIÓN | Y127: EDAD | AC127: USADO | AJ127: RESULTANTE: | AR127: REMANENTE
A128: I.- | T128: 1 | Y128: =+AS129 -> 0.7 | AC128: =P128*T128*Y128 -> 0 | AG128: 1 | AJ128: =J128*AC128*AG128 -> 0 | AP128: 60 | AQ128: 20 | AR128: =AP128-AQ128 -> 40 | AS128: =ROUND(((0.1*AP128)+(0.9*AR128))/AP128,2) -> 0.7
A129: II.- | T129: 1 | Y129: =+AS130 -> 0.7 | AC129: =P129*T129*Y129 -> 0 | AG129: 1 | AJ129: =J129*AC129*AG129 -> 0 | AP129: =AP128 -> 60 | AQ129: 20 | AR129: =AP129-AQ129 -> 40 | AS129: =ROUND(((0.1*AP129)+(0.9*AR129))/AP129,2) -> 0.7
A130: III.- | Y130: =+AS131 -> 1 | AC130: =P130*T130*Y130 -> 0 | AG130: 1 | AJ130: =J130*AC130*AG130 -> 0 | AP130: =AP129 -> 60 | AR130: =AP129-AQ129 -> 40 | AS130: =ROUND(((0.1*AP129)+(0.9*AR130))/AP129,2) -> 0.7
A131: IV.- | Y131: =+BG131 | AC131: =P131*T131*Y131 -> 0 | AG131: 1 | AJ131: =J131*AC131*AG131 -> 0 | AP131: =AP130 -> 60 | AR131: =AP130-AQ130 -> 60 | AS131: =ROUND(((0.1*AP130)+(0.9*AR131))/AP130,2) -> 1
A132: V.- | Y132: =+BG132 | AC132: =P132*T132*Y132 -> 0 | AG132: 1 | AJ132: =J132*AC132*AG132 -> 0 | AP132: =AP131 -> 60
C133: TINA | T133: 1 | Y133: =+BG133 | AC133: =P133*T133*Y133 -> 0 | AG133: 1 | AJ133: =J133*AC133*AG133 -> 0
C134: TINA | T134: 1 | Y134: =+BG134 | AC134: =P134*T134*Y134 -> 0 | AG134: 1 | AJ134: =J134*AC134*AG134 -> 0
C135: TINA | T135: 1 | Y135: =+BG135 | AC135: =P135*T135*Y135 -> 0 | AG135: 1 | AJ135: =J135*AC135*AG135 -> 0
C136: TINA | T136: 1 | Y136: =+BG136 | AC136: =P136*T136*Y136 -> 0 | AG136: 1 | AJ136: =J136*AC136*AG136 -> 0
C137: TINA | T137: 1 | Y137: =+BG137 | AC137: =P137*T137*Y137 -> 0 | AG137: 1 | AJ137: =J137*AC137*AG137 -> 0
C138: TINA | T138: 1 | Y138: =+BG138 | AC138: =P138*T138*Y138 -> 0 | AG138: 1 | AJ138: =J138*AC138*AG138 -> 0
C139: TINA | T139: 1 | Y139: =+BG139 | AC139: =P139*T139*Y139 -> 0 | AG139: 1 | AJ139: =J139*AC139*AG139 -> 0
C140: TINA | T140: 1 | Y140: =+BG140 | AC140: =P140*T140*Y140 -> 0 | AG140: 1 | AJ140: =J140*AC140*AG140 -> 0
C141: TINA | T141: 1 | Y141: =+BG141 | AC141: =P141*T141*Y141 -> 0 | AG141: 1 | AJ141: =J141*AC141*AG141 -> 0
C142: TINA | T142: 1 | Y142: =+BG142 | AC142: =P142*T142*Y142 -> 0 | AG142: 1 | AJ142: =J142*AC142*AG142 -> 0
C143: TINA | T143: 1 | Y143: =+BG143 | AC143: =P143*T143*Y143 -> 0 | AG143: 1 | AJ143: =J143*AC143*AG143 -> 0
C144: TINA | T144: 1 | AJ144: =J144*AC144*AG144 -> 0
J145: =SUM(J128:L144) -> 0 | AH145: VALOR DE LAS INST. ESPECIALES: | AJ145: =SUM(AJ128:AM144) -> 0 | BL145: ='OPI Terreno'!AG108*'OPI Terreno'!C108 -> 0 | BN145: SUP. PRIVATIVA
A147: INFORMACIÓN PROPORCIONADA POR: | AA147: VALOR FÍSICO O DIRECTO: | AJ147: =SUM(AJ111,AJ123,AJ145) -> #DIV/0!
A148: SUPERFICIES | Y148: FACTOR COMERCIAL DE LAS CONSTRUCCIONES: | AH148: 0.2 | AJ148: =(AJ145+AJ123)*AH148 -> 0
A150: DE TERRENO SEGÚN: | Q150: V.-CONCLUSIONES: | AI150: VALOR POR COMPARACIÓN SOLO TERRENO: | AJ150: =+AJ214 -> #DIV/0!
A151: CONSTRUCCIÓN SEGÚN: | AI151: VALOR FÍSICO O DIRECTO ACTUAL TERRENO Y CONSTRUCCIONES: | AJ151: =AJ147+AJ148 -> #DIV/0!
A152: NOTA IMPORTANTE: ESTE ANÁLISIS DE MERCADO NO CUMPLE CON EL FORMATO DE ELABORACIÓN DE AVALÚOS AUTORIZADO POR LA C.N.B. y de V. En la Circular No.-1462 De FEBRERO 14 Del 2000 DEBIDO A QUE ES UN INSTRUMENTO DE NEGOCIACIÓN Y DECISIÓN EN UNA OPERACIÓN DE COMPRA VENTA Y NO UN CERTIFICADO DE VALOR DE USO ABIERTO (NO ES EL VALOR CATASTRAL O DE DACIÓN EN PAGO) | AI152: RENTA ESTIMADA: | AJ152: =AJ151*AP152 -> #DIV/0! | AP152: 0.004
R154: VALOR COMERCIAL ESTIMADO TERRENO Y CONSTRUCCIÓN: | AI154: =+AJ151 -> #DIV/0!
Q156: =AR364 -> #DIV/0!
Q157: SE ESTIMA QUE EL VALOR COMERCIAL DEL INMUEBLE SEA IGUAL AL OBTENIDO POR EL AVALÚO DE MERCADO.
N159: ARQ. MVII. PEDRO VERGARA ESPINOSA
N160: CÉDULA FEDERAL 5685855 | T160: CÉDULA ESTATAL100795
A171: PREMISAS
A172: A) NO FUE MATERIA DE ESTE ANÁLISIS EL VERIFICAR LA PROPIEDAD LEGAL, NI LA EXISTENCIA DE RESERVAS DE DOMINIO O GRAVÁMENES SOBRE EL INMUEBLE, ASÍ COMO ALGÚN PROBLEMA EN CUANTO A SUS LINDEROS
A174: B) QUE LOS DATOS APORTADOS POR TERCERAS PERSONAS SON CIERTOS Y CORRECTOS.
A175: C) QUE EL VALUADOR NO TIENE NINGÚN INTERÉS MANIFIESTO SOBRE EL INMUEBLE.
A176: D) QUE NO SE HAN DESCARTADO NI SOBREESTIMADO DATOS IMPORTANTES.
...

Sheet OPI Terreno Rta
AF1: 3314189492 | AI1: 3336320507
AF2: avaluos@avaluosyarquitectura.com.mx
O3: OPINIÓN DE VALOR | AF3: avaluosyarquitectura2@gmail.com
AF4: www.avaluosyarquitectura.com.mx
C7: FOLIO | G7: =Query_Formato!D169 | AA7: Fecha: | AD7: =TODAY() -> 46202
A9: OPINIÓN DE VALOR DE:
A11: UBICACIÓN: | J11: =Query_Formato!B9 -> Pascal 2164 Colonia San Elias Guadalajara Jalisco 44240
A14: SOLICITANTE:
A16: PROPIETARIO: | J16: =J14
A18: =Fotos!E1 -> Foto | T18: =Fotos!E2
AB65: SOLO TERRENO | AD65: =+AI161 -> #REF!
AB67: CON CONSTRUCCIONES | AD67: =+AJ119+AJ131 -> #REF!
AB69: CON CONSTRUCCIONES ACCESORIAS | AD69: =+AJ158 -> #REF!
A71: ANTECEDENTES
A73: SOLICITANTE: | K73: =J14
A75: UBICACIÓN: | K75: =J11 -> Pascal 2164 Colonia San Elias Guadalajara Jalisco 44240
A77: CUENTA PREDIAL: | K77: No proporcionado | S77: CLAVE CATASTRAL: | AA77: 070-01-71-00-414-006-000-00-00
A79: INMUEBLE: | K79: =J9
A80: PROPIETARIO: | K80: =J16
A82: OBJETO DEL ANÁLISIS: | K82: Estimar el Valor Comercial | X82: RÉGIMEN DE PROP: | AD82: Privada en condominio
A84: CARACTERÍSTICAS URBANAS Y DEL INMUEBLE
A86: SERVICIOS: | K86: =+CONCATENATE(AQ97," ",AR97,", ",AQ98," ",AR98,", ",AQ99," ",AR99,", ",AQ100," ",AR100,", ",AQ101," ",AR101,", ",AQ102," ",AR102,", ",AQ103," ",AR103,", ",AQ104," ",AR104,", ",AQ105," ",AR105,".", ) -> SERVICIOS BÁSICOS: , AGUA POTABLE: , DRENAJE: , ENERGÍA ELÉCTRICA: , GAS: , ALUMBRADO EXTERIOR: , LÍNEAS TELEFÓNICAS: , VIALIDADES: , TRANSPORTE: .
A89: CLASIFICACIÓN DE LA ZONA:
V91: C.O.S. | X91: C.U.S. | Z91: Fr Min | AC91: M2 Min. Lote | AF91: N° Est. | AQ91: 1995
A92: USO DEL SUELO: | K92: =UPPER(CONCATENATE(VLOOKUP(F91,'catalogo 2'!L6:N104,2,0)," ",(VLOOKUP(F91,'catalogo 2'!L6:N104,3,0)))) -> #REF! | V92: 0.8 | X92: 1.6 | Z92: 6 | AC92: 90 m2 | AF92: 1
A94: EDAD APROX. | F94: VIDA ÚTIL | I94: ED. REMANENTE | M94: EDAD TIPO | R94: CALIDAD | V94: CONSERVACIÓN | AA94: PROYECTO: | AH94: CLAVE | AL94: % EDIF.
A95: =YEAR(TODAY()) - AQ91 -> 31 | F95: 60 | I95: =+F95-A95 -> 29 | M95: =VLOOKUP(A95,'catalogo 2'!C128:F133,4) -> #REF! | AG95: =+CONCATENATE(VLOOKUP(M95,'catalogo 2'!E135:F140,2,FALSE),".",VLOOKUP('OPI Constr'!R94,'catalogo 2'!G135:H140,2,FALSE),".",VLOOKUP('OPI Constr'!V94,'catalogo 2'!I135:J143,2,FALSE),".",VLOOKUP('OPI Constr'!Z94,'catalogo 2'!L135:M144,2,FALSE)) -> #REF! | AO95: SELECCIONAR SERVICIOS DE LA ZONA
A97: MEDIDAS Y LINDEROS SEGÚN: | X97: =#REF! -> #REF! | AQ97: SERVICIOS BÁSICOS:
AQ98: AGUA POTABLE:
A99: Norte | AQ99: DRENAJE:
A100: =IF($A$99="norte","Sur","Sureste") -> Sur | E100: =IF(E99<>"", E99, "") | AQ100: ENERGÍA ELÉCTRICA:
A101: =IF($A$99="norte","Este","Noroeste") -> Este | AQ101: GAS:
A102: =IF($A$99="norte","Oeste","Suroeste") -> Oeste | E102: =IF(E101<>"", E101, "") | AQ102: ALUMBRADO EXTERIOR:
AQ103: LÍNEAS TELEFÓNICAS:
A104: DESCRIPCIÓN DEL INMUEBLE | AQ104: VIALIDADES:
AQ105: TRANSPORTE:
A112: AVALÚO FÍSICO
C113: A) DEL TERRENO: | P113: LOTE TIPO: | Q113: VARIABLE
A114: FRACC. | C114: SUPERFICIE: | G114: SUPERFICIE M2 | K114: VALOR UNITARIO | L114: FACTORES DE EFICIENCIA DE SUELO: | AC114: V. TERRENO | AG114: INDIVISO: | AJ114: VALOR
L115: ZONA | N115: UBICA | P115: FRENTE | R115: FORMA | T115: SUPERFICIE | X115: TOPOGRAF. | Z115: FAC.RE. | AC115: RESULTANTE: | AJ115: RESULTANTE:
A116: 1 | K116: =+AL206 -> #REF! | L116: 1 | N116: 1 | P116: 1 | R116: 1 | T116: 1 | X116: 1 | Z116: =ROUND(N116*L116*P116*R116*T116*X116,2) -> 1 | AC116: =+Z116*K116 -> #REF! | AG116: 1 | AJ116: =G116*AC116*AG116 -> #REF!
A117: 2 | K117: =+K116 -> #REF! | L117: 1 | N117: 1 | P117: 1 | R117: 1 | T117: 1 | X117: 1 | Z117: =ROUND(N117*L117*P117*R117*T117*X117,2) -> 1 | AC117: =+Z117*K117 -> #REF! | AG117: 1 | AJ117: =+AC117*G117*AG117 -> #REF!
A118: 3 | K118: =+K117 -> #REF! | L118: 1 | N118: 1 | P118: 1 | R118: 1 | T118: 1 | X118: 1 | Z118: =ROUND(N118*L118*P118*R118*T118*X118,2) -> 1 | AC118: =+Z118*K118 -> #REF! | AG118: 1 | AJ118: =+AC118*G118*AG118 -> #REF!
A119: T | G119: =SUM(G116:J118) -> 0 | K119: OTRO: | AH119: VALOR DEL TERRENO: | AJ119: =SUM(AJ116:AM118) -> #REF!
C121: B) DE LAS CONSTRUCCIONES: | P121: VALOR NUEVO | T121: DEMÉRITO: | AC121: VALOR | AG121: INDIVISO: | AJ121: VALOR | AX121: COMENTARIOS: | AZ121: A PESAR DE QUE SE TRATA DE UN LOTE EN CONDOMINIO HORIZONTAL, ESTE SE COMERCIALIZA COMO SI FUERA UN LOTE INDIVIDUAL.
A122: TIPO: | C122: DESCRIPCIÓN | K122: SUPERFICIE: | T122: CONSERV | X122: PROYECTO | Z122: EDAD | AC122: USADO | AJ122: RESULTANTE: | AR122: REMANENTE | AX122: EJIDAL | AZ122: LA PROPIEDAD NO ESTÁ REGULARIZADA (EJIDAL) POR LO QUE ESTÁ OPINION DE VALOR REFLEJA EL VALOR EN QUE SE COMERCIALIZAN.
A123: I.- | T123: 0.85 | X123: 1 | Z123: =+AS123 -> #DIV/0! | AC123: =Z123*X123*T123*P123 -> #DIV/0! | AG123: =AG116 -> 1 | AJ123: =K123*AC123*AG123 -> #DIV/0! | AR123: =AP123-AQ123 -> 0 | AS123: =ROUND(((0.1*AP123)+(0.9*AR123))/AP123,2) -> #DIV/0! | AX123: NORMAL | AZ123: ='OPI Terreno Rta'!A155 -> INFORMACIÓN PROPORCIONADA POR:
A124: II.- | T124: 0.85 | X124: 1 | Z124: =+AS124 -> #DIV/0! | AC124: =Z124*X124*T124*P124 -> #DIV/0! | AG124: 1 | AJ124: =K124*AC124*AG124 -> #DIV/0! | AR124: =AP124-AQ124 -> 0 | AS124: =ROUND(((0.1*AP124)+(0.9*AR124))/AP124,2) -> #DIV/0! | AZ124: SUPERFICIE DE TERRENO SEGÚN DATOS PROPORCIONADOS Y DE CONSTRUCCIÓN SEGÚN MEDIDAS.
A125: III.- | T125: 0 | X125: 1 | Z125: =+AS125 -> #DIV/0! | AC125: =Z125*X125*T125*P125 -> #DIV/0! | AG125: 1 | AJ125: =K125*AC125*AG125 -> #DIV/0! | AR125: =AP125-AQ125 -> 0 | AS125: =ROUND(((0.1*AP125)+(0.9*AR125))/AP125,2) -> #DIV/0!
A126: IV.- | T126: 0 | X126: 1 | Z126: =+AS126 -> #DIV/0! | AC126: =Z126*X126*T126*P126 -> #DIV/0! | AG126: 1 | AJ126: =K126*AC126*AG126 -> #DIV/0! | AR126: =AP126-AQ126 -> 0 | AS126: =ROUND(((0.1*AP126)+(0.9*AR126))/AP126,2) -> #DIV/0!
A127: V.- | T127: 1 | X127: 1 | Z127: =IF(AS127<0.6,"0.60",AS127) -> #DIV/0! | AC127: =Z127*X127*T127*P127 -> #DIV/0! | AG127: 1 | AJ127: =K127*AC127*AG127 -> #DIV/0! | AR127: =AP127-AQ127 -> 0 | AS127: =ROUND(((0.1*AP127)+(0.9*AR127))/AP127,2) -> #DIV/0!
A128: VI.- | T128: 1 | X128: 1 | Z128: =IF(AS128<0.6,"0.60",AS128) -> #DIV/0! | AC128: =Z128*X128*T128*P128 -> #DIV/0! | AG128: 1 | AJ128: =K128*AC128*AG128 -> #DIV/0! | AR128: =AP128-AQ128 -> 0 | AS128: =ROUND(((0.1*AP128)+(0.9*AR128))/AP128,2) -> #DIV/0!
A129: VII.- | T129: 1 | X129: 1 | Z129: =IF(AS129<0.6,"0.60",AS129) -> #DIV/0! | AC129: =Z129*X129*T129*P129 -> #DIV/0! | AG129: 1 | AJ129: =K129*AC129*AG129 -> #DIV/0! | AR129: =AP129-AQ129 -> 0 | AS129: =ROUND(((0.1*AP129)+(0.9*AR129))/AP129,2) -> #DIV/0!
A130: VIII.- | T130: 1 | X130: 1 | Z130: =IF(AS130<0.6,"0.60",AS130) -> #DIV/0! | AC130: =Z130*X130*T130*P130 -> #DIV/0! | AG130: 1 | AJ130: =K130*AC130*AG130 -> #DIV/0! | AR130: =AP130-AQ130 -> 0 | AS130: =ROUND(((0.1*AP130)+(0.9*AR130))/AP130,2) -> #DIV/0!
C131: TOTAL: | K131: =SUM(K123:K130) -> 0 | AH131: VALOR DE LAS CONSTRUCCIONES: | AJ131: =SUM(AJ123:AJ130) -> #DIV/0!
C133: C)INSTALACIONES ADICIONALES, ACCESORIAS O ESPECIALES:
A134: CONCEPTO: | J134: CANTIDAD: | M134: UNIDAD: | P134: VALOR | T134: DEMÉRITO: | AC134: VALOR | AG134: INDIVISO: | AJ134: VALOR
P135: NUEVO | T135: CONSERVACIÓN | Y135: EDAD | AC135: USADO | AJ135: RESULTANTE: | AR135: REMANENTE
A136: I.- | T136: 0.85 | Y136: =+AS136 -> #DIV/0! | AC136: =P136*T136*Y136 -> #DIV/0! | AG136: 1 | AJ136: =J136*AC136*AG136 -> #DIV/0! | AR136: =AP136-AQ136 -> 0 | AS136: =ROUND(((0.1*AP136)+(0.9*AR136))/AP136,2) -> #DIV/0!
A137: II.- | T137: 0.85 | Y137: =+AS137 -> #DIV/0! | AC137: =P137*T137*Y137 -> #DIV/0! | AG137: 1 | AJ137: =J137*AC137*AG137 -> #DIV/0! | AR137: =AP137-AQ137 -> 0 | AS137: =ROUND(((0.1*AP137)+(0.9*AR137))/AP137,2) -> #DIV/0!
A138: III.- | Y138: =+AS138 -> #DIV/0! | AC138: =P138*T138*Y138 -> #DIV/0! | AG138: 1 | AJ138: =J138*AC138*AG138 -> #DIV/0! | AR138: =AP138-AQ138 -> 0 | AS138: =ROUND(((0.1*AP138)+(0.9*AR138))/AP138,2) -> #DIV/0!
A139: IV.- | Y139: =+AS139 -> #DIV/0! | AC139: =P139*T139*Y139 -> #DIV/0! | AG139: 1 | AJ139: =J139*AC139*AG139 -> #DIV/0! | AR139: =AP139-AQ139 -> 0 | AS139: =ROUND(((0.1*AP139)+(0.9*AR139))/AP139,2) -> #DIV/0!
A140: V.- | Y140: 1 | AC140: =P140*T140*Y140 -> 0 | AG140: 1 | AJ140: =J140*AC140*AG140 -> 0 | AR140: 0 | AS140: =ROUND(((0.1*AP140)+(0.9*AR140))/AP140,2) -> #DIV/0!
C141: TINA | T141: 1 | Y141: =+AS141 -> #DIV/0! | AC141: =P141*T141*Y141 -> #DIV/0! | AG141: 1 | AJ141: =J141*AC141*AG141 -> #DIV/0! | AR141: =AP141-AQ141 -> 0 | AS141: =ROUND(((0.1*AP141)+(0.9*AR141))/AP141,2) -> #DIV/0!
C142: TINA | T142: 1 | Y142: =+AS142 -> #DIV/0! | AC142: =P142*T142*Y142 -> #DIV/0! | AG142: 1 | AJ142: =J142*AC142*AG142 -> #DIV/0! | AR142: =AP142-AQ142 -> 0 | AS142: =ROUND(((0.1*AP142)+(0.9*AR142))/AP142,2) -> #DIV/0!
C143: TINA | T143: 1 | Y143: =+AS143 -> #DIV/0! | AC143: =P143*T143*Y143 -> #DIV/0! | AG143: 1 | AJ143: =J143*AC143*AG143 -> #DIV/0! | AR143: =AP143-AQ143 -> 0 | AS143: =ROUND(((0.1*AP143)+(0.9*AR143))/AP143,2) -> #DIV/0!
C144: TINA | T144: 1 | Y144: =+AS144 -> #DIV/0! | AC144: =P144*T144*Y144 -> #DIV/0! | AG144: 1 | AJ144: =J144*AC144*AG144 -> #DIV/0! | AR144: =AP144-AQ144 -> 0 | AS144: =ROUND(((0.1*AP144)+(0.9*AR144))/AP144,2) -> #DIV/0!
C145: TINA | T145: 1 | Y145: =+AS145 -> #DIV/0! | AC145: =P145*T145*Y145 -> #DIV/0! | AG145: 1 | AJ145: =J145*AC145*AG145 -> #DIV/0! | AR145: =AP145-AQ145 -> 0 | AS145: =ROUND(((0.1*AP145)+(0.9*AR145))/AP145,2) -> #DIV/0!
C146: TINA | T146: 1 | Y146: =+AS146 -> #DIV/0! | AC146: =P146*T146*Y146 -> #DIV/0! | AG146: 1 | AJ146: =J146*AC146*AG146 -> #DIV/0! | AR146: =AP146-AQ146 -> 0 | AS146: =ROUND(((0.1*AP146)+(0.9*AR146))/AP146,2) -> #DIV/0!
C147: TINA | T147: 1 | Y147: =+AS147 -> #DIV/0! | AC147: =P147*T147*Y147 -> #DIV/0! | AG147: 1 | AJ147: =J147*AC147*AG147 -> #DIV/0! | AR147: =AP147-AQ147 -> 0 | AS147: =ROUND(((0.1*AP147)+(0.9*AR147))/AP147,2) -> #DIV/0!
C148: TINA | T148: 1 | Y148: =+AS148 -> #DIV/0! | AC148: =P148*T148*Y148 -> #DIV/0! | AG148: 1 | AJ148: =J148*AC148*AG148 -> #DIV/0! | AR148: =AP148-AQ148 -> 0 | AS148: =ROUND(((0.1*AP148)+(0.9*AR148))/AP148,2) -> #DIV/0!
C149: TINA | T149: 1 | Y149: =+AS149 -> #DIV/0! | AC149: =P149*T149*Y149 -> #DIV/0! | AG149: 1 | AJ149: =J149*AC149*AG149 -> #DIV/0! | AR149: =AP149-AQ149 -> 0 | AS149: =ROUND(((0.1*AP149)+(0.9*AR149))/AP149,2) -> #DIV/0!
C150: TINA | T150: 1 | Y150: =+AS150 -> #DIV/0! | AC150: =P150*T150*Y150 -> #DIV/0! | AG150: 1 | AJ150: =J150*AC150*AG150 -> #DIV/0! | AR150: =AP150-AQ150 -> 0 | AS150: =ROUND(((0.1*AP150)+(0.9*AR150))/AP150,2) -> #DIV/0!
C151: TINA | T151: 1 | Y151: =+AS151 -> #DIV/0! | AC151: =P151*T151*Y151 -> #DIV/0! | AG151: 1 | AJ151: =J151*AC151*AG151 -> #DIV/0! | AR151: =AP151-AQ151 -> 0 | AS151: =ROUND(((0.1*AP151)+(0.9*AR151))/AP151,2) -> #DIV/0!
C152: TINA | T152: 1 | AJ152: =J152*AC152*AG152 -> 0 | AR152: =AP152-AQ152 -> 0 | AS152: =ROUND(((0.1*AP152)+(0.9*AR152))/AP152,2) -> #DIV/0!
AH153: VALOR DE LAS INST. ESPECIALES: | AJ153: =SUM(AJ136:AM152) -> #DIV/0! | AX153: ='OPI Terreno Rta'!AG116*'OPI Terreno Rta'!C116 -> 0 | AZ153: SUP. PRIVATIVA
A155: INFORMACIÓN PROPORCIONADA POR: | AA155: VALOR FÍSICO O DIRECTO: | AJ155: =SUM(AJ119,AJ131,AJ153) -> #REF!
A156: SUPERFICIES
A157: DE TERRENO SEGÚN: | Q157: V.-CONCLUSIONES: | AI157: VALOR POR COMPARACIÓN SOLO TERRENO: | AJ157: =+AJ212 -> #REF!
A158: CONSTRUCCIÓN SEGÚN: | AI158: VALOR FÍSICO O DIRECTO ACTUAL TERRENO Y CONSTRUCCIONES: | AJ158: =AJ155 -> #REF!
A159: NOTA IMPORTANTE: ESTE ANÁLISIS DE MERCADO NO CUMPLE CON EL FORMATO DE ELABORACIÓN DE AVALÚOS AUTORIZADO POR LA C.N.B. y de V. En la Circular No.-1462 De FEBRERO 14 Del 2000 DEBIDO A QUE ES UN INSTRUMENTO DE NEGOCIACIÓN Y DECISIÓN EN UNA OPERACIÓN DE COMPRA VENTA Y NO UN CERTIFICADO DE VALOR DE USO ABIERTO (NO ES EL VALOR CATASTRAL O DE DACIÓN EN PAGO)
AH161: VALOR COMERCIAL ESTIMADO SOLO TERRENO: | AI161: =+AJ157 -> #REF!
Q163: =A467 -> #REF!
Q164: SE ESTIMA QUE EL VALOR COMERCIAL DEL INMUEBLE SEA IGUAL AL OBTENIDO POR EL AVALÚO DE MERCADO.
N166: ARQ. MVII. PEDRO VERGARA ESPINOSA
N167: CÉDULA FEDERAL 5685855 | T167: CÉDULA ESTATAL100795
A169: PREMISAS
A170: A) NO FUE MATERIA DE ESTE ANÁLISIS EL VERIFICAR LA PROPIEDAD LEGAL, NI LA EXISTENCIA DE RESERVAS DE DOMINIO O GRAVÁMENES SOBRE EL INMUEBLE, ASÍ COMO ALGÚN PROBLEMA EN CUANTO A SUS LINDEROS
A172: B) QUE LOS DATOS APORTADOS POR TERCERAS PERSONAS SON CIERTOS Y CORRECTOS.
A173: C) QUE EL VALUADOR NO TIENE NINGÚN INTERÉS MANIFIESTO SOBRE EL INMUEBLE.
A174: D) QUE NO SE HAN DESCARTADO NI SOBREESTIMADO DATOS IMPORTANTES.
A175: E) EL PROCEDIMIENTO PARA ENCONTRAR EL VALOR Y SUS PARÁMETROS SON LOS COMUNES PARA ESTE TIPO DE DICTÁMENES.
A176: F) ESTE ANALISIS ES UN INSTRUMENTO DE NEGOCIACION Y DECISION EN UNA OPERACION DE COMPRA VENTA, Y NO UN CERTIFICADO DE VALOR DE USO ABIERTO.
A179: INVESTIGACIÓN DE MERCADO
C181: Tipo | H181: C A L L E: | O181: COLONIA/ZONA | U181: Edad | W181: C A R A C T E R Í S T I C A S: | AJ181: FUENTE/TELÉFONO
A182: 1 | C182: =+Mercado!C14 -> #REF! | H182: =+Mercado!F14 -> #REF! | O182: =+Mercado!E14 -> #REF! | U182: 0 | W182: =+Mercado!G14 -> #REF! | AJ182: =UPPER(CONCATENATE(Mercado!L14,", ",Mercado!M14)) -> #REF! | AR182: PU mercado | AS182: % | AU182: PU fisico | AV182: % | AX182: PU mercado | AY182: %
A183: 2 | C183: =+Mercado!C15 -> #REF! | H183: =+Mercado!F15 -> #REF! | O183: =+Mercado!E15 -> #REF! | U183: 0 | W183: =+PROPER(Mercado!G15) -> #REF! | AJ183: =UPPER(CONCATENATE(Mercado!L15,", ",Mercado!M15)) -> #REF! | AO183: T | AR183: =+AC116 -> #REF! | AS183: =+AR183/$AR$185 -> #REF! | AT183: Terreno | AU183: =+AJ119 -> #REF! | AV183: =+AU183/$AU$186 -> #REF! | AW183: Terreno | AX183: =+AU183 -> #REF! | AY183: =+AX183/$AX$186 -> #REF!
A184: 3 | C184: =+Mercado!C16 -> #REF! | H184: =+Mercado!F16 -> #REF! | O184: =+Mercado!E16 -> #REF! | U184: 0 | W184: =+PROPER(Mercado!G16) -> #REF! | AJ184: =UPPER(CONCATENATE(Mercado!L16,", ",Mercado!M16)) -> #REF! | AO184: C | AR184: =+AL206-AR183 -> #REF! | AS184: =+AR184/$AR$185 -> #REF! | AT184: Construcción | AU184: =+AJ131 -> #DIV/0! | AV184: =+AU184/$AU$186 -> #DIV/0! | AW184: Construcción | AX184: =+AJ212-AX183 -> #REF! | AY184: =+AX184/$AX$186 -> #REF!
A185: 4 | C185: =+Mercado!C17 -> #REF! | H185: =+Mercado!F17 -> #REF! | O185: =+Mercado!E17 -> #REF! | U185: 0 | W185: =+Mercado!G17 -> #REF! | AJ185: =UPPER(CONCATENATE(Mercado!L17,", ",Mercado!M17)) -> #REF! | AO185: tot | AR185: =SUM(AR183:AR184) -> #REF! | AS185: =+AR185/$AR$185 -> #REF! | AT185: Acabados Esp. | AU185: =+AJ153 -> #DIV/0! | AV185: =+AU185/$AU$186 -> #DIV/0! | AY185: =+AX185/$AX$186 -> #REF!
A186: 5 | C186: =+Mercado!C18 -> #REF! | H186: =+Mercado!F18 -> #REF! | O186: =+Mercado!E18 -> #REF! | U186: 0 | W186: =+Mercado!G18 -> #REF! | AJ186: =UPPER(CONCATENATE(Mercado!L18,", ",Mercado!M18)) -> #REF! | AT186: tot | AU186: =SUM(AU183:AU184) -> #REF! | AV186: =+AU186/$AU$186 -> #REF! | AX186: =SUM(AX183:AX184) -> #REF! | AY186: =+AX186/$AX$186 -> #REF!
...

Sheet OPI Rentas
AF1: 3314189492 | AI1: 3336320507
O2: OPINIÓN DE VALOR RENTA | AF2: avaluos@avaluosyarquitectura.com.mx
AF3: avaluosyarquitectura2@gmail.com
AF4: www.avaluosyarquitectura.com.mx
A6: FOLIO | E6: =Query_Formato!B168 -> OPI-25-11-07-OF | AF6: Fecha: | AG6: =TODAY() -> 46202
A8: TIPO DE PROPIEDAD: | Y8: SOLICITANTE: | Z8: =Query_Formato!B156 -> Federico Arellano
A10: UBICACIÓN: | E10: =Query_Formato!B9 -> Pascal 2164 Colonia San Elias Guadalajara Jalisco 44240 | Y10: PROPIETARIO:
A13: =VLOOKUP("1.jp*g",Fotos!$A$2:$E444,5,FALSE) | V13: =VLOOKUP("2.jp*g",Fotos!$A$2:$E444,5,FALSE)
A34: RESUMEN
A36: VALOR RENTA ESTIMADO PROMEDIO | N36: VALOR DE RENTA ESTIMADO PROMEDIO | AB36: REPRESENTATIVA DEL VALOR FÍSICO
A38: MÁXIMO sugerido | D38: =D40*1.1 -> #DIV/0! | N38: MÁXIMO | Q38: =Q40*1.1 -> #DIV/0! | AB38: TERRENO | AI38: =AN111 -> #DIV/0!
AB39: CONSTRUCCIONES | AI39: =AN123 -> #DIV/0!
A40: MEDIO o justo | D40: =ROUND(AJ161,3) -> #DIV/0! | N40: MEDIO | Q40: =ROUND(AI166,3) -> #DIV/0! | AB40: CONSTR. ACCESORIAS | AI40: =AN135 -> #DIV/0!
A42: MÍNIMO sugerido | D42: =D40*0.9 -> #DIV/0! | N42: MÍNIMO | Q42: =Q40*0.9 -> #DIV/0! | AB42: INSTALACIONES ACCESORIAS | AI42: =AN157 -> #DIV/0!
AI43: tot | AJ43: =SUM(AI38:AI43) -> #DIV/0!
A46: UNIDADES RENTABLES | K46: =AD80 | N46: TASA RENTA ANUAL | W46: =(AP166*10)/1 -> 0.04 | AB46: CALIFICA CRÉDITO
A48: NIVELES | I48: =AK86 | N48: ESTADO DE CONSERVACIÓN | X48: =W86
A50: NIVEL UBICACIÓN | H50: =AG86 | N50: EDAD PONDERADA APROX | W50: =A86 -> 7 | AB50: PLUSVALÍA ANUAL
A52: TERRENO | I52: =C111 -> 0 | N52: EDAD REMANENTE | W52: =I86 -> 53 | AB52: CERCANÍA
A54: CONSTRUCCIONES | I54: =K123 -> 0 | N54: AVANCE DE OBRA | W54: =AJ83 | AB54: DEMANDA DE LA ZONA
A55: vendibles
A56: RESUMEN DE ESPACIOS
B58: RESUMEN ESPACIOS BÁSICOS | P58: ELEMENTOS ACCESORIOS | AC58: AMENIDADES DEL CONJUNTO
A59: =IF(B59<>"", IF((COUNTIFS($AP$92:$AP$109, "*"&B59&"*") + COUNTIFS($AR$92:$AR$109, "*"&B59&"*")) > 0, SUMIFS($AO$92:$AO$109, $AP$92:$AP$109, "*"&B59&"*") + SUMIFS($AQ$92:$AQ$109, $AR$92:$AR$109, "*"&B59&"*") + SUMIFS($AT$92:$AT$109, $AU$92:$AU$109, "*"&B59&"*") + SUMIFS($AV$92:$AV$109, $AW$92:$AW$109, "*"&B59&"*"), ""), "") | B59: ESTACIONAMIENTOS | M59: =J140 | O59: =+UPPER(C140)
A60: =IF(B60<>"", IF((COUNTIFS($AP$92:$AP$109, "*"&B60&"*") + COUNTIFS($AR$92:$AR$109, "*"&B60&"*")) > 0, SUMIFS($AO$92:$AO$109, $AP$92:$AP$109, "*"&B60&"*") + SUMIFS($AQ$92:$AQ$109, $AR$92:$AR$109, "*"&B60&"*") + SUMIFS($AT$92:$AT$109, $AU$92:$AU$109, "*"&B60&"*") + SUMIFS($AV$92:$AV$109, $AW$92:$AW$109, "*"&B60&"*"), ""), "") | B60: COCINA | M60: =J141 | O60: =+UPPER(C141)
A61: =IF(B61<>"", IF((COUNTIFS($AP$92:$AP$109, "*"&B61&"*") + COUNTIFS($AR$92:$AR$109, "*"&B61&"*")) > 0, SUMIFS($AO$92:$AO$109, $AP$92:$AP$109, "*"&B61&"*") + SUMIFS($AQ$92:$AQ$109, $AR$92:$AR$109, "*"&B61&"*"), ""), "") | B61: PATIO | M61: =J142 | O61: =+UPPER(C142)
A62: =IF(B62<>"", IF((COUNTIFS($AP$92:$AP$109, "*"&B62&"*") + COUNTIFS($AR$92:$AR$109, "*"&B62&"*")) > 0, SUMIFS($AO$92:$AO$109, $AP$92:$AP$109, "*"&B62&"*") + SUMIFS($AQ$92:$AQ$109, $AR$92:$AR$109, "*"&B62&"*") + SUMIFS($AT$92:$AT$109, $AU$92:$AU$109, "*"&B62&"*") + SUMIFS($AV$92:$AV$109, $AW$92:$AW$109, "*"&B62&"*"), ""), "") | B62: RECAMARAS | M62: =J143 | O62: =+UPPER(C143)
A63: =IF(B63<>"", IF((COUNTIFS($AP$92:$AP$109, "*"&B63&"*") + COUNTIFS($AR$92:$AR$109, "*"&B63&"*")) > 0, SUMIFS($AO$92:$AO$109, $AP$92:$AP$109, "*"&B63&"*") + SUMIFS($AQ$92:$AQ$109, $AR$92:$AR$109, "*"&B63&"*") + SUMIFS($AT$92:$AT$109, $AU$92:$AU$109, "*"&B63&"*") + SUMIFS($AV$92:$AV$109, $AW$92:$AW$109, "*"&B63&"*"), ""), "") | B63: BAÑOS | M63: =J144 | O63: =+UPPER(C144)
A64: =IF(B64<>"", IF((COUNTIFS($AP$92:$AP$109, "*"&B64&"*") + COUNTIFS($AR$92:$AR$109, "*"&B64&"*")) > 0, SUMIFS($AO$92:$AO$109, $AP$92:$AP$109, "*"&B64&"*") + SUMIFS($AQ$92:$AQ$109, $AR$92:$AR$109, "*"&B64&"*") + SUMIFS($AT$92:$AT$109, $AU$92:$AU$109, "*"&B64&"*") + SUMIFS($AV$92:$AV$109, $AW$92:$AW$109, "*"&B64&"*"), ""), "") | M64: =J145 | O64: =+UPPER(C145)
A65: =IF(B65<>"", IF((COUNTIFS($AP$92:$AP$109, "*"&B65&"*") + COUNTIFS($AR$92:$AR$109, "*"&B65&"*")) > 0, SUMIFS($AO$92:$AO$109, $AP$92:$AP$109, "*"&B65&"*") + SUMIFS($AQ$92:$AQ$109, $AR$92:$AR$109, "*"&B65&"*") + SUMIFS($AT$92:$AT$109, $AU$92:$AU$109, "*"&B65&"*") + SUMIFS($AV$92:$AV$109, $AW$92:$AW$109, "*"&B65&"*"), ""), "") | M65: =J146 | O65: =+UPPER(C146)
A66: =IF(B66<>"", IF((COUNTIFS($AP$92:$AP$109, "*"&B66&"*") + COUNTIFS($AR$92:$AR$109, "*"&B66&"*")) > 0, SUMIFS($AO$92:$AO$109, $AP$92:$AP$109, "*"&B66&"*") + SUMIFS($AQ$92:$AQ$109, $AR$92:$AR$109, "*"&B66&"*") + SUMIFS($AT$92:$AT$109, $AU$92:$AU$109, "*"&B66&"*") + SUMIFS($AV$92:$AV$109, $AW$92:$AW$109, "*"&B66&"*"), ""), "") | M66: =J147 | O66: =+UPPER(C147)
A67: =IF(B67<>"", IF((COUNTIFS($AP$92:$AP$109, "*"&B67&"*") + COUNTIFS($AR$92:$AR$109, "*"&B67&"*")) > 0, SUMIFS($AO$92:$AO$109, $AP$92:$AP$109, "*"&B67&"*") + SUMIFS($AQ$92:$AQ$109, $AR$92:$AR$109, "*"&B67&"*") + SUMIFS($AT$92:$AT$109, $AU$92:$AU$109, "*"&B67&"*") + SUMIFS($AV$92:$AV$109, $AW$92:$AW$109, "*"&B67&"*"), ""), "") | M67: =J148 | O67: =+UPPER(C148)
AP69: AÑO ACTUAL | AQ69: 2024
A70: CARACTERÍSTICAS URBANAS Y DEL INMUEBLE
AP71: AÑO DE CONSTR. | AQ71: 2019
A72: CUENTA PREDIAL: | H72: =Query_Formato!B31 | O72: CLAVE CATASTRAL: | T72: =Query_Formato!B30 | Z72: MUNICIPIO | AB72: =Query_Formato!K30 | AP72: EDAD | AQ72: =+AQ69-AQ71 -> 5
A74: OBJETO DEL ANÁLISIS: | S74: RÉGIMEN DE PROP: | AF74: COLONIA
AO75: SELECCIONAR SERVICIOS DE LA ZONA
A77: SERVICIOS: | H77: =+CONCATENATE(AQ77," ",AR77,", ",AQ78," ",AR78,", ",AQ79," ",AR79,", ",AQ80," ",AR80,", ",AQ81," ",AR81,", ",AQ82," ",AR82,", ",AQ83," ",AR83,", ",AQ84," ",AR84,", ",AQ85," ",AR85,".", ) -> SERVICIOS BÁSICOS: , AGUA POTABLE: , DRENAJE: , ENERGÍA ELÉCTRICA: , GAS: , ALUMBRADO EXTERIOR: , LÍNEAS TELEFÓNICAS: , VIALIDADES: , TRANSPORTE: . | AQ77: SERVICIOS BÁSICOS:
AQ78: AGUA POTABLE:
AQ79: DRENAJE:
A80: CLASIFICACIÓN DE LA ZONA: | AC80: UNIDADES RENTABLES: | AI80: FORMATO DE RENTA: | AQ80: ENERGÍA ELÉCTRICA: | AX80: CLAVE
AQ81: GAS: | AW81: =+CONCATENATE(VLOOKUP(M86,'catalogo 2'!E134:F139,2,FALSE),".",VLOOKUP('OPI Rentas'!R86,'catalogo 2'!G134:H139,2,FALSE),".",VLOOKUP('OPI Rentas'!W86,'catalogo 2'!I134:J142,2,FALSE),".",VLOOKUP('OPI Rentas'!AB86,'catalogo 2'!L134:M142,2,FALSE)) -> #N/A
U82: C.O.S. | W82: C.U.S. | Z82: Fr Min | AB82: M2 Min. Lote | AE82: N° Est. | AG82: % Renta Zona | AJ82: % EDIF. SUJETO | AQ82: ALUMBRADO EXTERIOR:
A83: USO DEL SUELO: | E83: H1-U | I83: =UPPER(CONCATENATE(VLOOKUP(E83,'catalogo 2'!L5:N103,2,0)," ",(VLOOKUP(E83,'catalogo 2'!L5:N103,3,0)))) -> HABITACIONAL DENSIDAD MÍNIMA UNIFAMILIAR | U83: =VLOOKUP(E83,'catalogo 2'!L4:AI84,14,0) -> 0.4 | W83: =VLOOKUP(E83,'catalogo 2'!L4:AI84,16,0) -> 0.8 | Z83: =VLOOKUP(E83,'catalogo 2'!L4:AI84,11,0) -> 20 | AB83: =VLOOKUP(E83,'catalogo 2'!L4:AI84,10,0) -> 600 m2 | AE83: =VLOOKUP(E83,'catalogo 2'!L4:AI84,18,0) -> 4 | AQ83: LÍNEAS TELEFÓNICAS:
AQ84: VIALIDADES:
A85: EDAD APROX. | F85: VIDA ÚTIL | I85: ED. REMANENTE | M85: EDAD TIPO | S85: CALIDAD | X85: CONSERVACIÓN | AC85: PROYECTO: | AF85: NIVEL DE UBICACIÓN | AJ85: NIVELES DEL SUJETO | AQ85: TRANSPORTE:
A86: =YEAR(TODAY()) - AQ71 -> 7 | F86: =IF(OR(R86="MEDIO",R86="SUPERIOR",R86="LUJO"),70,60) -> 60 | I86: =IF(OR(R86="MEDIO",R86="SUPERIOR",R86="LUJO"),70,60)-A86 -> 53 | M86: =VLOOKUP(A86,'catalogo 2'!C124:F132,4) -> MODERNO 2
AO87: , | AQ87: DE
A88: MEDIDAS Y LINDEROS SEGÚN: | X88: =VLOOKUP("3.jp*g",Fotos!$A$2:$E444,5,FALSE)
AO89: SELECCIONAR ESPACIOS
A90: Noreste
A91: =IF($A$90="norte","Sur","Sureste") -> Sureste | E91: =IF(E90<>"", E90, "") | AO91: CANT | AP91: ESPACIO | AQ91: CANT | AR91: ESPACIO | AT91: CANT | AU91: ESPACIO | AV91: CANT | AW91: ESPACIO
A92: =IF($A$90="norte","Este","Noroeste") -> Noroeste
A93: =IF($A$90="norte","Oeste","Suroeste") -> Suroeste | E93: =IF(E92<>"", E92, "")
A95: DESCRIPCIÓN DEL INMUEBLE
A96: {=E8& IF(AK86<>"",AQ87&AK86,"")& IF(AJ85<>"",AP87&AJ86,"")& IF(AK86<>""," NIVEL(ES), DISTRIBUIDA EN: ","")& IF(AO90<>"",AO90&" CON: ","")& IF(AO92<>"",AO92&" "&AP92&", ","")& IF(AO93<>"",AO93&" "&AP93&", ","")& IF(AO94<>"",AO94&" "&AP94&", ","")& IF(AO95<>"",AO95&" "&AP95&", ","")& IF(AO96<>"",AO96&" "&AP96&", ","")& IF(AO97<>"",AO97&" "&AP97&", ","")& IF(AO98<>"",AO98&" "&AP98&", ","")& IF(AO99<>"",AO99&" "&AP99&", ","")& IF(AO100<>"",AO100&" "&AP100&", ","")& IF(AO101<>"",AO101&" "&AP101&", ","")& IF(AQ90<>""," EN "&AQ90&" CON: ","")& IF(AQ92<>"",AQ92&" "&AR92&", ","")& IF(AQ93<>"",AQ93&" "&AR93&", ","")& IF(AQ94<>"",AQ94&" "&AR94&", ","")& IF(AQ95<>"",AQ95&" "&AR95&", ","")& IF(AQ96<>"",AQ96&" "&AR96&", ","")& IF(AQ97<>"",AQ97&" "&AR97&", ","")& IF(AQ98<>"",AQ98&" "&AR98&", ","")& IF(AQ99<>"",AQ99&" "&AR99&", ","")& IF(AQ100<>"",AQ100&" "&AR100&", ","")& IF(AQ101<>"",AQ101&" "&AR101&", ","")& IF(AT90<>""," EN "&AT90&" CON: ","")& IF(AT92<>"",AT92&" "&AU92&", ","")& IF(AT93<>"",AT93&" "&AU93&", ","")& IF(AT94<>"",AT94&" "&AU94&", ","")& IF(AT95<>"",AT95&" "&AU95&", ","")& IF(AT96<>"",AT96&" "&AU96&", ","")& IF(AT97<>"",AT97&" "&AU97&", ","")& IF(AT98<>"",AT98&" "&AU98&", ","")& IF(AT99<>"",AT99&" "&AU99&", ","")& IF(AT100<>"",AT100&" "&AU100&", ","")& IF(AT101<>"",AT101&" "&AU101&", ","")& IF(AV90<>""," EN "&AV90&" CON: ","")& IF(AV92<>"",AV92&" "&AW92&", ","")& IF(AV93<>"",AV93&" "&AW93&", ","")& IF(AV94<>"",AV94&" "&AW94&", ","")& IF(AV95<>"",AV95&" "&AW95&", ","")& IF(AV96<>"",AV96&" "&AW96&", ","")& IF(AV97<>"",AV97&" "&AW97&", ","")& IF(AV98<>"",AV98&" "&AW98&", ","")& IF(AV99<>"",AV99&" "&AW99&", ","")& IF(AV100<>"",AV100&" "&AW95&", ","")& IF(AV101<>"",AV101&" "&AW101," ")}
A104: AVALÚO FÍSICO
C105: A) DEL TERRENO: | P105: LOTE TIPO: | Q105: VARIABLE
A106: FRACC. | C106: SUPERFICIE: | G106: VALOR UNITARIO | K106: FACTORES DE EFICIENCIA DE SUELO: | AC106: V. TERRENO | AG106: INDIVISO: | AJ106: VALOR
K107: ZONA | M107: UBICACIÓN | P107: FRENTE | R107: FORMA | T107: SUPERFICIE | X107: OTRO | Z107: FAC.RE. | AC107: RESULTANTE: | AJ107: RESULTANTE:
A108: 1 | K108: 1 | M108: 1 | P108: 1 | R108: 1 | T108: 1 | X108: 1 | Z108: =ROUND(K108*M108*P108*R108*T108*X108,2) -> 1 | AC108: =+Z108*G108 -> 0 | AG108: 1 | AJ108: =C108*AC108*AG108 -> 0
A109: 2 | G109: 0 | AC109: =+Z109*G109 -> 0 | AG109: 1 | AJ109: =+AC109*C109*AG109 -> 0
A110: 3 | G110: 0 | AC110: =+Z110*G110 -> 0 | AG110: 1 | AJ110: =+AC110*C110*AG110 -> 0
A111: T | C111: =SUM(C108:F110) -> 0 | K111: OTRO: | AC111: =SUM(AC108:AF110) -> 0 | AG111: VALOR DEL TERRENO | AJ111: =SUM(AJ108:AM110) -> 0 | AN111: =AJ111/$AJ$159 -> #DIV/0! | AP111: MOVER EDAD MANUALMENTE CUANDO HAY MEJORAS O AMPLIACIONES
C113: B) DE LAS CONSTRUCCIONES: | N113: VALOR NUEVO | Q113: DEMÉRITO: | AC113: VALOR | AG113: INDIVISO: | AJ113: VALOR
A114: TIPO: | C114: DESCRIPCIÓN | K114: SUPERFICIE: | Q114: ACABADOS | T114: CONSERV | X114: PROYECTO | Z114: EDAD | AC114: USADO | AJ114: RESULTANTE: | AP114: NUEVA | AQ114: EDAD | AR114: REMANENTE
A115: I.- | Q115: 1 | T115: 0.85 | X115: 1 | Z115: =IF(AS115<0.2,"0.20",AS115) -> 0.9 | AC115: =Z115*Q115*X115*T115*N115 -> 0 | AG115: 1 | AJ115: =K115*AC115*AG115 -> 0 | AP115: =+F86 -> 60 | AQ115: =+A86 -> 7 | AR115: =AP115-AQ115 -> 53 | AS115: =ROUND(((0.1*AP115)+(0.9*AR115))/AP115,2) -> 0.9
A116: II.- | Q116: 1 | T116: 0 | X116: 1 | Z116: =IF(AS116<0.2,"0.20",AS116) -> 0.9 | AC116: =Z116*Q116*X116*T116*N116 -> 0 | AG116: 1 | AJ116: =K116*AC116*AG116 -> 0 | AP116: =+AP115 -> 60 | AQ116: =+AQ115 -> 7 | AR116: =AP116-AQ116 -> 53 | AS116: =ROUND(((0.1*AP116)+(0.9*AR116))/AP116,2) -> 0.9
A117: III.- | Q117: 1 | T117: 0 | X117: 1 | Z117: =IF(AS117<0.2,"0.20",AS117) -> 0.9 | AC117: =Z117*Q117*X117*T117*N117 -> 0 | AG117: 1 | AJ117: =K117*AC117*AG117 -> 0 | AP117: =+AP116 -> 60 | AQ117: =+AQ116 -> 7 | AR117: =AP117-AQ117 -> 53 | AS117: =ROUND(((0.1*AP117)+(0.9*AR117))/AP117,2) -> 0.9
A118: IV.- | Q118: 1 | T118: 0 | X118: 1 | Z118: =IF(AS118<0.6,"0.60",AS118) -> 0.9 | AC118: =Z118*X118*T118*P118 -> 0 | AG118: 1 | AJ118: =K118*AC118*AG118 -> 0 | AP118: =+AP117 -> 60 | AQ118: =+AQ117 -> 7 | AR118: =AP118-AQ118 -> 53 | AS118: =ROUND(((0.1*AP118)+(0.9*AR118))/AP118,2) -> 0.9
A119: V.- | Q119: 1 | T119: 1 | X119: 1 | Z119: =IF(AS119<0.6,"0.60",AS119) -> 0.88 | AC119: =Z119*X119*T119*P119 -> 0 | AG119: 1 | AJ119: =K119*AC119*AG119 -> 0 | AP119: 75 | AQ119: 10 | AR119: =AP119-AQ119 -> 65 | AS119: =ROUND(((0.1*AP119)+(0.9*AR119))/AP119,2) -> 0.88
A120: VI.- | Q120: 1 | T120: 1 | X120: 1 | Z120: =IF(AS120<0.6,"0.60",AS120) -> 0.88 | AC120: =Z120*X120*T120*P120 -> 0 | AG120: 1 | AJ120: =K120*AC120*AG120 -> 0 | AP120: 75 | AQ120: 10 | AR120: =AP120-AQ120 -> 65 | AS120: =ROUND(((0.1*AP120)+(0.9*AR120))/AP120,2) -> 0.88
A121: VII.- | Q121: 1 | T121: 1 | X121: 1 | Z121: =IF(AS121<0.6,"0.60",AS121) -> 0.88 | AC121: =Z121*X121*T121*P121 -> 0 | AG121: 1 | AJ121: =K121*AC121*AG121 -> 0 | AP121: 75 | AQ121: 10 | AR121: =AP121-AQ121 -> 65 | AS121: =ROUND(((0.1*AP121)+(0.9*AR121))/AP121,2) -> 0.88
A122: VIII.- | Q122: 1 | T122: 1 | X122: 1 | Z122: =IF(AS122<0.6,"0.60",AS122) -> 0.88 | AC122: =Z122*X122*T122*P122 -> 0 | AG122: 1 | AJ122: =K122*AC122*AG122 -> 0 | AP122: 75 | AQ122: 10 | AR122: =AP122-AQ122 -> 65 | AS122: =ROUND(((0.1*AP122)+(0.9*AR122))/AP122,2) -> 0.88
C123: TOTAL: | K123: =SUM(K115:K122) -> 0 | AH123: VALOR DE LAS CONSTRUCCIONES: | AJ123: =SUM(AJ115:AJ122) -> 0 | AN123: =AJ123/$AJ$159 -> #DIV/0!
C125: C) DE LAS CONSTRUCCIONES ACCESORIAS: | P125: VALOR NUEVO | T125: DEMÉRITO: | AC125: VALOR | AG125: INDIVISO: | AJ125: VALOR
A126: TIPO: | C126: DESCRIPCIÓN | K126: SUPERFICIE: | T126: CONS | X126: PROYECTO | Z126: EDAD | AC126: USADO | AJ126: RESULTANTE: | AP126: NUEVA | AQ126: EDAD | AR126: REMANENTE
A127: I.- | T127: 0.85 | X127: 1 | Z127: =IF(AS127<0.2,"0.20",AS127) -> 0.9 | AC127: =Z127*X127*T127*P127 -> 0 | AG127: 1 | AJ127: =K127*AC127*AG127 -> 0 | AP127: =+F86 -> 60 | AQ127: =+A86 -> 7 | AR127: =AP127-AQ127 -> 53 | AS127: =ROUND(((0.1*AP127)+(0.9*AR127))/AP127,2) -> 0.9
A128: II.- | T128: 1 | X128: 1 | Z128: =IF(AS128<0.6,"0.60",AS128) -> 0.9 | AC128: =Z128*X128*T128*P128 -> 0 | AG128: 1 | AJ128: =K128*AC128*AG128 -> 0 | AP128: =+AP127 -> 60 | AQ128: =+AQ127 -> 7 | AR128: =AP128-AQ128 -> 53 | AS128: =ROUND(((0.1*AP128)+(0.9*AR128))/AP128,2) -> 0.9
A129: III.- | T129: 1 | X129: 1 | Z129: =IF(AS129<0.6,"0.60",AS129) -> 0.9 | AC129: =Z129*X129*T129*P129 -> 0 | AG129: 1 | AJ129: =K129*AC129*AG129 -> 0 | AP129: =+AP128 -> 60 | AQ129: =+AQ128 -> 7 | AR129: =AP129-AQ129 -> 53 | AS129: =ROUND(((0.1*AP129)+(0.9*AR129))/AP129,2) -> 0.9
A130: IV.- | T130: 1 | X130: 1 | Z130: =IF(AS130<0.6,"0.60",AS130) -> 0.9 | AC130: =Z130*X130*T130*P130 -> 0 | AG130: 1 | AJ130: =K130*AC130*AG130 -> 0 | AP130: =+AP129 -> 60 | AQ130: =+AQ129 -> 7 | AR130: =AP130-AQ130 -> 53 | AS130: =ROUND(((0.1*AP130)+(0.9*AR130))/AP130,2) -> 0.9
A131: V.- | T131: 1 | X131: 1 | Z131: =IF(AS131<0.6,"0.60",AS131) -> 0.88 | AC131: =Z131*X131*T131*P131 -> 0 | AG131: 1 | AJ131: =K131*AC131*AG131 -> 0 | AP131: 75 | AQ131: 10 | AR131: =AP131-AQ131 -> 65 | AS131: =ROUND(((0.1*AP131)+(0.9*AR131))/AP131,2) -> 0.88
A132: VI.- | T132: 1 | X132: 1 | Z132: =IF(AS132<0.6,"0.60",AS132) -> 0.88 | AC132: =Z132*X132*T132*P132 -> 0 | AG132: 1 | AJ132: =K132*AC132*AG132 -> 0 | AP132: 75 | AQ132: 10 | AR132: =AP132-AQ132 -> 65 | AS132: =ROUND(((0.1*AP132)+(0.9*AR132))/AP132,2) -> 0.88
A133: VII.- | T133: 1 | X133: 1 | Z133: =IF(AS133<0.6,"0.60",AS133) -> 0.88 | AC133: =Z133*X133*T133*P133 -> 0 | AG133: 1 | AJ133: =K133*AC133*AG133 -> 0 | AP133: 75 | AQ133: 10 | AR133: =AP133-AQ133 -> 65 | AS133: =ROUND(((0.1*AP133)+(0.9*AR133))/AP133,2) -> 0.88
A134: VIII.- | T134: 1 | X134: 1 | Z134: =IF(AS134<0.6,"0.60",AS134) -> 0.88 | AC134: =Z134*X134*T134*P134 -> 0 | AG134: 1 | AJ134: =K134*AC134*AG134 -> 0 | AP134: 75 | AQ134: 10 | AR134: =AP134-AQ134 -> 65 | AS134: =ROUND(((0.1*AP134)+(0.9*AR134))/AP134,2) -> 0.88
C135: TOTAL: | K135: =SUM(K127:K134) -> 0 | AH135: VALOR DE LAS CONSTRUCCIONES: | AJ135: =SUM(AJ127:AJ134) -> 0 | AN135: =AJ135/$AJ$159 -> #DIV/0!
C137: D) INSTALACIONES ADICIONALES, MOBILIARIO, ACCESORIAS O ESPECIALES: | AP137: MOVER EDAD MANUALMENTE CUANDO HAY MEJORAS O AMPLIACIONES
A138: CONCEPTO: | J138: CANTIDAD: | M138: UNIDAD: | P138: VALOR | T138: DEMÉRITO: | AC138: VALOR | AG138: INDIVISO: | AJ138: VALOR
P139: NUEVO | T139: CONSERVACIÓN | Y139: EDAD | AC139: USADO | AJ139: RESULTANTE:
A140: I.- | T140: 0.85 | Y140: =+AS140 -> 0.91 | AC140: =P140*T140*Y140 -> 0 | AG140: 1 | AJ140: =J140*AC140*AG140 -> 0 | AP140: 50 | AQ140: 5 | AR140: =AP140-AQ140 -> 45 | AS140: =ROUND(((0.1*AP140)+(0.9*AR140))/AP140,2) -> 0.91
A141: II.- | T141: 0.91 | Y141: =+AS141 -> 0.9 | AC141: =P141*T141*Y141 -> 0 | AG141: 1 | AJ141: =J141*AC141*AG141 -> 0 | AP141: 45 | AQ141: 5 | AR141: =AP141-AQ141 -> 40 | AS141: =ROUND(((0.1*AP141)+(0.9*AR141))/AP141,2) -> 0.9
A142: III.- | AC142: =P142*T142*Y142 -> 0 | AG142: 1 | AJ142: =J142*AC142*AG142 -> 0 | AP142: 45 | AQ142: 4 | AR142: =AP142-AQ142 -> 41 | AS142: =ROUND(((0.1*AP142)+(0.9*AR142))/AP142,2) -> 0.92
A143: IV.- | AC143: =P143*T143*Y143 -> 0 | AG143: 1 | AJ143: =J143*AC143*AG143 -> 0 | AP143: 70 | AQ143: 0 | AR143: =AP143-AQ143 -> 70 | AS143: =ROUND(((0.1*AP143)+(0.9*AR143))/AP143,2) -> 1
A144: V.- | AC144: =P144*T144*Y144 -> 0 | AG144: 1 | AJ144: =J144*AC144*AG144 -> 0 | AP144: 70 | AQ144: 16 | AR144: 0 | AS144: =ROUND(((0.1*AP144)+(0.9*AR144))/AP144,2) -> 0.1
T145: 1 | Y145: =+AS145 -> 0.78 | AC145: =P145*T145*Y145 -> 0 | AG145: 1 | AJ145: =J145*AC145*AG145 -> 0 | AP145: 60 | AQ145: 15 | AR145: =AP145-AQ145 -> 45 | AS145: =ROUND(((0.1*AP145)+(0.9*AR145))/AP145,2) -> 0.78
T146: 1 | Y146: =+AS146 -> 0.72 | AC146: =P146*T146*Y146 -> 0 | AG146: 1 | AJ146: =J146*AC146*AG146 -> 0 | AP146: 45 | AQ146: 14 | AR146: =AP146-AQ146 -> 31 | AS146: =ROUND(((0.1*AP146)+(0.9*AR146))/AP146,2) -> 0.72
T147: 1 | Y147: =+AS147 -> 0.96 | AC147: =P147*T147*Y147 -> 0 | AG147: 1 | AJ147: =J147*AC147*AG147 -> 0 | AP147: 45 | AQ147: 2 | AR147: =AP147-AQ147 -> 43 | AS147: =ROUND(((0.1*AP147)+(0.9*AR147))/AP147,2) -> 0.96
T148: 1 | Y148: =+AS148 -> 0.8 | AC148: =P148*T148*Y148 -> 0 | AG148: 1 | AJ148: =J148*AC148*AG148 -> 0 | AP148: 45 | AQ148: 10 | AR148: =AP148-AQ148 -> 35 | AS148: =ROUND(((0.1*AP148)+(0.9*AR148))/AP148,2) -> 0.8
T149: 1 | Y149: =+AS149 -> 0.8 | AC149: =P149*T149*Y149 -> 0 | AG149: 1 | AJ149: =J149*AC149*AG149 -> 0 | AP149: 45 | AQ149: 10 | AR149: =AP149-AQ149 -> 35 | AS149: =ROUND(((0.1*AP149)+(0.9*AR149))/AP149,2) -> 0.8
...

Sheet OPI Constr
AF1: 3314189492 | AI1: 3336320507
O2: OPINIÓN DE VALOR | AF2: avaluos@avaluosyarquitectura.com.mx
AF3: avaluosyarquitectura2@gmail.com
AF4: www.avaluosyarquitectura.com.mx
A6: FOLIO | E6: =Query_Formato!B168 -> OPI-25-11-07-OF | AF6: Fecha: | AG6: =TODAY() -> 46202
A8: TIPO DE PROPIEDAD: | E8: =Query_Formato!B44 -> Casa Habitación | Y8: SOLICITANTE: | Z8: =Query_Formato!B156 -> Federico Arellano
A10: UBICACIÓN: | E10: Pascal 2164, San Elías, 44246 Guadalajara, Jal. | Y10: PROPIETARIO: | Z10: Datos No Proporcionados
A13: =VLOOKUP("1.jp*g",Fotos!$A$2:$E371,5,FALSE) | V13: =VLOOKUP("2.jp*g",Fotos!$A$2:$E371,5,FALSE)
A34: RESUMEN
A36: VALOR VENTA ESTIMADO PROMEDIO | N36: VALOR DE RENTA ESTIMADO PROMEDIO | AB36: REPRESENTATIVA DEL VALOR FÍSICO
A38: MÁXIMO sugerido | D38: =D40*1.1 -> 2676300 | N38: MÁXIMO | Q38: =Q40*1.1 -> 11000 | AB38: TERRENO | AI38: =AN111 -> 0.53348441
AB39: CONSTRUCCIONES | AI39: =AN123 -> 0.46183497
A40: MEDIO o justo | D40: =AI165 -> 2433000 | N40: MEDIO | Q40: =ROUND(AI166,-3) -> 10000 | AB40: CONSTR. ACCESORIAS | AI40: =AN135 -> 0
A42: MÍNIMO sugerido | D42: =D40*0.9 -> 2189700 | N42: MÍNIMO | Q42: =Q40*0.9 -> 9000 | AB42: INSTALACIONES ACCESORIAS | AI42: =AN157 -> 0.0046806206
AI43: tot | AJ43: =SUM(AI38:AI43) -> 1
A46: UNIDADES RENTABLES | K46: =AE80 -> 1 | N46: TASA RENTA ANUAL | W46: =(AP166*10)/1 -> 0.04 | AB46: CALIFICA CRÉDITO | AH46: SI
AB47: para bancos, infonavit, fovisste, instituciones financieras
A48: NIVELES | I48: =AK86 -> 1 | N48: ESTADO DE CONSERVACIÓN | X48: =W86 -> REMODELADO
A50: NIVEL UBICACIÓN | H50: =AG86 -> 0 - P.BAJA | N50: EDAD PONDERADA APROX | W50: =A86 -> 21 | AB50: PLUSVALÍA ANUAL | AI50: 4-6%
A52: TERRENO | I52: =C111 -> 91.97 | N52: EDAD REMANENTE | W52: =I86 -> 49 | AB52: CERCANÍA | AG52: INTERMEDIA
A54: CONSTRUCCIONES | I54: =K123 -> 74.2 | N54: AVANCE DE OBRA | W54: =AJ83 -> 1 | AB54: DEMANDA DE LA ZONA | AG54: MEDIA
A55: vendibles
A56: RESUMEN DE ESPACIOS
B58: RESUMEN ESPACIOS BÁSICOS | P58: ELEMENTOS ACCESORIOS | AC58: AMENIDADES DEL CONJUNTO
A59: =IF(B59<>"", IF((COUNTIFS($AP$92:$AP$109, "*"&B59&"*") + COUNTIFS($AR$92:$AR$109, "*"&B59&"*")) > 0, SUMIFS($AO$92:$AO$109, $AP$92:$AP$109, "*"&B59&"*") + SUMIFS($AQ$92:$AQ$109, $AR$92:$AR$109, "*"&B59&"*") + SUMIFS($AT$92:$AT$109, $AU$92:$AU$109, "*"&B59&"*") + SUMIFS($AV$92:$AV$109, $AW$92:$AW$109, "*"&B59&"*"), ""), "") -> 1 | B59: SALA | O59: NO TIENE | AB59: NO TIENE
A60: =IF(B60<>"", IF((COUNTIFS($AP$92:$AP$109, "*"&B60&"*") + COUNTIFS($AR$92:$AR$109, "*"&B60&"*")) > 0, SUMIFS($AO$92:$AO$109, $AP$92:$AP$109, "*"&B60&"*") + SUMIFS($AQ$92:$AQ$109, $AR$92:$AR$109, "*"&B60&"*") + SUMIFS($AT$92:$AT$109, $AU$92:$AU$109, "*"&B60&"*") + SUMIFS($AV$92:$AV$109, $AW$92:$AW$109, "*"&B60&"*"), ""), "") -> 1 | B60: COCINA | E60: COMERCIAL | I60: MINIMA | M60: =J141 | AB60: =+UPPER(C141)
A61: =IF(B61<>"", IF((COUNTIFS($AP$92:$AP$109, "*"&B61&"*") + COUNTIFS($AR$92:$AR$109, "*"&B61&"*")) > 0, SUMIFS($AO$92:$AO$109, $AP$92:$AP$109, "*"&B61&"*") + SUMIFS($AQ$92:$AQ$109, $AR$92:$AR$109, "*"&B61&"*"), ""), "") -> 1 | B61: PATIO | M61: =J142 | O61: =+UPPER(C142)
A62: =IF(B62<>"", IF((COUNTIFS($AP$92:$AP$109, "*"&B62&"*") + COUNTIFS($AR$92:$AR$109, "*"&B62&"*")) + COUNTIFS($AU$92:$AUR$109, "*"&B62&"*") > 0, SUMIFS($AO$92:$AO$109, $AP$92:$AP$109, "*"&B62&"*") + SUMIFS($AQ$92:$AQ$109, $AR$92:$AR$109, "*"&B62&"*") + SUMIFS($AT$92:$AT$109, $AU$92:$AU$109, "*"&B62&"*") + SUMIFS($AV$92:$AV$109, $AW$92:$AW$109, "*"&B62&"*"), ""), "") -> 3 | B62: RECAMARAS | M62: =J143 | O62: =+UPPER(C143)
A63: =IF(B63<>"", IF((COUNTIFS($AP$92:$AP$109, "*"&B63&"*") + COUNTIFS($AR$92:$AR$109, "*"&B63&"*")) > 0, SUMIFS($AO$92:$AO$109, $AP$92:$AP$109, "*"&B63&"*") + SUMIFS($AQ$92:$AQ$109, $AR$92:$AR$109, "*"&B63&"*") + SUMIFS($AT$92:$AT$109, $AU$92:$AU$109, "*"&B63&"*") + SUMIFS($AV$92:$AV$109, $AW$92:$AW$109, "*"&B63&"*"), ""), "") -> 2 | B63: BAÑOS | M63: =J144 | O63: =+UPPER(C144)
A64: =IF(B64<>"", IF((COUNTIFS($AP$92:$AP$109, "*"&B64&"*") + COUNTIFS($AR$92:$AR$109, "*"&B64&"*")) > 0, SUMIFS($AO$92:$AO$109, $AP$92:$AP$109, "*"&B64&"*") + SUMIFS($AQ$92:$AQ$109, $AR$92:$AR$109, "*"&B64&"*") + SUMIFS($AT$92:$AT$109, $AU$92:$AU$109, "*"&B64&"*") + SUMIFS($AV$92:$AV$109, $AW$92:$AW$109, "*"&B64&"*"), ""), "") | B64: . | M64: =J145 | O64: =+UPPER(C145)
A65: =IF(B65<>"", IF((COUNTIFS($AP$92:$AP$109, "*"&B65&"*") + COUNTIFS($AR$92:$AR$109, "*"&B65&"*")) > 0, SUMIFS($AO$92:$AO$109, $AP$92:$AP$109, "*"&B65&"*") + SUMIFS($AQ$92:$AQ$109, $AR$92:$AR$109, "*"&B65&"*") + SUMIFS($AT$92:$AT$109, $AU$92:$AU$109, "*"&B65&"*") + SUMIFS($AV$92:$AV$109, $AW$92:$AW$109, "*"&B65&"*"), ""), "") | M65: =J146 | O65: =+UPPER(C146)
A66: =IF(B66<>"", IF((COUNTIFS($AP$92:$AP$109, "*"&B66&"*") + COUNTIFS($AR$92:$AR$109, "*"&B66&"*")) > 0, SUMIFS($AO$92:$AO$109, $AP$92:$AP$109, "*"&B66&"*") + SUMIFS($AQ$92:$AQ$109, $AR$92:$AR$109, "*"&B66&"*") + SUMIFS($AT$92:$AT$109, $AU$92:$AU$109, "*"&B66&"*") + SUMIFS($AV$92:$AV$109, $AW$92:$AW$109, "*"&B66&"*"), ""), "") | M66: =J147 | O66: =+UPPER(C147)
A67: =IF(B67<>"", IF((COUNTIFS($AP$92:$AP$109, "*"&B67&"*") + COUNTIFS($AR$92:$AR$109, "*"&B67&"*")) > 0, SUMIFS($AO$92:$AO$109, $AP$92:$AP$109, "*"&B67&"*") + SUMIFS($AQ$92:$AQ$109, $AR$92:$AR$109, "*"&B67&"*") + SUMIFS($AT$92:$AT$109, $AU$92:$AU$109, "*"&B67&"*") + SUMIFS($AV$92:$AV$109, $AW$92:$AW$109, "*"&B67&"*"), ""), "") | M67: =J148 | O67: =+UPPER(C148)
AP69: AÑO ACTUAL | AQ69: 2025
A70: CARACTERÍSTICAS URBANAS Y DEL INMUEBLE
AP71: AÑO DE CONSTR. | AQ71: 2005
A72: CUENTA PREDIAL: | H72: Datos No Proporcionados | O72: CLAVE CATASTRAL: | S72: Datos No Proporcionados | Z72: MUNICIPIO | AB72: Guadalajara | AP72: EDAD | AQ72: =+AQ69-AQ71 -> 20
A74: OBJETO DEL ANÁLISIS: | H74: Estimar el Valor Comercial | S74: RÉGIMEN DE PROP: | W74: Privada | AF74: COLONIA | AG74: San Elías
AO75: SELECCIONAR SERVICIOS DE LA ZONA
A77: SERVICIOS: | H77: =+CONCATENATE(AQ77," ",AR77,", ",AQ78," ",AR78,", ",AQ79," ",AR79,", ",AQ80," ",AR80,", ",AQ81," ",AR81,", ",AQ82," ",AR82,", ",AQ83," ",AR83,", ",AQ84," ",AR84,", ",AQ85," ",AR85,".", ) -> SERVICIOS BÁSICOS: COMPLETOS, AGUA POTABLE: ENTUBADA, DRENAJE: ENTUBADO, ENERGÍA ELÉCTRICA: CON CABLEADO AÉREO, CON CILINDROS, ALUMBRADO EXTERIOR: CON CABLEADO AÉREO, LÍNEAS TELEFÓNICAS: CON CABLEADO AÉREO, VIALIDADES: DE ASFALTO, TRANSPORTE: URBANO. | AQ77: SERVICIOS BÁSICOS: | AR77: COMPLETOS
AQ78: AGUA POTABLE: | AR78: ENTUBADA
AQ79: DRENAJE: | AR79: ENTUBADO
A80: CLASIFICACIÓN DE LA ZONA: | H80: HABITACIONAL DE 2DO. ORDEN | Z80: UNIDADES RENTABLES: | AE80: =Query_Formato!B45 -> 1 | AJ80: % AVANCE EDIF. SUJETO | AQ80: ENERGÍA ELÉCTRICA: | AR80: CON CABLEADO AÉREO | AX80: CLAVE
AR81: CON CILINDROS | AW81: =+CONCATENATE(VLOOKUP(M86,'catalogo 2'!E134:F139,2,FALSE),".",VLOOKUP('OPI Constr'!R86,'catalogo 2'!G134:H139,2,FALSE),".",VLOOKUP('OPI Constr'!W86,'catalogo 2'!I134:J142,2,FALSE),".",VLOOKUP('OPI Constr'!AB86,'catalogo 2'!L134:M142,2,FALSE)) -> SM2.S.RM+.R
U82: C.O.S. | W82: C.U.S. | Z82: Fr Min | AB82: M2 Min. Lote | AE82: N° Est. | AG82: % Edif. Zona | AQ82: ALUMBRADO EXTERIOR: | AR82: CON CABLEADO AÉREO
A83: USO DEL SUELO: | E83: H4 | I83: =UPPER(CONCATENATE(VLOOKUP(E83,'catalogo 2'!L5:N103,2,0)," ",(VLOOKUP(E83,'catalogo 2'!L5:N103,3,0)))) -> HABITACIONAL DENSIDAD ALTA | U83: =VLOOKUP(E83,'catalogo 2'!L4:AI84,14,0) -> 0.8 | W83: 2 | Z83: =VLOOKUP(E83,'catalogo 2'!L4:AI84,11,0) -> 6 | AB83: =VLOOKUP(E83,'catalogo 2'!L4:AI84,10,0) -> 90 m2 | AE83: =VLOOKUP(E83,'catalogo 2'!L4:AI84,18,0) -> 1 | AG83: 0.98 | AJ83: 1 | AQ83: LÍNEAS TELEFÓNICAS: | AR83: CON CABLEADO AÉREO
AQ84: VIALIDADES: | AR84: DE ASFALTO
A85: EDAD APROX. | F85: VIDA ÚTIL | I85: ED. REMANENTE | M85: EDAD TIPO | S85: CALIDAD | X85: CONSERVACIÓN | AC85: PROYECTO: | AF85: NIVEL DE UBICACIÓN | AJ85: NIVELES DEL SUJETO | AQ85: TRANSPORTE: | AR85: URBANO
A86: =YEAR(TODAY()) - AQ71 -> 21 | F86: =IF(OR(R86="MEDIO",R86="SUPERIOR",R86="LUJO"),70,60) -> 70 | I86: =IF(OR(R86="MEDIO",R86="SUPERIOR",R86="LUJO"),70,60)-A86 -> 49 | M86: =VLOOKUP(A86,'catalogo 2'!C124:F132,4) -> SEMI MODERNO 2 | R86: MEDIO | W86: REMODELADO | AB86: REGULAR | AG86: 0 - P.BAJA | AK86: =Query_Formato!B43 -> 1
AO87: , | AQ87: DE
A88: MEDIDAS Y LINDEROS SEGÚN: | I88: Datos No Proporcionados | X88: =VLOOKUP("3.jp*g",Fotos!$A$2:$E371,5,FALSE)
AO89: SELECCIONAR ESPACIOS
A90: Norte | E90: . | H90: . | AO90: NIVEL 0 - PLANTA BAJA
A91: =IF($A$90="norte","Sur","Sureste") -> Sur | E91: . | H91: . | AO91: CANT | AP91: ESPACIO | AQ91: CANT | AR91: ESPACIO | AT91: CANT | AU91: ESPACIO | AV91: CANT | AW91: ESPACIO
A92: =IF($A$90="norte","Este","Noroeste") -> Este | E92: . | H92: . | AO92: 1 | AP92: Sala
A93: =IF($A$90="norte","Oeste","Suroeste") -> Oeste | E93: . | H93: . | AO93: 1 | AP93: Comedor
AO94: 1 | AP94: Cocina
A95: DESCRIPCIÓN DEL INMUEBLE | AO95: 3 | AP95: Recamaras
A96: =IFERROR(__xludf.DUMMYFUNCTION("ARRAYFORMULA( E8 & IF(AK86<>"""", AQ87 & AK86 & "" NIVEL(ES), DISTRIBUIDA EN: "", """") & TEXTJOIN("", "", TRUE, IF(AO90<>"""", AO90 & "" CON: "" & AP90 & "" "" & TEXTJOIN("", "", TRUE, FILTER(AO92:AO108 & "" "" & AP92:AP108, AO92:AO108<>"""")),"&" """"), IF(AQ90<>"""", "" EN "" & AQ90 & "" CON: "" & AR90 & "" "" & TEXTJOIN("", "", TRUE, FILTER(AQ92:AQ108 & "" "" & AR92:AR108, AQ92:AQ108<>"""")), """"), IF(AT90<>"""", "" EN "" & AT90 & "" CON: "" & AU90 & "" "" & TEXTJOIN("", "", TRUE, FILT"&"ER(AT92:AT108 & "" "" & AU92:AU108, AT92:AT108<>"""")), """"), IF(AV90<>"""", "" EN "" & AV90 & "" CON: "" & AW90 & "" "" & TEXTJOIN("", "", TRUE, FILTER(AV92:AV108 & "" "" & AV92:AW108, AV92:AV108<>"""")), """") ))"),"Casa Habitación DE 1 NIVEL(ES), DISTRIBUIDA EN: NIVEL 0 - PLANTA BAJA CON: 1 Sala, 1 Comedor, 1 Cocina, 3 Recamaras, 2 Baños, 1 Patio") -> Casa Habitación DE 1 NIVEL(ES), DISTRIBUIDA EN: NIVEL 0 - PLANTA BAJA CON: 1 Sala, 1 Comedor, 1 Cocina, 3 Recamaras, 2 Baños, 1 Patio | AO96: 2 | AP96: Baños
AO97: 1 | AP97: Patio
A104: AVALÚO FÍSICO
C105: A) DEL TERRENO: | P105: LOTE TIPO: | Q105: VARIABLE
A106: FRACC. | C106: SUPERFICIE: | G106: VALOR UNITARIO | K106: FACTORES DE EFICIENCIA DE SUELO: | AC106: V. TERRENO | AG106: INDIVISO: | AJ106: VALOR
K107: ZONA | M107: UBICACIÓN | P107: FRENTE | R107: FORMA | T107: SUPERFICIE | X107: OTRO | Z107: FAC.RE. | AC107: RESULTANTE: | AJ107: RESULTANTE:
A108: 1 | C108: 91.97 | G108: 10500 | K108: 1 | M108: 1 | P108: 1 | R108: 1 | T108: 1 | X108: 1 | Z108: =ROUND(K108*M108*P108*R108*T108*X108,2) -> 1 | AC108: =+Z108*G108 -> 10500 | AG108: 1 | AJ108: =C108*AC108*AG108 -> 965685
A109: 2 | G109: 0 | AC109: =+Z109*G109 -> 0 | AG109: 1 | AJ109: =+AC109*C109*AG109 -> 0
A110: 3 | G110: 0 | AC110: =+Z110*G110 -> 0 | AG110: 1 | AJ110: =+AC110*C110*AG110 -> 0
A111: T | C111: =SUM(C108:F110) -> 91.97 | K111: OTRO: | AC111: =SUM(AC108:AF110) -> 10500 | AG111: VALOR DEL TERRENO | AJ111: =SUM(AJ108:AM110) -> 965685 | AN111: =AJ111/$AJ$159 -> 0.53348441 | AP111: MOVER EDAD MANUALMENTE CUANDO HAY MEJORAS O AMPLIACIONES
C113: B) DE LAS CONSTRUCCIONES: | N113: VALOR NUEVO | Q113: DEMÉRITO: | AC113: VALOR | AG113: INDIVISO: | AJ113: VALOR
A114: TIPO: | C114: DESCRIPCIÓN | K114: SUPERFICIE: | Q114: ACABADOS | T114: CONSERV | X114: PROYECTO | Z114: EDAD | AC114: USADO | AJ114: RESULTANTE: | AP114: NUEVA | AQ114: EDAD | AR114: REMANENTE
A115: I.- | C115: Planta Unica | K115: 16.08 | N115: 13500 | Q115: 1 | T115: 0.95 | X115: 1 | Z115: =IF(AS115<0.2,"0.20",AS115) -> 0.73 | AC115: =Z115*Q115*X115*T115*N115 -> 9362.25 | AG115: 1 | AJ115: =K115*AC115*AG115 -> 150544.98 | AP115: =+F86 -> 70 | AQ115: =+A86 -> 21 | AR115: =AP115-AQ115 -> 49 | AS115: =ROUND(((0.1*AP115)+(0.9*AR115))/AP115,2) -> 0.73
A116: II.- | C116: Ampliación Recámara | K116: 58.12 | N116: 13500 | Q116: 1 | T116: 0.91 | X116: 1 | Z116: =IF(AS116<0.2,"0.20",AS116) -> 0.96 | AC116: =Z116*Q116*X116*T116*N116 -> 11793.6 | AG116: 1 | AJ116: =K116*AC116*AG116 -> 685444.03 | AP116: =+AP115 -> 70 | AQ116: 3 | AR116: =AP116-AQ116 -> 67 | AS116: =ROUND(((0.1*AP116)+(0.9*AR116))/AP116,2) -> 0.96
A117: III.- | K117: 0 | Q117: 1 | T117: 0 | X117: 1 | Z117: =IF(AS117<0.2,"0.20",AS117) -> 0.96 | AC117: =Z117*Q117*X117*T117*N117 -> 0 | AG117: 1 | AJ117: =K117*AC117*AG117 -> 0 | AP117: =+AP116 -> 70 | AQ117: =+AQ116 -> 3 | AR117: =AP117-AQ117 -> 67 | AS117: =ROUND(((0.1*AP117)+(0.9*AR117))/AP117,2) -> 0.96
A118: IV.- | Q118: 1 | T118: 0 | X118: 1 | Z118: =IF(AS118<0.6,"0.60",AS118) -> 0.96 | AC118: =Z118*X118*T118*P118 -> 0 | AG118: 1 | AJ118: =K118*AC118*AG118 -> 0 | AP118: =+AP117 -> 70 | AQ118: =+AQ117 -> 3 | AR118: =AP118-AQ118 -> 67 | AS118: =ROUND(((0.1*AP118)+(0.9*AR118))/AP118,2) -> 0.96
A119: V.- | Q119: 1 | T119: 1 | X119: 1 | Z119: =IF(AS119<0.6,"0.60",AS119) -> 0.88 | AC119: =Z119*X119*T119*P119 -> 0 | AG119: 1 | AJ119: =K119*AC119*AG119 -> 0 | AP119: 75 | AQ119: 10 | AR119: =AP119-AQ119 -> 65 | AS119: =ROUND(((0.1*AP119)+(0.9*AR119))/AP119,2) -> 0.88
A120: VI.- | Q120: 1 | T120: 1 | X120: 1 | Z120: =IF(AS120<0.6,"0.60",AS120) -> 0.88 | AC120: =Z120*X120*T120*P120 -> 0 | AG120: 1 | AJ120: =K120*AC120*AG120 -> 0 | AP120: 75 | AQ120: 10 | AR120: =AP120-AQ120 -> 65 | AS120: =ROUND(((0.1*AP120)+(0.9*AR120))/AP120,2) -> 0.88
A121: VII.- | Q121: 1 | T121: 1 | X121: 1 | Z121: =IF(AS121<0.6,"0.60",AS121) -> 0.88 | AC121: =Z121*X121*T121*P121 -> 0 | AG121: 1 | AJ121: =K121*AC121*AG121 -> 0 | AP121: 75 | AQ121: 10 | AR121: =AP121-AQ121 -> 65 | AS121: =ROUND(((0.1*AP121)+(0.9*AR121))/AP121,2) -> 0.88
A122: VIII.- | Q122: 1 | T122: 1 | X122: 1 | Z122: =IF(AS122<0.6,"0.60",AS122) -> 0.88 | AC122: =Z122*X122*T122*P122 -> 0 | AG122: 1 | AJ122: =K122*AC122*AG122 -> 0 | AP122: 75 | AQ122: 10 | AR122: =AP122-AQ122 -> 65 | AS122: =ROUND(((0.1*AP122)+(0.9*AR122))/AP122,2) -> 0.88
C123: TOTAL: | K123: =SUM(K115:K122) -> 74.2 | AH123: VALOR DE LAS CONSTRUCCIONES: | AJ123: =SUM(AJ115:AJ122) -> 835989.01 | AN123: =AJ123/$AJ$159 -> 0.46183497
C125: C) DE LAS CONSTRUCCIONES ACCESORIAS: | P125: VALOR NUEVO | T125: DEMÉRITO: | AC125: VALOR | AG125: INDIVISO: | AJ125: VALOR
A126: TIPO: | C126: DESCRIPCIÓN | K126: SUPERFICIE: | T126: CONS | X126: PROYECTO | Z126: EDAD | AC126: USADO | AJ126: RESULTANTE: | AP126: NUEVA | AQ126: EDAD | AR126: REMANENTE
A127: I.- | C127: . | K127: 0 | P127: 0 | T127: 0.85 | X127: 1 | Z127: =IF(AS127<0.2,"0.20",AS127) -> 0.73 | AC127: =Z127*X127*T127*P127 -> 0 | AG127: 1 | AJ127: =K127*AC127*AG127 -> 0 | AP127: =+F86 -> 70 | AQ127: =+A86 -> 21 | AR127: =AP127-AQ127 -> 49 | AS127: =ROUND(((0.1*AP127)+(0.9*AR127))/AP127,2) -> 0.73
A128: II.- | C128: . | T128: 1 | X128: 1 | Z128: =IF(AS128<0.6,"0.60",AS128) -> 0.73 | AC128: =Z128*X128*T128*P128 -> 0 | AG128: 1 | AJ128: =K128*AC128*AG128 -> 0 | AP128: =+AP127 -> 70 | AQ128: =+AQ127 -> 21 | AR128: =AP128-AQ128 -> 49 | AS128: =ROUND(((0.1*AP128)+(0.9*AR128))/AP128,2) -> 0.73
A129: III.- | T129: 1 | X129: 1 | Z129: =IF(AS129<0.6,"0.60",AS129) -> 0.73 | AC129: =Z129*X129*T129*P129 -> 0 | AG129: 1 | AJ129: =K129*AC129*AG129 -> 0 | AP129: =+AP128 -> 70 | AQ129: =+AQ128 -> 21 | AR129: =AP129-AQ129 -> 49 | AS129: =ROUND(((0.1*AP129)+(0.9*AR129))/AP129,2) -> 0.73
A130: IV.- | T130: 1 | X130: 1 | Z130: =IF(AS130<0.6,"0.60",AS130) -> 0.73 | AC130: =Z130*X130*T130*P130 -> 0 | AG130: 1 | AJ130: =K130*AC130*AG130 -> 0 | AP130: =+AP129 -> 70 | AQ130: =+AQ129 -> 21 | AR130: =AP130-AQ130 -> 49 | AS130: =ROUND(((0.1*AP130)+(0.9*AR130))/AP130,2) -> 0.73
A131: V.- | T131: 1 | X131: 1 | Z131: =IF(AS131<0.6,"0.60",AS131) -> 0.88 | AC131: =Z131*X131*T131*P131 -> 0 | AG131: 1 | AJ131: =K131*AC131*AG131 -> 0 | AP131: 75 | AQ131: 10 | AR131: =AP131-AQ131 -> 65 | AS131: =ROUND(((0.1*AP131)+(0.9*AR131))/AP131,2) -> 0.88
A132: VI.- | T132: 1 | X132: 1 | Z132: =IF(AS132<0.6,"0.60",AS132) -> 0.88 | AC132: =Z132*X132*T132*P132 -> 0 | AG132: 1 | AJ132: =K132*AC132*AG132 -> 0 | AP132: 75 | AQ132: 10 | AR132: =AP132-AQ132 -> 65 | AS132: =ROUND(((0.1*AP132)+(0.9*AR132))/AP132,2) -> 0.88
A133: VII.- | T133: 1 | X133: 1 | Z133: =IF(AS133<0.6,"0.60",AS133) -> 0.88 | AC133: =Z133*X133*T133*P133 -> 0 | AG133: 1 | AJ133: =K133*AC133*AG133 -> 0 | AP133: 75 | AQ133: 10 | AR133: =AP133-AQ133 -> 65 | AS133: =ROUND(((0.1*AP133)+(0.9*AR133))/AP133,2) -> 0.88
A134: VIII.- | T134: 1 | X134: 1 | Z134: =IF(AS134<0.6,"0.60",AS134) -> 0.88 | AC134: =Z134*X134*T134*P134 -> 0 | AG134: 1 | AJ134: =K134*AC134*AG134 -> 0 | AP134: 75 | AQ134: 10 | AR134: =AP134-AQ134 -> 65 | AS134: =ROUND(((0.1*AP134)+(0.9*AR134))/AP134,2) -> 0.88
C135: TOTAL: | K135: =SUM(K127:K134) -> 0 | AH135: VALOR DE LAS CONSTRUCCIONES: | AJ135: =SUM(AJ127:AJ134) -> 0 | AN135: =AJ135/$AJ$159 -> 0
C137: D) INSTALACIONES ADICIONALES, ACCESORIAS O ESPECIALES: | AP137: MOVER EDAD MANUALMENTE CUANDO HAY MEJORAS O AMPLIACIONES
A138: CONCEPTO: | J138: CANTIDAD: | M138: UNIDAD: | P138: VALOR | T138: DEMÉRITO: | AC138: VALOR | AG138: INDIVISO: | AJ138: VALOR
P139: NUEVO | T139: CONSERVACIÓN | Y139: EDAD | AC139: USADO | AJ139: RESULTANTE:
A140: I.- | C140: Techo Provisional | J140: =4.05+7.36 -> 11.41 | M140: m2 | P140: 850 | T140: 0.91 | Y140: =+AS140 -> 0.96 | AC140: =P140*T140*Y140 -> 742.56 | AG140: 1 | AJ140: =J140*AC140*AG140 -> 8472.6096 | AP140: 60 | AQ140: 3 | AR140: =AP140-AQ140 -> 57 | AS140: =ROUND(((0.1*AP140)+(0.9*AR140))/AP140,2) -> 0.96
A141: II.- | T141: 0.91 | Y141: =+AS141 -> 0.9 | AC141: =P141*T141*Y141 -> 0 | AG141: 1 | AJ141: =J141*AC141*AG141 -> 0 | AP141: 45 | AQ141: 5 | AR141: =AP141-AQ141 -> 40 | AS141: =ROUND(((0.1*AP141)+(0.9*AR141))/AP141,2) -> 0.9
A142: III.- | AC142: =P142*T142*Y142 -> 0 | AG142: 1 | AJ142: =J142*AC142*AG142 -> 0 | AP142: 45 | AQ142: 4 | AR142: =AP142-AQ142 -> 41 | AS142: =ROUND(((0.1*AP142)+(0.9*AR142))/AP142,2) -> 0.92
A143: IV.- | AC143: =P143*T143*Y143 -> 0 | AG143: 1 | AJ143: =J143*AC143*AG143 -> 0 | AP143: 70 | AQ143: 0 | AR143: =AP143-AQ143 -> 70 | AS143: =ROUND(((0.1*AP143)+(0.9*AR143))/AP143,2) -> 1
A144: V.- | AC144: =P144*T144*Y144 -> 0 | AG144: 1 | AJ144: =J144*AC144*AG144 -> 0 | AP144: 70 | AQ144: 16 | AR144: 0 | AS144: =ROUND(((0.1*AP144)+(0.9*AR144))/AP144,2) -> 0.1
T145: 1 | Y145: =+AS145 -> 0.78 | AC145: =P145*T145*Y145 -> 0 | AG145: 1 | AJ145: =J145*AC145*AG145 -> 0 | AP145: 60 | AQ145: 15 | AR145: =AP145-AQ145 -> 45 | AS145: =ROUND(((0.1*AP145)+(0.9*AR145))/AP145,2) -> 0.78
T146: 1 | Y146: =+AS146 -> 0.72 | AC146: =P146*T146*Y146 -> 0 | AG146: 1 | AJ146: =J146*AC146*AG146 -> 0 | AP146: 45 | AQ146: 14 | AR146: =AP146-AQ146 -> 31 | AS146: =ROUND(((0.1*AP146)+(0.9*AR146))/AP146,2) -> 0.72
...

Sheet Formulario Rta
A1: TIEMPO RENTA | B1: OCUPACION | C1: SEXO | D1: EDAD | E1: PROCEDENCIA | F1: INGRESOS | G1: INTERES | H1: TRANSPORTE | I1: CERCANIA | J1: BAÑO | K1: PREFERENCIAS | L1: HORARIOS | M1: TOPE PRESUPUESTO | N1: NOMBRE | O1: CONTACTO

Sheet Estructura Formulario
A1: Form Title: | B1: Description: | C1: URL Formulario Edición | D1: URL Formulario Producción
A2: Esto es una prueba | B2: Esto es otra prueba | C2: https://docs.google.com/forms/d/1jOj5Q_ITljql8OtieIXmQVCeRM0Epbu7PfoN4C9rKQI/edit | D2: https://forms.gle/VXjT7o5P9uFxPA2bA
E3: Opciones
A4: Tipo Pregunta | B4: Descripción de la Pregunta | C4: Tipo Atributo | D4: Opción Requerida ? | E4: Op1 | F4: Op2 | G4: Op3 | H4: Op4 | I4: Op5 | J4: Op6 | K4: Op7
A5: TIEMPO RENTA | B5: Prueba | C5: Texto | D5: TRUE
A6: OCUPACION | B6: Prueba | C6: Texto | D6: TRUE
A7: SEXO | B7: Prueba | C7: Texto | D7: TRUE
A8: EDAD | B8: Prueba | C8: Varias Opciones | D8: TRUE | E8: aSD | F8: ASDA
A9: PROCEDENCIA | B9: Prueba | C9: Texto | D9: TRUE
A10: INGRESOS | B10: Prueba | C10: Desplegable | D10: TRUE | E10: DASDQ32 | F10: 213ESAD | G10: WSDAS2 | H10: 21E
A11: INTERES | B11: Prueba | C11: Parrafo | D11: FALSE
A12: TRANSPORTE | B12: Prueba | C12: Parrafo | D12: FALSE
A13: CERCANIA | B13: Prueba | C13: Parrafo | D13: FALSE
A14: BAÑO | B14: Prueba | C14: Parrafo | D14: FALSE
A15: PREFERENCIAS | B15: Prueba | C15: Parrafo | D15: FALSE
A16: HORARIOS | B16: Prueba | C16: Parrafo | D16: FALSE
A17: TOPE PRESUPUESTO | B17: Prueba | C17: Casilla | D17: FALSE | E17: DASD2E | F17: QWD21EDAS | G17: Q2E21EDQW | H17: ASD2E12 | I17: AD2ER12
A18: NOMBRE | B18: Prueba | C18: Parrafo | D18: FALSE
A19: CONTACTO | B19: Prueba | C19: Parrafo | D19: FALSE

Sheet Mercado
A2: ESTUDIO DE MERCADO DE VENTAS TERRENOS | H2: COMPARABLES DE VENTA
A3: Fecha | B3: ESTATUS COMERCIAL: | C3: TIPO: | D3: CIUDAD | E3: Colonia | F3: DIRECCIÓN: | G3: COMENT: | H3: TERRENO | I3: CONST | J3: PRECIO: | K3: $ por m2 | L3: FUENTE: | M3: TELÉFONO: | N3: LINK:
B4: VENTA | C4: ='OPI Terreno'!E8 | E4: Rancho Nuevo 1ra. Sección | H4: 365 | J4: 3150000 | K4: =J4/H4 -> 8630.137 | N4: https://www.casasyterrenos.com/propiedad/terreno-venta-eutimio-pinzon-rancho-nuevo-1ra-seccion-guadalajara-jal-3779336
B5: =+B4 -> VENTA | C5: =C4
B6: =+B5 -> VENTA | C6: =C5 | E6: Independencia | H6: 200 | J6: 2400000 | K6: =J6/H6 -> 12000 | N6: https://www.inmuebles24.com/propiedades/clasificado/vecltein-venta-de-terreno-en-colonia-independencia-147013498.html?n_src=Listado&n_exp=trigger_pills-original&n_pg=1&n_pos=1
B7: =+B6 -> VENTA | C7: =C6
B8: =+B7 -> VENTA | C8: =C7
B9: =+B8 -> VENTA | K9: =+AVERAGE(K4,K5,K6,K7,K8) -> 10315.068
A11: OTROS COMPARABLES DE TERRENO
K12: =J12/H12 -> #DIV/0!
K13: =J13/H13 -> #DIV/0!
K14: =J14/H14 -> #DIV/0!
K15: =J15/H15 -> #DIV/0!
K16: =J16/H16 -> #DIV/0!
A18: ESTUDIO RESIDUAL DE TERRENO | H18: COMPARABLES DE VENTA
A19: Fecha | B19: ESTATUS COMERCIAL: | C19: TIPO: | D19: CIUDAD | E19: Colonia | F19: DIRECCIÓN: | G19: COMENT: | H19: TERRENO | I19: CONST | J19: PRECIO: | K19: EDAD | L19: ESTADO CONSERV. | M19: FACTOR | N19: $/M2 CONST. Usado | O19: VALOR CONST. | P19: VALOR TERRENO | Q19: $/M2 TERRENO
B20: VENTA | C20: =+'OPI Constr'!$E$8 -> Casa Habitación | D20: =D30 | E20: =E30 -> SAN ELIAS | F20: =F30 -> Avenida Fidel Velazquez 380 | G20: =G30 -> 1 Nivel 3 Recamaras con closet Cocina con alacenas estufas Área Sala-Comedor 1 Baño completo Patio amplio con Jardín | H20: =H30 -> 117 | I20: =I30 -> 71 | J20: =J30 -> 2700000 | K20: =L30 -> 40 | L20: Bueno | M20: =IF(L20<>"",VLOOKUP(K20,'Ross Heideke'!$A$6:$J$76,MATCH(L20,'Ross Heideke'!$B$5:$J$5,0),FALSE),"") -> 0.55084408 | N20: =+IF(M20<>"",'OPI Constr'!$N$115*$M20,"") -> 7436.3951 | O20: =+IF(N20<>"",N20*I20,"") -> 527984.05 | P20: =+IF(O20<>"",J20-O20,"") -> 2172015.9 | Q20: =+IF(P20<>"",P20/H20,"") -> 18564.239
B21: =+B20 -> VENTA | C21: =+C20 -> Casa Habitación | D21: =D31 | E21: =E31 -> INDEPENDENCIA | F21: =F31 -> Platón S/N | G21: =G31 -> 3 Recámaras 2 1/2 Baños 3 Cocheras Terraza al ingreso de la casa 1 Área de lavado Local comercial al frente de 35.00 mts con medio baño. | H21: =H31 -> 276 | I21: =I31 -> 193 | J21: =J31 -> 6600000 | K21: =L31 -> 30 | L21: Bueno | M21: =IF(L21<>"",VLOOKUP(K21,'Ross Heideke'!$A$6:$J$76,MATCH(L21,'Ross Heideke'!$B$5:$J$5,0),FALSE),"") -> 0.69365551 | N21: =+IF(M21<>"",'OPI Constr'!$N$115*$M21,"") -> 9364.3494 | O21: =+IF(N21<>"",N21*I21,"") -> 1807319.4 | P21: =+IF(O21<>"",J21-O21,"") -> 4792680.6 | Q21: =+IF(P21<>"",P21/H21,"") -> 17364.785 | Z21: =+(L30-20)/20 -> 1
B22: =+B21 -> VENTA | C22: =+C21 -> Casa Habitación | D22: =D32 | E22: =E32 -> Monumental | F22: =F32 -> Monumental S/N | G22: =G32 -> Cochera un auto, jardín exterior, sala comedor, cocina, patio de servicio, pasillo distribuidor, dos recámara secundarias cada una con su clóset que comparten un baño completo y otra principal con baño completo, jardín interior. | H22: =H32 -> 140 | I22: =I32 -> 103 | J22: =J32 -> 3790000 | K22: =L32 -> 6 | L22: Bueno | M22: =IF(L22<>"",VLOOKUP(K22,'Ross Heideke'!$A$6:$J$76,MATCH(L22,'Ross Heideke'!$B$5:$J$5,0),FALSE),"") -> 0.95316428 | N22: =+IF(M22<>"",'OPI Constr'!$N$115*$M22,"") -> 12867.718 | O22: =+IF(N22<>"",N22*I22,"") -> 1325374.9 | P22: =+IF(O22<>"",J22-O22,"") -> 2464625.1 | Q22: =+IF(P22<>"",P22/H22,"") -> 17604.465
B23: =+B22 -> VENTA | C23: =+C22 -> Casa Habitación | D23: =D33 | E23: =E33 -> Alcalde Barranquitas | F23: =F33 -> Avenida de los Maestros 576 | G23: =G33 -> 4 recámaras, 2 baños uso de suelo mixto, comercial y habitacional, cuarto de servicio con baño, área de lavandería | H23: =H33 -> 314 | I23: =I33 -> 201 | J23: =J33 -> 7500000 | K23: =L33 -> 40 | L23: Bueno | M23: =IF(L23<>"",VLOOKUP(K23,'Ross Heideke'!$A$6:$J$76,MATCH(L23,'Ross Heideke'!$B$5:$J$5,0),FALSE),"") -> 0.55084408 | N23: =+IF(M23<>"",'OPI Constr'!$N$115*$M23,"") -> 7436.3951 | O23: =+IF(N23<>"",N23*I23,"") -> 1494715.4 | P23: =+IF(O23<>"",J23-O23,"") -> 6005284.6 | Q23: =+IF(P23<>"",P23/H23,"") -> 19125.11
B24: =+B23 -> VENTA | C24: =+C23 -> Casa Habitación | D24: =D34 | E24: =E34 -> Independencia Oriente | F24: =F34 -> Los Alpes 1548 | G24: =G34 -> Sala y comedor Cocina integral 5 recámaras, 2 baños completos, Jardín lateral, espacio para 1 auto | H24: =H34 -> 175 | I24: =I34 -> 158 | J24: =J34 -> 4200000 | K24: =L34 -> 40 | L24: Bueno | M24: =IF(L24<>"",VLOOKUP(K24,'Ross Heideke'!$A$6:$J$76,MATCH(L24,'Ross Heideke'!$B$5:$J$5,0),FALSE),"") -> 0.55084408 | N24: =+IF(M24<>"",'OPI Constr'!$N$115*$M24,"") -> 7436.3951 | O24: =+IF(N24<>"",N24*I24,"") -> 1174950.4 | P24: =+IF(O24<>"",J24-O24,"") -> 3025049.6 | Q24: =+IF(P24<>"",P24/H24,"") -> 17285.998
B25: =+B24 -> VENTA | C25: =+C24 -> Casa Habitación | Q25: =+AVERAGE(Q20:Q24) -> 17988.919
A28: ESTUDIO DE MERCADO DE VENTAS CONSTRUCCIONES | H28: COMPARABLES DE VENTA
A29: Fecha | B29: ESTATUS COMERCIAL: | C29: TIPO: | D29: CIUDAD | E29: Colonia | F29: DIRECCIÓN: | G29: COMENT: | H29: TERRENO | I29: CONST | J29: PRECIO: | K29: $ por m2 | L29: EDAD: | M29: FUENTE: | N29: TELÉFONO: | O29: LINK:
B30: VENTA | C30: =+'OPI Constr'!$E$8 -> Casa Habitación | E30: SAN ELIAS | F30: Avenida Fidel Velazquez 380 | G30: 1 Nivel 3 Recamaras con closet Cocina con alacenas estufas Área Sala-Comedor 1 Baño completo Patio amplio con Jardín | H30: 117 | I30: 71 | J30: 2700000 | K30: =J30/I30 -> 38028.169 | L30: 40 | M30: GPM BIENES RAICES | N30: 33 1305 0083 | O30: https://www.inmuebles24.com/propiedades/clasificado/veclcain-casa-en-venta.-fraccionamiento-estadio-poniente-147959813.html?n_src=Listado&n_exp=trigger_pills-original&n_pg=1&n_pos=1
B31: =+B30 -> VENTA | C31: =+C30 -> Casa Habitación | E31: INDEPENDENCIA | F31: Platón S/N | G31: 3 Recámaras 2 1/2 Baños 3 Cocheras Terraza al ingreso de la casa 1 Área de lavado Local comercial al frente de 35.00 mts con medio baño. | H31: 276 | I31: 193 | J31: 6600000 | K31: =J31/I31 -> 34196.891 | L31: 30 | M31: Impacto Inmobiliaria | N31: 33 3485 2244 | O31: https://www.inmuebles24.com/propiedades/clasificado/veclcain-casa-en-venta-calle-platon-col.-independencia-146764086.html?n_src=Listado&n_exp=trigger_pills-original&n_pg=1&n_pos=1
B32: =+B31 -> VENTA | C32: =+C31 -> Casa Habitación | E32: Monumental | F32: Monumental S/N | G32: Cochera un auto, jardín exterior, sala comedor, cocina, patio de servicio, pasillo distribuidor, dos recámara secundarias cada una con su clóset que comparten un baño completo y otra principal con baño completo, jardín interior. | H32: 140 | I32: 103 | J32: 3790000 | K32: =J32/I32 -> 36796.116 | L32: 6 | M32: Enf Comercializadora | N32: 5664068640 | O32: https://www.inmuebles24.com/propiedades/clasificado/veclcapa-espectacular-casa-col-monumental-147753528.html?n_src=Listado&n_exp=trigger_pills-original&n_pg=1&n_pos=1
B33: =+B32 -> VENTA | C33: =+C32 -> Casa Habitación | E33: Alcalde Barranquitas | F33: Avenida de los Maestros 576 | G33: 4 recámaras, 2 baños uso de suelo mixto, comercial y habitacional, cuarto de servicio con baño, área de lavandería | H33: 314 | I33: 201 | J33: 7500000 | K33: =J33/I33 -> 37313.433 | L33: 40 | M33: iad Inmobiliaria | N33: 5513289530 | O33: https://www.inmuebles24.com/propiedades/clasificado/veclcain-casa-en-venta-en-alcalde-barranquitas-143208861.html?n_src=Listado&n_exp=trigger_pills-original&n_pg=1&n_pos=1
B34: =+B33 -> VENTA | C34: =+C33 -> Casa Habitación | E34: Independencia Oriente | F34: Los Alpes 1548 | G34: Sala y comedor Cocina integral 5 recámaras, 2 baños completos, Jardín lateral, espacio para 1 auto | H34: 175 | I34: 158 | J34: 4200000 | K34: =J34/I34 -> 26582.278 | L34: 40 | M34: Casa Administraciones | N34: 33 3040 8700 | O34: https://www.inmuebles24.com/propiedades/clasificado/veclcain-casa-en-venta-de-un-nivel-en-la-colonia-independencia-147097244.html?n_src=Listado&n_exp=trigger_pills-original&n_pg=1&n_pos=1
B35: =+B34 -> VENTA | C35: =+C34 -> Casa Habitación | K35: =+AVERAGE(K30,K31,K32,K33,K34) -> 34583.378
A37: OTROS COMPARABLES DE VENTA
H38: 200 | I38: 198 | J38: 4100000 | K38: =J38/I38 -> 20707.071 | L38: 40 | O38: https://www.inmuebles24.com/propiedades/clasificado/veclcain-casa-en-belisario-dominguez-gdl-148141350.html?n_src=Listado&n_exp=trigger_pills-original&n_pg=1&n_pos=1
H39: 120 | I39: 140 | J39: 3250000 | K39: =J39/I39 -> 23214.286 | L39: 30 | O39: https://www.inmuebles24.com/propiedades/clasificado/veclcain-casa-con-departamento-independiente-cerca-del-148214120.html?n_src=Listado&n_exp=trigger_pills-original&n_pg=1&n_pos=1
K41: =J41/I41 -> #DIV/0!
K42: =J42/I42 -> #DIV/0!
A45: ESTUDIO MERCADO RENTAS CONSTRUCCIONES | H45: COMPARABLES DE RENTA
A46: FECHA | B46: ESTATUS COMERCIAL: | C46: TIPO: | D46: CIUDAD | E46: COLONIA | F46: DIRECCIÓN: | G46: COMENT: | H46: COMENT: | I46: TERRENO | J46: CONST | K46: RENTA | L46: $ X M2 RENTA | M46: PRECIO HOMOLOGADO SUJETO: | N46: $/m2 VALOR DE VENTA | O46: EDAD: | P46: FUENTE: | Q46: TELÉFONO: | R46: LINK:
B47: RENTA | C47: =+C30 -> Casa Habitación | L47: =+K47/J47 -> #DIV/0! | M47: =+L47*'OPI Constr'!$K$123 -> #DIV/0! | N47: =+(L47*12-(L47*12*0.2839))/0.0661 -> #DIV/0!
B48: =+B47 -> RENTA | C48: =+C47 -> Casa Habitación | L48: =+K48/J48 -> #DIV/0! | M48: =+L48*'OPI Constr'!$K$123 -> #DIV/0! | N48: =+(L48*12-(L48*12*0.2839))/0.0661 -> #DIV/0!
B49: =+B48 -> RENTA | C49: =+C48 -> Casa Habitación | L49: =+K49/J49 -> #DIV/0! | M49: =+L49*'OPI Constr'!$K$123 -> #DIV/0! | N49: =+(L49*12-(L49*12*0.2839))/0.0661 -> #DIV/0!
B50: =+B49 -> RENTA | C50: =+C49 -> Casa Habitación | L50: =+K50/J50 -> #DIV/0! | M50: =+L50*'OPI Constr'!$K$123 -> #DIV/0! | N50: =+(L50*12-(L50*12*0.2839))/0.0661 -> #DIV/0!
B51: =+B50 -> RENTA | C51: =+C50 -> Casa Habitación | L51: =+K51/J51 -> #DIV/0! | M51: =+L51*'OPI Constr'!$K$123 -> #DIV/0! | N51: =+(L51*12-(L51*12*0.2839))/0.0661 -> #DIV/0!
C52: =+C51 -> Casa Habitación
A54: OTROS COMPARABLES DE RENTA
O55: VALOR TERRENO /M2 | P55: REC: | Q55: BAÑOS | R55: AUTOS | S55: NIVELES
O56: VALOR TERRENO /M3
O57: VALOR TERRENO /M4
O58: VALOR TERRENO /M5
O59: VALOR TERRENO /M6
A61: ESTUDIO MERCADO RENTAS TERRENOS | H61: COMPARABLES DE RENTA
A62: FECHA | B62: ESTATUS COMERCIAL: | C62: TIPO: | D62: CIUDAD | E62: COLONIA | F62: DIRECCIÓN: | G62: COMENT: | H62: COMENT: | I62: TERRENO | J62: CONST | K62: RENTA | L62: $ X M2 RENTA | M62: PRECIO HOMOLOGADO SUJETO: | N62: $/m2 VALOR DE VENTA | O62: EDAD: | P62: FUENTE: | Q62: TELÉFONO: | R62: LINK:
B63: RENTA | C63: =+C46 -> TIPO: | L63: =+K63/I63 -> #DIV/0! | M63: =+L63*'OPI Constr'!$C$121 -> #DIV/0! | N63: =+(L63*12-(L63*12*0.2839))/0.0661 -> #DIV/0!
B64: =+B63 -> RENTA | C64: =+C63 -> TIPO: | L64: =+K64/I64 -> #DIV/0! | M64: =+L64*'OPI Constr'!$C$121 -> #DIV/0! | N64: =+(L64*12-(L64*12*0.2839))/0.0661 -> #DIV/0!
B65: =+B64 -> RENTA | C65: =+C64 -> TIPO: | L65: =+K65/I65 -> #DIV/0! | M65: =+L65*'OPI Constr'!$C$121 -> #DIV/0! | N65: =+(L65*12-(L65*12*0.2839))/0.0661 -> #DIV/0!
B66: =+B65 -> RENTA | C66: =+C65 -> TIPO: | L66: =+K66/I66 -> #DIV/0! | M66: =+L66*'OPI Constr'!$C$121 -> #DIV/0! | N66: =+(L66*12-(L66*12*0.2839))/0.0661 -> #DIV/0!
B67: =+B66 -> RENTA | C67: =+C66 -> TIPO: | L67: =+K67/I67 -> #DIV/0! | M67: =+L67*'OPI Constr'!$C$121 -> #DIV/0! | N67: =+(L67*12-(L67*12*0.2839))/0.0661 -> #DIV/0!
C68: =+C67 -> TIPO:
A70: OTROS COMPARABLES DE RENTA
L71: =+K71/I71 -> #DIV/0! | O71: VALOR TERRENO /M2 | P71: REC: | Q71: BAÑOS | R71: AUTOS | S71: NIVELES
L72: =+K72/I72 -> #DIV/0! | O72: VALOR TERRENO /M3
L73: =+K73/I73 -> #DIV/0! | O73: VALOR TERRENO /M4
L74: =+K74/I74 -> #DIV/0! | O74: VALOR TERRENO /M5
L75: =+K75/I75 -> #DIV/0! | O75: VALOR TERRENO /M6

Sheet Ross Heideke
A1: Vida útil: | B1: 70
A2: PARA USAR ESTA TABLA SOLO TECLEA EL NUMERO DE AÑOS DE LA FINCA EN EL CUADRO ROJO Y LE DARA LOS VALORES
A3: 1 | B3: 2 | C3: 3 | D3: 4 | E3: 5 | F3: 6 | G3: 7 | H3: 8 | I3: 9 | J3: 10
A4: ESTADO DE CONSERVACIÓN
A5: EDAD DEL INMUEBLE | B5: Nuevo | C5: Muy Bueno | D5: Bueno | E5: Regular | F5: Remodelado - | G5: Remodelado + | H5: Rehabilitación completa | I5: Ruinoso | J5: Ruinoso Inutilizable | L5: Nuevo
A6: 0 | B6: 1 | C6: =1-0.00032 -> 0.99968 | D6: =1-0.0252 -> 0.9748 | E6: =1-0.0809 -> 0.9191 | F6: =1-0.181 -> 0.819 | G6: =1-0.332 -> 0.668 | H6: =1-0.526 -> 0.474 | I6: =1-0.752 -> 0.248 | J6: 0.1 | L6: Muy Bueno
A7: 1 | B7: =(1-(0.5*(($A7/$B$1)+(($A7/$B$1)^2))))*$B$6 -> 0.9927551 | C7: =(1-(0.5*(($A7/$B$1)+(($A7/$B$1)^2))))*$C$6 -> 0.99243742 | D7: =(1-(0.5*(($A7/$B$1)+(($A7/$B$1)^2))))*$D$6 -> 0.96773767 | E7: =(1-(0.5*(($A7/$B$1)+(($A7/$B$1)^2))))*$E$6 -> 0.91244121 | F7: =(1-(0.5*(($A7/$B$1)+(($A7/$B$1)^2))))*$F$6 -> 0.81306643 | G7: =(1-(0.5*(($A7/$B$1)+(($A7/$B$1)^2))))*$G$6 -> 0.66316041 | H7: =(1-(0.5*(($A7/$B$1)+(($A7/$B$1)^2))))*$H$6 -> 0.47056592 | I7: =(1-(0.5*(($A7/$B$1)+(($A7/$B$1)^2))))*$I$6 -> 0.24620327 | J7: =(1-(0.5*(($A7/$B$1)+(($A7/$B$1)^2))))*$J$6 -> 0.09927551 | L7: Bueno
A8: 2 | B8: =(1-(0.5*(($A8/$B$1)+(($A8/$B$1)^2))))*$B$6 -> 0.98530612 | C8: =(1-(0.5*(($A8/$B$1)+(($A8/$B$1)^2))))*$C$6 -> 0.98499082 | D8: =(1-(0.5*(($A8/$B$1)+(($A8/$B$1)^2))))*$D$6 -> 0.96047641 | E8: =(1-(0.5*(($A8/$B$1)+(($A8/$B$1)^2))))*$E$6 -> 0.90559486 | F8: =(1-(0.5*(($A8/$B$1)+(($A8/$B$1)^2))))*$F$6 -> 0.80696571 | G8: =(1-(0.5*(($A8/$B$1)+(($A8/$B$1)^2))))*$G$6 -> 0.65818449 | H8: =(1-(0.5*(($A8/$B$1)+(($A8/$B$1)^2))))*$H$6 -> 0.4670351 | I8: =(1-(0.5*(($A8/$B$1)+(($A8/$B$1)^2))))*$I$6 -> 0.24435592 | J8: =(1-(0.5*(($A8/$B$1)+(($A8/$B$1)^2))))*$J$6 -> 0.098530612 | L8: Regular
A9: 3 | B9: =(1-(0.5*(($A9/$B$1)+(($A9/$B$1)^2))))*$B$6 -> 0.97765306 | C9: =(1-(0.5*(($A9/$B$1)+(($A9/$B$1)^2))))*$C$6 -> 0.97734021 | D9: =(1-(0.5*(($A9/$B$1)+(($A9/$B$1)^2))))*$D$6 -> 0.9530162 | E9: =(1-(0.5*(($A9/$B$1)+(($A9/$B$1)^2))))*$E$6 -> 0.89856093 | F9: =(1-(0.5*(($A9/$B$1)+(($A9/$B$1)^2))))*$F$6 -> 0.80069786 | G9: =(1-(0.5*(($A9/$B$1)+(($A9/$B$1)^2))))*$G$6 -> 0.65307224 | H9: =(1-(0.5*(($A9/$B$1)+(($A9/$B$1)^2))))*$H$6 -> 0.46340755 | I9: =(1-(0.5*(($A9/$B$1)+(($A9/$B$1)^2))))*$I$6 -> 0.24245796 | J9: =(1-(0.5*(($A9/$B$1)+(($A9/$B$1)^2))))*$J$6 -> 0.097765306 | L9: Remodelado -
A10: 4 | B10: =(1-(0.5*(($A10/$B$1)+(($A10/$B$1)^2))))*$B$6 -> 0.96979592 | C10: =(1-(0.5*(($A10/$B$1)+(($A10/$B$1)^2))))*$C$6 -> 0.96948558 | D10: =(1-(0.5*(($A10/$B$1)+(($A10/$B$1)^2))))*$D$6 -> 0.94535706 | E10: =(1-(0.5*(($A10/$B$1)+(($A10/$B$1)^2))))*$E$6 -> 0.89133943 | F10: =(1-(0.5*(($A10/$B$1)+(($A10/$B$1)^2))))*$F$6 -> 0.79426286 | G10: =(1-(0.5*(($A10/$B$1)+(($A10/$B$1)^2))))*$G$6 -> 0.64782367 | H10: =(1-(0.5*(($A10/$B$1)+(($A10/$B$1)^2))))*$H$6 -> 0.45968327 | I10: =(1-(0.5*(($A10/$B$1)+(($A10/$B$1)^2))))*$I$6 -> 0.24050939 | J10: =(1-(0.5*(($A10/$B$1)+(($A10/$B$1)^2))))*$J$6 -> 0.096979592 | L10: Remodelado +
A11: 5 | B11: =(1-(0.5*(($A11/$B$1)+(($A11/$B$1)^2))))*$B$6 -> 0.96173469 | C11: =(1-(0.5*(($A11/$B$1)+(($A11/$B$1)^2))))*$C$6 -> 0.96142694 | D11: =(1-(0.5*(($A11/$B$1)+(($A11/$B$1)^2))))*$D$6 -> 0.93749898 | E11: =(1-(0.5*(($A11/$B$1)+(($A11/$B$1)^2))))*$E$6 -> 0.88393036 | F11: =(1-(0.5*(($A11/$B$1)+(($A11/$B$1)^2))))*$F$6 -> 0.78766071 | G11: =(1-(0.5*(($A11/$B$1)+(($A11/$B$1)^2))))*$G$6 -> 0.64243878 | H11: =(1-(0.5*(($A11/$B$1)+(($A11/$B$1)^2))))*$H$6 -> 0.45586224 | I11: =(1-(0.5*(($A11/$B$1)+(($A11/$B$1)^2))))*$I$6 -> 0.2385102 | J11: =(1-(0.5*(($A11/$B$1)+(($A11/$B$1)^2))))*$J$6 -> 0.096173469 | L11: Rehabilitación completa
A12: 6 | B12: =(1-(0.5*(($A12/$B$1)+(($A12/$B$1)^2))))*$B$6 -> 0.95346939 | C12: =(1-(0.5*(($A12/$B$1)+(($A12/$B$1)^2))))*$C$6 -> 0.95316428 | D12: =(1-(0.5*(($A12/$B$1)+(($A12/$B$1)^2))))*$D$6 -> 0.92944196 | E12: =(1-(0.5*(($A12/$B$1)+(($A12/$B$1)^2))))*$E$6 -> 0.87633371 | F12: =(1-(0.5*(($A12/$B$1)+(($A12/$B$1)^2))))*$F$6 -> 0.78089143 | G12: =(1-(0.5*(($A12/$B$1)+(($A12/$B$1)^2))))*$G$6 -> 0.63691755 | H12: =(1-(0.5*(($A12/$B$1)+(($A12/$B$1)^2))))*$H$6 -> 0.45194449 | I12: =(1-(0.5*(($A12/$B$1)+(($A12/$B$1)^2))))*$I$6 -> 0.23646041 | J12: =(1-(0.5*(($A12/$B$1)+(($A12/$B$1)^2))))*$J$6 -> 0.095346939 | L12: Ruinoso
A13: 7 | B13: =(1-(0.5*(($A13/$B$1)+(($A13/$B$1)^2))))*$B$6 -> 0.945 | C13: =(1-(0.5*(($A13/$B$1)+(($A13/$B$1)^2))))*$C$6 -> 0.9446976 | D13: =(1-(0.5*(($A13/$B$1)+(($A13/$B$1)^2))))*$D$6 -> 0.921186 | E13: =(1-(0.5*(($A13/$B$1)+(($A13/$B$1)^2))))*$E$6 -> 0.8685495 | F13: =(1-(0.5*(($A13/$B$1)+(($A13/$B$1)^2))))*$F$6 -> 0.773955 | G13: =(1-(0.5*(($A13/$B$1)+(($A13/$B$1)^2))))*$G$6 -> 0.63126 | H13: =(1-(0.5*(($A13/$B$1)+(($A13/$B$1)^2))))*$H$6 -> 0.44793 | I13: =(1-(0.5*(($A13/$B$1)+(($A13/$B$1)^2))))*$I$6 -> 0.23436 | J13: =(1-(0.5*(($A13/$B$1)+(($A13/$B$1)^2))))*$J$6 -> 0.0945 | L13: Ruinoso Inutilizable
A14: 8 | B14: =(1-(0.5*(($A14/$B$1)+(($A14/$B$1)^2))))*$B$6 -> 0.93632653 | C14: =(1-(0.5*(($A14/$B$1)+(($A14/$B$1)^2))))*$C$6 -> 0.93602691 | D14: =(1-(0.5*(($A14/$B$1)+(($A14/$B$1)^2))))*$D$6 -> 0.9127311 | E14: =(1-(0.5*(($A14/$B$1)+(($A14/$B$1)^2))))*$E$6 -> 0.86057771 | F14: =(1-(0.5*(($A14/$B$1)+(($A14/$B$1)^2))))*$F$6 -> 0.76685143 | G14: =(1-(0.5*(($A14/$B$1)+(($A14/$B$1)^2))))*$G$6 -> 0.62546612 | H14: =(1-(0.5*(($A14/$B$1)+(($A14/$B$1)^2))))*$H$6 -> 0.44381878 | I14: =(1-(0.5*(($A14/$B$1)+(($A14/$B$1)^2))))*$I$6 -> 0.23220898 | J14: =(1-(0.5*(($A14/$B$1)+(($A14/$B$1)^2))))*$J$6 -> 0.093632653
A15: 9 | B15: =(1-(0.5*(($A15/$B$1)+(($A15/$B$1)^2))))*$B$6 -> 0.92744898 | C15: =(1-(0.5*(($A15/$B$1)+(($A15/$B$1)^2))))*$C$6 -> 0.9271522 | D15: =(1-(0.5*(($A15/$B$1)+(($A15/$B$1)^2))))*$D$6 -> 0.90407727 | E15: =(1-(0.5*(($A15/$B$1)+(($A15/$B$1)^2))))*$E$6 -> 0.85241836 | F15: =(1-(0.5*(($A15/$B$1)+(($A15/$B$1)^2))))*$F$6 -> 0.75958071 | G15: =(1-(0.5*(($A15/$B$1)+(($A15/$B$1)^2))))*$G$6 -> 0.61953592 | H15: =(1-(0.5*(($A15/$B$1)+(($A15/$B$1)^2))))*$H$6 -> 0.43961082 | I15: =(1-(0.5*(($A15/$B$1)+(($A15/$B$1)^2))))*$I$6 -> 0.23000735 | J15: =(1-(0.5*(($A15/$B$1)+(($A15/$B$1)^2))))*$J$6 -> 0.092744898
A16: 10 | B16: =(1-(0.5*(($A16/$B$1)+(($A16/$B$1)^2))))*$B$6 -> 0.91836735 | C16: =(1-(0.5*(($A16/$B$1)+(($A16/$B$1)^2))))*$C$6 -> 0.91807347 | D16: =(1-(0.5*(($A16/$B$1)+(($A16/$B$1)^2))))*$D$6 -> 0.89522449 | E16: =(1-(0.5*(($A16/$B$1)+(($A16/$B$1)^2))))*$E$6 -> 0.84407143 | F16: =(1-(0.5*(($A16/$B$1)+(($A16/$B$1)^2))))*$F$6 -> 0.75214286 | G16: =(1-(0.5*(($A16/$B$1)+(($A16/$B$1)^2))))*$G$6 -> 0.61346939 | H16: =(1-(0.5*(($A16/$B$1)+(($A16/$B$1)^2))))*$H$6 -> 0.43530612 | I16: =(1-(0.5*(($A16/$B$1)+(($A16/$B$1)^2))))*$I$6 -> 0.2277551 | J16: =(1-(0.5*(($A16/$B$1)+(($A16/$B$1)^2))))*$J$6 -> 0.091836735
A17: 11 | B17: =(1-(0.5*(($A17/$B$1)+(($A17/$B$1)^2))))*$B$6 -> 0.90908163 | C17: =(1-(0.5*(($A17/$B$1)+(($A17/$B$1)^2))))*$C$6 -> 0.90879073 | D17: =(1-(0.5*(($A17/$B$1)+(($A17/$B$1)^2))))*$D$6 -> 0.88617278 | E17: =(1-(0.5*(($A17/$B$1)+(($A17/$B$1)^2))))*$E$6 -> 0.83553693 | F17: =(1-(0.5*(($A17/$B$1)+(($A17/$B$1)^2))))*$F$6 -> 0.74453786 | G17: =(1-(0.5*(($A17/$B$1)+(($A17/$B$1)^2))))*$G$6 -> 0.60726653 | H17: =(1-(0.5*(($A17/$B$1)+(($A17/$B$1)^2))))*$H$6 -> 0.43090469 | I17: =(1-(0.5*(($A17/$B$1)+(($A17/$B$1)^2))))*$I$6 -> 0.22545224 | J17: =(1-(0.5*(($A17/$B$1)+(($A17/$B$1)^2))))*$J$6 -> 0.090908163
A18: 12 | B18: =(1-(0.5*(($A18/$B$1)+(($A18/$B$1)^2))))*$B$6 -> 0.89959184 | C18: =(1-(0.5*(($A18/$B$1)+(($A18/$B$1)^2))))*$C$6 -> 0.89930397 | D18: =(1-(0.5*(($A18/$B$1)+(($A18/$B$1)^2))))*$D$6 -> 0.87692212 | E18: =(1-(0.5*(($A18/$B$1)+(($A18/$B$1)^2))))*$E$6 -> 0.82681486 | F18: =(1-(0.5*(($A18/$B$1)+(($A18/$B$1)^2))))*$F$6 -> 0.73676571 | G18: =(1-(0.5*(($A18/$B$1)+(($A18/$B$1)^2))))*$G$6 -> 0.60092735 | H18: =(1-(0.5*(($A18/$B$1)+(($A18/$B$1)^2))))*$H$6 -> 0.42640653 | I18: =(1-(0.5*(($A18/$B$1)+(($A18/$B$1)^2))))*$I$6 -> 0.22309878 | J18: =(1-(0.5*(($A18/$B$1)+(($A18/$B$1)^2))))*$J$6 -> 0.089959184
A19: 13 | B19: =(1-(0.5*(($A19/$B$1)+(($A19/$B$1)^2))))*$B$6 -> 0.88989796 | C19: =(1-(0.5*(($A19/$B$1)+(($A19/$B$1)^2))))*$C$6 -> 0.88961319 | D19: =(1-(0.5*(($A19/$B$1)+(($A19/$B$1)^2))))*$D$6 -> 0.86747253 | E19: =(1-(0.5*(($A19/$B$1)+(($A19/$B$1)^2))))*$E$6 -> 0.81790521 | F19: =(1-(0.5*(($A19/$B$1)+(($A19/$B$1)^2))))*$F$6 -> 0.72882643 | G19: =(1-(0.5*(($A19/$B$1)+(($A19/$B$1)^2))))*$G$6 -> 0.59445184 | H19: =(1-(0.5*(($A19/$B$1)+(($A19/$B$1)^2))))*$H$6 -> 0.42181163 | I19: =(1-(0.5*(($A19/$B$1)+(($A19/$B$1)^2))))*$I$6 -> 0.22069469 | J19: =(1-(0.5*(($A19/$B$1)+(($A19/$B$1)^2))))*$J$6 -> 0.088989796
A20: 14 | B20: =(1-(0.5*(($A20/$B$1)+(($A20/$B$1)^2))))*$B$6 -> 0.88 | C20: =(1-(0.5*(($A20/$B$1)+(($A20/$B$1)^2))))*$C$6 -> 0.8797184 | D20: =(1-(0.5*(($A20/$B$1)+(($A20/$B$1)^2))))*$D$6 -> 0.857824 | E20: =(1-(0.5*(($A20/$B$1)+(($A20/$B$1)^2))))*$E$6 -> 0.808808 | F20: =(1-(0.5*(($A20/$B$1)+(($A20/$B$1)^2))))*$F$6 -> 0.72072 | G20: =(1-(0.5*(($A20/$B$1)+(($A20/$B$1)^2))))*$G$6 -> 0.58784 | H20: =(1-(0.5*(($A20/$B$1)+(($A20/$B$1)^2))))*$H$6 -> 0.41712 | I20: =(1-(0.5*(($A20/$B$1)+(($A20/$B$1)^2))))*$I$6 -> 0.21824 | J20: =(1-(0.5*(($A20/$B$1)+(($A20/$B$1)^2))))*$J$6 -> 0.088
A21: 15 | B21: =(1-(0.5*(($A21/$B$1)+(($A21/$B$1)^2))))*$B$6 -> 0.86989796 | C21: =(1-(0.5*(($A21/$B$1)+(($A21/$B$1)^2))))*$C$6 -> 0.86961959 | D21: =(1-(0.5*(($A21/$B$1)+(($A21/$B$1)^2))))*$D$6 -> 0.84797653 | E21: =(1-(0.5*(($A21/$B$1)+(($A21/$B$1)^2))))*$E$6 -> 0.79952321 | F21: =(1-(0.5*(($A21/$B$1)+(($A21/$B$1)^2))))*$F$6 -> 0.71244643 | G21: =(1-(0.5*(($A21/$B$1)+(($A21/$B$1)^2))))*$G$6 -> 0.58109184 | H21: =(1-(0.5*(($A21/$B$1)+(($A21/$B$1)^2))))*$H$6 -> 0.41233163 | I21: =(1-(0.5*(($A21/$B$1)+(($A21/$B$1)^2))))*$I$6 -> 0.21573469 | J21: =(1-(0.5*(($A21/$B$1)+(($A21/$B$1)^2))))*$J$6 -> 0.086989796
A22: 16 | B22: =(1-(0.5*(($A22/$B$1)+(($A22/$B$1)^2))))*$B$6 -> 0.85959184 | C22: =(1-(0.5*(($A22/$B$1)+(($A22/$B$1)^2))))*$C$6 -> 0.85931677 | D22: =(1-(0.5*(($A22/$B$1)+(($A22/$B$1)^2))))*$D$6 -> 0.83793012 | E22: =(1-(0.5*(($A22/$B$1)+(($A22/$B$1)^2))))*$E$6 -> 0.79005086 | F22: =(1-(0.5*(($A22/$B$1)+(($A22/$B$1)^2))))*$F$6 -> 0.70400571 | G22: =(1-(0.5*(($A22/$B$1)+(($A22/$B$1)^2))))*$G$6 -> 0.57420735 | H22: =(1-(0.5*(($A22/$B$1)+(($A22/$B$1)^2))))*$H$6 -> 0.40744653 | I22: =(1-(0.5*(($A22/$B$1)+(($A22/$B$1)^2))))*$I$6 -> 0.21317878 | J22: =(1-(0.5*(($A22/$B$1)+(($A22/$B$1)^2))))*$J$6 -> 0.085959184
A23: 17 | B23: =(1-(0.5*(($A23/$B$1)+(($A23/$B$1)^2))))*$B$6 -> 0.84908163 | C23: =(1-(0.5*(($A23/$B$1)+(($A23/$B$1)^2))))*$C$6 -> 0.84880993 | D23: =(1-(0.5*(($A23/$B$1)+(($A23/$B$1)^2))))*$D$6 -> 0.82768478 | E23: =(1-(0.5*(($A23/$B$1)+(($A23/$B$1)^2))))*$E$6 -> 0.78039093 | F23: =(1-(0.5*(($A23/$B$1)+(($A23/$B$1)^2))))*$F$6 -> 0.69539786 | G23: =(1-(0.5*(($A23/$B$1)+(($A23/$B$1)^2))))*$G$6 -> 0.56718653 | H23: =(1-(0.5*(($A23/$B$1)+(($A23/$B$1)^2))))*$H$6 -> 0.40246469 | I23: =(1-(0.5*(($A23/$B$1)+(($A23/$B$1)^2))))*$I$6 -> 0.21057224 | J23: =(1-(0.5*(($A23/$B$1)+(($A23/$B$1)^2))))*$J$6 -> 0.084908163
A24: 18 | B24: =(1-(0.5*(($A24/$B$1)+(($A24/$B$1)^2))))*$B$6 -> 0.83836735 | C24: =(1-(0.5*(($A24/$B$1)+(($A24/$B$1)^2))))*$C$6 -> 0.83809907 | D24: =(1-(0.5*(($A24/$B$1)+(($A24/$B$1)^2))))*$D$6 -> 0.81724049 | E24: =(1-(0.5*(($A24/$B$1)+(($A24/$B$1)^2))))*$E$6 -> 0.77054343 | F24: =(1-(0.5*(($A24/$B$1)+(($A24/$B$1)^2))))*$F$6 -> 0.68662286 | G24: =(1-(0.5*(($A24/$B$1)+(($A24/$B$1)^2))))*$G$6 -> 0.56002939 | H24: =(1-(0.5*(($A24/$B$1)+(($A24/$B$1)^2))))*$H$6 -> 0.39738612 | I24: =(1-(0.5*(($A24/$B$1)+(($A24/$B$1)^2))))*$I$6 -> 0.2079151 | J24: =(1-(0.5*(($A24/$B$1)+(($A24/$B$1)^2))))*$J$6 -> 0.083836735
A25: 19 | B25: =(1-(0.5*(($A25/$B$1)+(($A25/$B$1)^2))))*$B$6 -> 0.82744898 | C25: =(1-(0.5*(($A25/$B$1)+(($A25/$B$1)^2))))*$C$6 -> 0.8271842 | D25: =(1-(0.5*(($A25/$B$1)+(($A25/$B$1)^2))))*$D$6 -> 0.80659727 | E25: =(1-(0.5*(($A25/$B$1)+(($A25/$B$1)^2))))*$E$6 -> 0.76050836 | F25: =(1-(0.5*(($A25/$B$1)+(($A25/$B$1)^2))))*$F$6 -> 0.67768071 | G25: =(1-(0.5*(($A25/$B$1)+(($A25/$B$1)^2))))*$G$6 -> 0.55273592 | H25: =(1-(0.5*(($A25/$B$1)+(($A25/$B$1)^2))))*$H$6 -> 0.39221082 | I25: =(1-(0.5*(($A25/$B$1)+(($A25/$B$1)^2))))*$I$6 -> 0.20520735 | J25: =(1-(0.5*(($A25/$B$1)+(($A25/$B$1)^2))))*$J$6 -> 0.082744898
... A76: 70 | B76: =(1-(0.5*(($A76/$B$1)+(($A76/$B$1)^2))))*$B$6 -> 0 | C76: =(1-(0.5*(($A76/$B$1)+(($A76/$B$1)^2))))*$C$6 -> 0 | D76: =(1-(0.5*(($A76/$B$1)+(($A76/$B$1)^2))))*$D$6 -> 0 | E76: =(1-(0.5*(($A76/$B$1)+(($A76/$B$1)^2))))*$E$6 -> 0 | F76: =(1-(0.5*(($A76/$B$1)+(($A76/$B$1)^2))))*$F$6 -> 0 | G76: =(1-(0.5*(($A76/$B$1)+(($A76/$B$1)^2))))*$G$6 -> 0 | H76: =(1-(0.5*(($A76/$B$1)+(($A76/$B$1)^2))))*$H$6 -> 0 | I76: =(1-(0.5*(($A76/$B$1)+(($A76/$B$1)^2))))*$I$6 -> 0 | J76: =(1-(0.5*(($A76/$B$1)+(($A76/$B$1)^2))))*$J$6 -> 0

Sheet catalogo 2
A1: ED
A2: 0 | B2: 5 | C2: 100 | F2: Clasificación de la Zona | M2: Uso de Suelo
A3: 6 | B3: 10 | C3: 95 | L3: Clave | M3: Clasificación | N3: Descripción | S3: Densidad Máxima de habitantes/ ha. | T3: Densidad máxima de viviendas/ ha. | U3: Superficie mínima de lote | V3: Frente mínimo del lote | W3: Índice de edificación | X3: Coeficiente de Ocupación del Suelo | Y3: (C.O.S.) | Z3: Coeficiente de Utilización del Suelo | AA3: (C.U.S.) | AB3: Altura máxima de la edificación | AC3: Cajones de estacionamiento por vivienda | AD3: Restricción frontal | AE3: % ajardinado en la restricción frontal | AF3: Restricciones laterales | AG3: Restricción posterior | AH3: Modo de edificación
A4: 11 | B4: 15 | C4: 90 | F4: (Personalizar)
A5: 16 | B5: 20 | C5: 85 | F5: HABITACIONAL DE LUJO | L5: P | M5: Piscícola | N5: Piscícola
A6: 21 | B6: 30 | C6: 80 | F6: HABITACIONAL DE 1ER. ORDEN | L6: AS | M6: Actividades silvestres | N6: Actividades silvestres
A7: 31 | B7: 60 | C7: 75 | F7: HABITACIONAL DE 2DO. ORDEN | L7: F | M7: Forestal | N7: Forestal
A8: EDAD COMPARABLES | F8: HABITACIONAL DE 3ER. ORDEN | L8: AE-M | M8: Actividades extractivas | N8: Actividades extractivas metálicas
A9: 0 | B9: 5 | C9: 100 | F9: HABITACIONAL ANTIGUA | L9: AE-N | M9: Actividades extractivas | N9: Actividades extractivas no metálicas
A10: 6 | B10: 10 | C10: 95 | F10: HABITACIONAL PROLETARIA CON SERVICIOS MUNICIPALES | L10: AG | M10: Agropecuario | N10: Agropecuario
A11: 11 | B11: 15 | C11: 90 | F11: HABITACIONAL DE INTERÉS SOCIAL | L11: GH | M11: Granjas y huertos | N11: Granjas y huertos
A12: 16 | B12: 20 | C12: 85 | F12: HABITACIONAL POPULAR CON SERVICIOS MUNICIPALES | L12: TE | M12: Turístico ecológico | N12: Turístico ecológico
A13: 21 | B13: 30 | C13: 80 | F13: HABITACIONAL CAMPESTRE | L13: TC | M13: Turístico campestre | N13: Turístico campestre | S13: 20 | T13: 4 | U13: 1600 | V13: 40 | W13: 1600 | Y13: 0.25 | AA13: 0.5 | AC13: 4 | AD13: 10 | AE13: 0.8 | AF13: 10 | AG13: 5 | AH13: Abierto
A14: 31 | B14: 60 | C14: 75 | F14: HABITACIÓN EN TRANSFORMACIO | L14: TH-1 | M14: Turístico hotelero | N14: Turístico hotelero densidad mínima | T14: 15 cuartos | U14: 10000 | Y14: 0.15 | AA14: 0.3 | AD14: 10 | AF14: 5 | AG14: 10 | AH14: Abierto
A15: Propósito del avalúo | F15: HABITACIONAL CON COMERCIAL DE LUJO | L15: TH-2 | M15: Turístico hotelero | N15: Turístico hotelero densidad baja | T15: 30 cuartos | U15: 7500 | Y15: 0.2 | AA15: 0.6 | AD15: 10 | AF15: 5 | AG15: 10 | AH15: Abierto
F16: HABITACIONAL COMERCIAL DE 1ER. ORDEN | L16: TH-3 | M16: Turístico hotelero | N16: Turístico hotelero densidad media | T16: 60 cuartos | U16: 5000 | Y16: 0.25 | AA16: 1 | AD16: 5 | AF16: 3 | AG16: 10 | AH16: Abierto
A17: Estimar el Valor Comercial | F17: HABITACIONAL COMERCIAL DE 2DO. ORDEN | L17: TH-4 | M17: Turístico hotelero | N17: Turístico hotelero densidad alta | T17: 100 cuartos | U17: 3000 | Y17: 0.3 | AA17: 1.2 | AD17: 5 | AF17: 3 | AG17: 10 | AH17: Abierto
A18: Originación | F18: HABITACIONAL COMERCIAL DE 3ER. ORDEN | L18: HJ | M18: Habitacional Jardín | N18: Habitacional jardín | S18: 20 | T18: 4 | U18: 2500 m2 | V18: 50 | W18: 2500 m2 | Y18: 0.2 | AA18: 0.4 | AB18: R | AC18: 4 | AD18: 5 | AE18: 0.8 | AF18: 10 | AG18: 10 | AH18: Abierto.
A19: Recuperación | F19: HABITACIONAL COMERCIAL POPULAR | L19: H1-U | M19: Habitacional densidad mínima | N19: Unifamiliar | S19: 50 | T19: 10 | U19: 600 m2 | V19: 20 | W19: 600 m2 | Y19: 0.4 | AA19: 0.8 | AB19: R | AC19: 4 | AD19: 5 ** | AE19: 0.6 | AF19: 2.5 | AG19: 3 | AH19: Abierto
A20: Otros | F20: COMERCIAL Y DE OFICINAS DE LUJO | L20: H1-H | M20: Habitacional densidad mínima | N20: Plurifamiliar horizontal | S20: 75 | T20: 15 | U20: 800 m2 | V20: 20 | W20: 400 m2 | Y20: 0.4 | AA20: 0.8 | AB20: R | AC20: 4 * | AD20: 5 ** | AE20: 0.5 | AF20: 2.5 | AG20: 3 | AH20: Abierto
F21: COMERCIAL Y DE OFICINAS DE 1RA | L21: H1-V | M21: Habitacional densidad mínima | N21: Plurifamiliar vertical | S21: 100 | T21: 20 | U21: 1200 m2 | V21: 40 | W21: 300 m2 | Y21: 0.4 | AA21: 1.2 | AB21: R | AC21: 4 * | AD21: 5 ** | AE21: 0.5 | AF21: 2.5 | AG21: 3 | AH21: Abierto
A22: Referencia de Proximidad SHF | F22: COMERCIAL Y DE OFICINAS DE 2DA | L22: H2-U | M22: Habitacional densidad baja | N22: Unifamiliar | S22: 95 | T22: 19 | U22: 300 m2 | V22: 10 | W22: 300 m2 | Y22: 0.6 | AA22: 1.2 | AB22: R | AC22: 3 | AD22: 5 | AE22: 0.5 | AF22: *** | AG22: 3 | AH22: Semicerrado
A23: Céntrica | F23: COMERCIAL Y DE OFICINAS DE 3RA | L23: H2-H | M23: Habitacional densidad baja | N23: Plurifamiliar horizontal | S23: 115 | T23: 23 | U23: 500 m2 | V23: 10 | W23: 250 m2 | Y23: 0.6 | AA23: 1.2 | AB23: R | AC23: 3 * | AD23: 5 ** | AE23: 0.4 | AF23: *** | AG23: 3 | AH23: Semicerrado
A24: Intermedia | F24: COMERCIAL DE MERCADOS | L24: H2-V | M24: Habitacional densidad baja | N24: Plurifamiliar vertical | S24: 140 | T24: 28 | U24: 800 m2 | V24: 20 | W24: 200 m2 | Y24: 0.6 | AA24: 1.8 | AB24: R | AC24: 3 * | AD24: 5 ** | AE24: 0.4 | AF24: *** | AG24: 3 | AH24: Abierto – Semiabierto
A25: Periférica | F25: COMERCIAL Y CENTRALES DE ABASTO | L25: H3-U | M25: Habitacional densidad media | N25: Unifamiliar | S25: 195 | T25: 39 | U25: 140 m2 | V25: 8 | W25: 140 m2 | Y25: 0.7 | AA25: 1.4 | AB25: R | AC25: 2 | AD25: 3 | AE25: 0.4 | AF25: *** | AG25: 3 | AH25: Semicerrado
A26: De expansión | F26: COMERCIAL Y DE OFICINAS EN PLAZAS COMERCIALES | L26: H3-H | M26: Habitacional densidad media | N26: Plurifamiliar horizontal | S26: 210 | T26: 42 | U26: 260 m2 | V26: 8 | W26: 130 m2 | Y26: 0.7 | AA26: 1.4 | AB26: R | AC26: 2 * | AD26: 3 ** | AE26: 0.3 | AF26: *** | AG26: 3 | AH26: Semicerrado
A27: Rural | F27: INDUSTRIA LIGERA | L27: H3-V | M27: Habitacional densidad media | N27: Plurifamiliar vertical | S27: 270 | T27: 54 | U27: 480 m2 | V27: 16 | W27: 120 m2 | Y27: 0.7 | AA27: 2.1 | AB27: R | AC27: 2* | AD27: 3 ** | AE27: 0.3 | AF27: *** | AG27: 3 | AH27: Abierto – Semiabierto
F28: INDUSTRIA SEMIPESADA | L28: H4 | M28: Habitacional densidad alta | S28: 290 | T28: 58 | U28: 90 m2 | V28: 6 | W28: 90 m2 | Y28: 0.8 | AA28: 1.6 | AB28: R | AC28: 1 | AD28: 2 ** | AE28: 0.3 | AF28: **** | AG28: 3 | AH28: Cerrado Semicerrado
A29: Densidad habitacional | F29: INDUSTRIA PESADA | L29: H4-H | M29: Habitacional densidad alta | N29: Plurifamiliar horizontal | S29: 435 | T29: 87 | U29: 120 m2 | V29: 8 | W29: 60 m2 | Y29: 0.8 | AA29: 1.6 | AB29: R | AC29: 1 * | AD29: 2 ** | AE29: 0.2 | AF29: **** | AG29: 3 | AH29: Cerrado Semicerrado
A30: Escasa de 1 a 40 Viv / Ha | F30: INDUSTRIA ARTESANAL | L30: H4-V | M30: Habitacional densidad alta | N30: Plurifamiliar vertical | S30: 520 | T30: 104 | U30: 200 m2 | V30: 12 | W30: 50 m2 | Y30: 0.8 | AA30: 2.4 | AB30: R | AC30: 1 * | AD30: 2 ** | AE30: 0.2 | AF30: **** | AG30: 3 | AH30: Variable.
A31: Baja de 41 a 60 Viv / Ha | F31: PARQUE INDUSTRIAL | L31: MB1 | M31: Mixto barrial | N31: Intensidad mínima | S31: 800 m2 | T31: 20 | V31: 0.4 | X31: 1.2 | Y31: 0.4 | Z31: R | AA31: 1.2 | AB31: Ver cuadro 48 | AC31: 0.5 | AD31: 5 * | AE31: 4 | AF31: Variable
A32: Media de 61 a 80 Viv / Ha | F32: RÚSTICA | L32: MB2 | M32: Mixto barrial | N32: Intensidad baja | S32: 300 m2 | T32: 10 | V32: 0.6 | X32: 1.8 | Y32: 0.6 | Z32: R | AA32: 1.8 | AB32: Ver cuadro 48 | AC32: 0.4 | AD32: 5 * | AE32: 3 | AF32: Variable
A33: Media Alta de 81 a 100 Viv / Ha | F33: AGROPECUARIA | L33: MB3 | M33: Mixto barrial | N33: Intensidad media | S33: 280 m2 | T33: 10 | V33: 0.7 | X33: 2.1 | Y33: 0.7 | Z33: R | AA33: 2.1 | AB33: Ver cuadro 48 | AC33: 0.3 | AD33: 6 * | AE33: 4 | AF33: Variable
A34: Alta de 101 a 120 Viv / Ha | F34: GANADERA | L34: MB4 | M34: Mixto barrial | N34: Intensidad alta | S34: 180 m2 | T34: 8 | V34: 0.8 | X34: 2.4 | Y34: 0.8 | Z34: R | AA34: 2.4 | AB34: Ver cuadro 48 | AC34: 0.2 | AD34: 5 * | AE34: 3 | AF34: Variable
A35: Inmueble que se Valúa | C35: TIpo Inmueble Renta | D35: Tiempo Renta | F35: TURÍSTICA | L35: MD1 | M35: Mixto distrital | N35: Intensidad mínima | S35: 800 m2 | T35: 20 | V35: 0.4 | X35: 1.2 | Y35: 0.4 | Z35: R | AA35: 1.2 | AB35: Ver cuadro 48 | AC35: 0.5 | AD35: 5 * | AE35: 3 | AF35: Variable
A36: TERRENO URBANO | C36: Casa | D36: Dia | F36: ADMINISTRATIVA | L36: MD2 | M36: Mixto distrital | N36: Intensidad baja | S36: 600 m2 | T36: 15 | V36: 0.6 | X36: 1.8 | Y36: 0.6 | Z36: R | AA36: 1.8 | AB36: Ver cuadro 48 | AC36: 0.4 | AD36: 5 * | AE36: 3 | AF36: Variable
A37: TERRENO EJIDAL | C37: Departamento | D37: Semana | F37: HOSPITALARIA | L37: MD3 | M37: Mixto distrital | N37: Intensidad media | S37: 420 m2 | T37: 12 | V37: 0.7 | X37: 2.1 | Y37: 0.7 | Z37: R | AA37: 2.1 | AB37: Ver cuadro 48 | AC37: 0.3 | AD37: 5 * | AE37: 3 | AF37: Variable
A38: TERRENO CON CONSTRUCCIONES | C38: Estudio | D38: Mes | F38: CULTURAL | L38: MD4 | M38: Mixto distrital | N38: Intensidad alta | S38: 270 m2 | T38: 12 | V38: 0.8 | X38: 2.4 | Y38: 0.8 | Z38: R | AA38: 2.4 | AB38: Ver cuadro 48 | AC38: 0.2 | AD38: 5 * | AE38: 3 | AF38: Variable
A39: TERRENO EJIDAL CON CONSTRUCCIONES | C39: Cabaña | D39: Año | F39: ESCOLAR | L39: MD5 | M39: Mixto distrital | N39: Intensidad máxima | S39: 270 m2 | T39: 12 | V39: 0.8 | X39: 3.2 | Y39: 0.8 | Z39: R | AA39: 3.2 | AB39: Ver cuadro 48 | AC39: 0.2 | AD39: 5 * | AE39: 3 | AF39: Variable
A40: TERRENO EN BREÑA | C40: Habitación | D40: Hora | F40: HABITACIONAL POPULAR CON SERVICIOS MUNICIPALES COMPLETOS | L40: MC1 | M40: Mixto central | N40: Intensidad mínima | S40: 800 m2 | T40: 20 | V40: 0.4 | X40: 1.2. | Y40: 0.4 | Z40: R | AA40: 1.2. | AB40: Ver cuadro 49 | AC40: 0.5 | AD40: 5 * | AE40: 3 | AF40: Variable
A41: CASA HABITACIÓN | C41: Bungalow | F41: HABITACIONAL | L41: MC2 | M41: Mixto central | N41: Intensidad baja | S41: 600 m2 | T41: 15 | V41: 0.6 | X41: 1.8 | Y41: 0.6 | Z41: R | AA41: 1.8 | AB41: Ver cuadro 48 | AC41: 0.4 | AD41: 5 * | AE41: 3 | AF41: Variable
A42: CASA HABITACIÓN EN TERRENO EJIDAL | C42: Capsula | L42: MC3 | M42: Mixto central | N42: Intensidad media | S42: 420 m2 | T42: 12 | V42: 0.7 | X42: 2.1 | Y42: 0.7 | Z42: R | AA42: 2.1 | AB42: Ver cuadro 48 | AC42: 0.3 | AD42: 5 * | AE42: 3 | AF42: Variable
A43: CASA HABITACIÓN CON LOCAL | C43: Oficina | F43: Calidad del Proyecto | H43: Espacios | J43: Niel Ubicación | K43: NIVELES DESCR. | L43: MC4 | M43: Mixto central | N43: Intensidad alta | S43: 270 m2 | T43: 12 | V43: 0.8 | X43: 2.4 | Y43: 0.8 | Z43: R | AA43: 2.4 | AB43: Ver cuadro 48 | AC43: 0.2 | AD43: 5 * | AE43: 3 | AF43: Variable
A44: CASA HABITACIÓN EN CONDOMINIO | C44: Terreno | F44: NUEVO | H44: Estacionamientos subterráneos | J44: -1 | K44: SÓTANO 1 | L44: MC5 | M44: Mixto central | N44: Intensidad máxima | S44: 270 m2 | T44: 12 | V44: 0.8 | X44: 3.2 | Y44: 0.8 | Z44: R | AA44: 3.2 | AB44: Ver cuadro 48 | AC44: 0.2 | AD44: 5 * | AE44: 3 | AF44: Variable
A45: DEPARTAMENTO EN CONDOMINIO | F45: EXCELENTE | H45: Estacionamientos descubiertos | J45: 0 - P.BAJA | K45: SÓTANO 2 | L45: MR | M45: Mixto regional | S45: 1200 m2 | T45: 20 | V45: 0.8 | X45: 2.4. | Y45: 0.8 | Z45: R | AA45: 2.4. | AB45: Ver cuadro 48 | AC45: 20 | AD45: 5 * | AE45: Sin restricción | AF45: Variable
A46: BODEGA | C46: Bodega | F46: BUENO | H46: Estacionamientos semi-cubiertos | J46: 1° | K46: SÓTANO 3 | L46: CV1 | M46: Comercio vecinal | N46: Intensidad mínima | S46: (800) 50* | T46: 20 | V46: 0.4 | X46: 0.8 | Y46: 0.4 | Z46: R | AA46: 0.8 | AB46: Ver cuadro 48 | AC46: 60’% | AD46: 5 ** | AE46: 3 | AF46: Variable
A47: NAVE INDUSTRIAL | C47: Local | F47: ACEPTABLE | H47: Estacionamientos cubiertos | J47: 2° | K47: SOTANO 4 | L47: CV2 | M47: Comercio vecinal | N47: Intensidad baja | S47: 300 (50)* | T47: 10 | V47: 0.6 | X47: 1.2 | Y47: 0.6 | Z47: R | AA47: 1.2 | AB47: Ver cuadro 48 | AC47: 0.5 | AD47: 5 ** | AE47: 3 | AF47: Variable
A48: VECINDAD | C48: Consultorio | F48: ADECUADO | H48: Sala | J48: 3° | K48: SÓTANO 5 | L48: CV3 | M48: Comercio vecinal | N48: Intensidad media | S48: 140 (50)* | T48: 8 | V48: 0.7 | X48: 1.4 | Y48: 0.7 | Z48: R | AA48: 1.4 | AB48: Ver cuadro 48 | AC48: 0.4 | AD48: 3 ** | AE48: 3 | AF48: Variable
A49: LOCAL COMERCIAL | C49: Estacionamiento | F49: FUNCIONAL | H49: Sala de Cine | J49: 4° | K49: NIVEL 0 - PLANTA BAJA | L49: CV4 | M49: Comercio vecinal | N49: Intensidad alta | S49: 90 (50)* | T49: 6 | V49: 0.8 | X49: 1.6 | Y49: 0.8 | Z49: R | AA49: 1.6 | AB49: Ver cuadro 48 | AC49: 0.3 | AD49: 2 ** | AE49: 3 | AF49: Variable
A50: PLAZA COMERCIAL | C50: Isla comercial | F50: REGULAR | H50: Comedor | J50: 5° | K50: PLANTA ALTA | L50: CB1 | M50: Comercio barrial | N50: Intensidad mínima | S50: 800 m2 | T50: 20 | V50: 0.4 | X50: 1.2 | Y50: 0.4 | Z50: R | AA50: 1.2 | AB50: Ver cuadro 48 | AC50: 0.5 | AD50: 5 * | AE50: 4 | AF50: Variable
A51: EDIFICIO COMERCIAL | F51: MALO | H51: Cocina | J51: 6° | K51: NIVEL 1 | L51: CB2 | M51: Comercio barrial | N51: Intensidad baja | S51: 300 m2 | T51: 10 | V51: 0.6 | X51: 1.8 | Y51: 0.6 | Z51: R | AA51: 1.8 | AB51: Ver cuadro 48 | AC51: 0.4 | AD51: 5 * | AE51: 3 | AF51: Variable
A52: EDIFICIO OFICINAS | F52: DEFICIENTE | H52: Baños | J52: 7° | K52: NIVEL 2 | L52: CB3 | M52: Comercio barrial | N52: Intensidad media | S52: 280 m2 | T52: 10 | V52: 0.7 | X52: 2.1 | Y52: 0.7 | Z52: R | AA52: 2.1 | AB52: Ver cuadro 48 | AC52: 0.3 | AD52: 6 * | AE52: 4 | AF52: Variable
A53: CONSULTORIO | F53: OBSOLETO | H53: 1/2 Baños | J53: 8° | K53: NIVEL 3 | L53: CB4 | M53: Comercio barrial | N53: Intensidad alta | S53: 180 m2 | T53: 8 | V53: 0.8 | X53: 2.4 | Y53: 0.8 | Z53: R | AA53: 2.4 | AB53: Ver cuadro 48 | AC53: 0.2 | AD53: 5 * | AE53: 3 | AF53: Variable
A54: HOTEL DE PASO | F54: ADECUADO A SU ÉPOCA | H54: Cuarto de Lavado | J54: 9° | K54: NIVEL 4 | L54: CD1 | M54: Comercio distrital | N54: Intensidad mínima | S54: 800 m2 | T54: 20 | V54: 0.4 | X54: 1.2 | Y54: 0.4 | Z54: R | AA54: 1.2 | AB54: Ver cuadro 48 | AC54: 0.5 | AD54: 5 * | AE54: 3 | AF54: Variable
A55: ESCUELA | F55: ADECUADO A SU USO | H55: Area de lavado | J55: 10° | K55: NIVEL 5 | L55: CD2 | M55: Comercio distrital | N55: Intensidad baja | S55: 600 m2 | T55: 15 | V55: 0.6 | X55: 1.8 | Y55: 0.6 | Z55: R | AA55: 1.8 | AB55: Ver cuadro 48 | AC55: 0.4 | AD55: 5 * | AE55: 3 | AF55: Variable
A56: CONJUNTO DE VIVIENDAS | F56: INADECUADO | H56: Cuarto de Servicios | J56: 11° | K56: NIVEL 6 | L56: CD3 | M56: Comercio distrital | N56: Intensidad media | S56: 420 m2 | T56: 12 | V56: 0.7 | X56: 2.1 | Y56: 0.7 | Z56: R | AA56: 2.1 | AB56: Ver cuadro 48 | AC56: 0.3 | AD56: 5 * | AE56: 3 | AF56: Variable
A57: EDIFICIO DE OFICINAS | H57: Patio | J57: 12° | K57: NIVEL 7 | L57: CD4 | M57: Comercio distrital | N57: Intensidad alta | S57: 270 m2 | T57: 12 | V57: 0.8 | X57: 2.4 | Y57: 0.8 | Z57: R | AA57: 2.4 | AB57: Ver cuadro 48 | AC57: 0.2 | AD57: 5 * | AE57: 3 | AF57: Variable
A58: CONJUNTO DE DEPARTAMENTOS | F58: Colintandias | H58: Patio de Servicios | J58: 13° | K58: NIVEL 8 | L58: CD5 | M58: Comercio distrital | N58: Intensidad máxima | S58: 270 m2 | T58: 12 | V58: 0.8 | X58: 3.2 | Y58: 0.8 | Z58: R | AA58: 3.2 | AB58: Ver cuadro 48 | AC58: 0.2 | AD58: 5 * | AE58: 3 | AF58: Variable
A59: Población | B59: (Personalizar) | F59: Norte | G59: Noreste | H59: Jardín | J59: 14° | K59: NIVEL 9 | L59: CC1 | M59: Comercio central | N59: Intensidad mínima | S59: 800 m2 | T59: 20 | V59: 0.4 | X59: 1.2. | Y59: 0.4 | Z59: R | AA59: 1.2. | AB59: Ver cuadro 49 | AC59: 0.5 | AD59: 5 * | AE59: 3 | AF59: Variable
A60: Nula | F60: Sur | G60: Suroriente | H60: Terraza | J60: 15° | K60: NIVEL 10 | L60: CC2 | M60: Comercio central | N60: Intensidad baja | S60: 600 m2 | T60: 15 | V60: 0.6 | X60: 1.8 | Y60: 0.6 | Z60: R | AA60: 1.8 | AB60: Ver cuadro 48 | AC60: 0.4 | AD60: 5 * | AE60: 3 | AF60: Variable
A61: Escasa de Nivel Socioeconómico Bajo | F61: Este | G61: Norponiente | H61: Estar Familiar | J61: 16° | K61: PENT HOUSE | L61: CC3 | M61: Comercio central | N61: Intensidad media | S61: 420 m2 | T61: 12 | V61: 0.7 | X61: 2.1 | Y61: 0.7 | Z61: R | AA61: 2.1 | AB61: Ver cuadro 48 | AC61: 0.3 | AD61: 5 * | AE61: 3 | AF61: Variable
A62: Escasa de Nivel Socioeconómico medio | F62: Oeste | G62: Surponiente | H62: Recamaras | J62: 17° | K62: MEZZANINE | L62: CC4 | M62: Comercio central | N62: Intensidad alta | S62: 270 m2 | T62: 12 | V62: 0.8 | X62: 2.4 | Y62: 0.8 | Z62: R | AA62: 2.4 | AB62: Ver cuadro 48 | AC62: 0.2 | AD62: 5 * | AE62: 3 | AF62: Variable
A63: Escasa de Nivel Socioeconómico medio Bajo | H63: Recamara Principal | J63: 18° | K63: AZOTEA | L63: CC5 | M63: Comercio central | N63: Intensidad máxima | S63: 270 m2 | T63: 12 | V63: 0.8 | X63: 3.2 | Y63: 0.8 | Z63: R | AA63: 3.2 | AB63: Ver cuadro 48 | AC63: 0.2 | AD63: 5 * | AE63: 3 | AF63: Variable
A64: Escasa de Nivel Socioeconómico Alto | H64: Recibidor | J64: 19° | K64: ROOF TOP | L64: CR | M64: Comercio regional | N64: Comercio regional | S64: 1200 m2 | T64: 20 | V64: 0.8 | X64: 2.4. | Y64: 0.8 | Z64: R | AA64: 2.4. | AB64: Ver cuadro 48 | AC64: 20 | AD64: 5 * | AE64: Sin restricción | AF64: Variable
A65: Normal | F65: Régimen de Propiedad | H65: Desayunador | J65: 20° | K65: NIVEL DE CALLE | L65: SV1 | M65: Servicios vecinales | N65: Intensidad mínima | S65: 800 m2 | T65: 20 | V65: 0.4 | X65: 0.8 | Y65: 0.4 | Z65: R | AA65: 0.8 | AB65: Ver cuadro 48 | AC65: 60 | AD65: 5 ** | AE65: 3 | AF65: Variable
A66: Normal de Nivel Socioeconómico Bajo | F66: Privada | H66: Alberca Descubierta | J66: 21° | L66: SV2 | M66: Servicios vecinales | N66: Intensidad baja | S66: 300 m2 | T66: 10 | V66: 0.6 | X66: 1.2 | Y66: 0.6 | Z66: R | AA66: 1.2 | AB66: Ver cuadro 48 | AC66: 50 | AD66: 5 ** | AE66: 3 | AF66: Variable
A67: Normal de Nivel Socioeconómico Medio Bajo | F67: Privada en condominio | H67: Alberca Techada | J67: 22° | L67: SV3 | M67: Servicios vecinales | N67: Intensidad media | S67: 140 m2 | T67: 8 | V67: 0.7 | X67: 1.4 | Y67: 0.7 | Z67: R | AA67: 1.4 | AB67: Ver cuadro 48 | AC67: 40 | AD67: 3 ** | AE67: 3 | AF67: Variable
A68: Normal de Nivel Socioeconómico Medio | F68: Privada en copropiedad | H68: Jacuzzi | J68: 23° | L68: SV4 | M68: Servicios vecinales | N68: Intensidad alta | S68: 90 m2 | T68: 6 | V68: 0.8 | X68: 1.6 | Y68: 0.8 | Z68: R | AA68: 1.6 | AB68: Ver cuadro 48 | AC68: 30 | AD68: 2 ** | AE68: 3 | AF68: Variable
A69: Normal de Nivel Socioeconómico Medio Alto | F69: Ejidal | H69: Salon Multiusos | J69: 24° | L69: SB1 | M69: Servicios barriales | N69: Intensidad mínima | S69: 800 m2 | T69: 20 | V69: 0.4 | X69: 1.2 | Y69: 0.4 | Z69: R | AA69: 1.2 | AB69: Ver cuadro 48 | AC69: 0.5 | AD69: 5 * | AE69: 3 | AF69: Variable
A70: Normal de Nivel Socioeconómico Alto | F70: Privada, certificados de vivienda | H70: Closet | J70: 25° | L70: SB2 | M70: Servicios barriales | N70: Intensidad baja | S70: 300 m2 | T70: 10 | V70: 0.6 | X70: 1.8 | Y70: 0.6 | Z70: R | AA70: 1.8 | AB70: Ver cuadro 48 | AC70: 0.4 | AD70: 5 * | AE70: 3 | AF70: Variable
A71: Normal de Gran Poder Adquisitivo | F71: Absoluta | H71: Espacio para closet | J71: 26° | L71: SB3 | M71: Servicios barriales | N71: Intensidad media | S71: 280 m2 | T71: 10 | V71: 0.7 | X71: 2.1 | Y71: 0.7 | Z71: R | AA71: 2.1 | AB71: Ver cuadro 48 | AC71: 0.3 | AD71: 5 * | AE71: 3 | AF71: Variable
A72: Densa de Nivel Socioeconómico Bajo | F72: Sociedad Anónima | H72: Closet Vestidor | J72: 27° | L72: SB4 | M72: Servicios barriales | N72: Intensidad alta | S72: 180 m2 | T72: 8 | V72: 0.8 | X72: 2.4 | Y72: 0.8 | Z72: R | AA72: 2.4 | AB72: Ver cuadro 48 | AC72: 0.2 | AD72: 5 * | AE72: 3 | AF72: Variable
A73: Densa de Nivel Socioeconómico Medio Bajo | F73: Sociedad Anónima de C.V. | H73: Bodega | J73: 28° | L73: SD1 | M73: Servicios distritales | N73: Intensidad mínima | S73: 800 m2 | T73: 20 | V73: 0.4 | X73: 1.2 | Y73: 0.4 | Z73: R | AA73: 1.2 | AB73: Ver cuadro 48 | AC73: 0.5 | AD73: 5 * | AE73: 3 | AF73: Variable
A74: Densa de Nivel Socioeconómico Medio | F74: Propiedad privada bajo régimen de sociedad | H74: Almacén | J74: 29° | L74: SD2 | M74: Servicios distritales | N74: Intensidad baja | S74: 800 m2 | T74: 15 | V74: 0.6 | X74: 1.8 | Y74: 0.6 | Z74: R | AA74: 1.8 | AB74: Ver cuadro 48 | AC74: 0.4 | AD74: 5 * | AE74: 3 | AF74: Variable
A75: Densa Flotante de Nivel Socioeconómico Bajo | H75: Oficinas | J75: 30° | L75: SD3 | M75: Servicios distritales | N75: Intensidad media | S75: 420 m2 | T75: 12 | V75: 0.7 | X75: 2.1 | Y75: 0.7 | Z75: R | AA75: 2.1 | AB75: Ver cuadro 48 | AC75: 0.3 | AD75: 5 * | AE75: 3 | AF75: Variable
A76: Densa Flotante de Nivel Socioeconómico Medio | F76: INFORMACIÓN FUE PROPORCIONADA POR: | H76: Local Comercial | J76: 31° | L76: SD4 | M76: Servicios distritales | N76: Intensidad alta | S76: 270 m2 | T76: 12 | V76: 0.8 | X76: 2.4 | Y76: 0.8 | Z76: R | AA76: 2.4 | AB76: Ver cuadro 48 | AC76: 0.2 | AD76: 5 * | AE76: 3 | AF76: Variable
A77: Densa Flotante de Nivel Socioeconómico Alto | F77: SOLICITANTE | H77: Locales comerciales | J77: 32° | L77: SD5 | M77: Servicios distritales | N77: Intensidad máxima | S77: 270 m2 | T77: 12 | V77: 0.8 | X77: 3.2 | Y77: 0.8 | Z77: R | AA77: 3.2 | AB77: Ver cuadro 48 | AC77: 0.2 | AD77: 5 * | AE77: 3 | AF77: Variable
A78: Densa Flotante de Nivel Socioeconómico Medio Alto | F78: PROPIETARIO | H78: Elevador | J78: 33° | L78: SC1 | M78: Servicios centrales | N78: Intensidad mínima | S78: 800 m2 | T78: 20 | V78: 0.4 | X78: 1.2 | Y78: 0.4 | Z78: R | AA78: 1.2 | AB78: Ver cuadro 48 | AC78: 0.5 | AD78: 5 * | AE78: 3 | AF78: Variable
F79: NO SE PROPORCIONÓ DOCUMENTACIÓN | H79: Montacargas | J79: 34° | L79: SC2 | M79: Servicios centrales | N79: Intensidad baja | S79: 600 m2 | T79: 15 | V79: 0.6 | X79: 1.8 | Y79: 0.6 | Z79: R | AA79: 1.8 | AB79: Ver cuadro 48 | AC79: 0.4 | AD79: 5 * | AE79: 3 | AF79: Variable
F80: INMOBILIARIA | J80: 35° | L80: SC3 | M80: Servicios centrales | N80: Intensidad media | S80: 420 m2 | T80: 12 | V80: 0.7 | X80: 2.1 | Y80: 0.7 | Z80: R | AA80: 2.1 | AB80: Ver cuadro 48 | AC80: 0.3 | AD80: 5 * | AE80: 3 | AF80: Variable
A81: Fuentes de colindancias | F81: SUPERFICIE DE TERRENO SEGÚN: | J81: 36° | L81: SC4 | M81: Servicios centrales | N81: Intensidad alta | S81: 270 m2 | T81: 12 | V81: 0.8 | X81: 2.4 | Y81: 0.8 | Z81: R | AA81: 2.4 | AB81: Ver cuadro 48 | AC81: 0.2 | AD81: 5 * | AE81: 3 | AF81: Variable
F82: ESCRITURA PÚBLICA . | L82: SC5 | M82: Servicios centrales | N82: Intensidad máxima | S82: 270 m2 | T82: 12 | V82: 0.8 | X82: 3.2 | Y82: 0.8 | Z82: R | AA82: 3.2 | AB82: Ver cuadro 48 | AC82: 0.2 | AD82: 5 * | AE82: 3 | AF82: Variable
A83: Escrituras | F83: LEVANTAMIENTO APROXIMADO | L83: SR | M83: Servicios regionales | N83: Servicios regionales | S83: 1200 m2 | T83: 20 | V83: 0.8 | X83: 2.4 | Y83: 0.8 | Z83: R | AA83: 2.4 | AB83: Ver cuadro 48 | AC83: 0.2 | AD83: 5 * | AE83: Sin restricción
A84: Datos de Registro Público | F84: CONTRATO DE COMPRAVENTA | L84: SI | M84: Servicios a la industria y comercio | N84: Servicios a la industria y comercio | S84: 600 m2 | T84: 15 | V84: 0.8 | X84: 0.8 | Y84: 0.8 | Z84: R | AA84: 0.8 | AB84: 20 | AC84: 5 * | AD84: Sin restricción | AE84: Variable
A85: Contrato de Compra - Venta | F85: TÍTULO DE PROPIEDAD | L85: MFD | M85: Manufacturas domiciliarias | N85: Manufacturas domiciliarias | S85: Superficie mínima a desarrollar | T85: Superficie mínima de lote | U85: Superficie máxima de lote | V85: Frente mínimo del lote | W85: Coeficiente de ocupación del suelo (C.O.S.) | X85: Coeficiente de utilización del suelo (C.U.S.) | Y85: Altura máxima de la edificación | Z85: Cajones de estacionamiento | AB85: % Frente ajardinado | AD85: Restricción frontal | AE85: Restricciones laterales | AG85: Restricción posterior | AI85: Modo de edificación
A86: Contrato | F86: PREDIAL | L86: MFM | M86: Manufacturas menores | N86: Manufacturas menores | T86: 180 m2 | U86: 400,000 m2 | V86: 12 metros lineales | W86: 0.8 | X86: 1.6 | Y86: R | Z86: SEGÚN CUADRO 48 | AB86: 0.2 | AD86: 3 ** | AG86: 3 ** | AI86: VARIA
A87: Datos proporcionados por el solicitante | F87: SUPERFICIE DE CONSTRUCCIONES SEGÚN: | L87: I1 | M87: Industria ligera de riesgo bajo | N87: Industria ligera y de riesgo bajo | S87: --- | U87: 600 m2 | W87: --- | X87: 15 | Z87: 0.8 | AA87: 8.00 m3 | AC87: R | AD87: SEGÚN CUADRO 48 | AF87: 0.2 | AG87: 5 ** | AI87: --- | AJ87: 12 *** | AL87: VARIA
A88: Subdivisión Autorizada | F88: LEVANTAMIENTO APROXIMADO | L88: I2 | M88: Industria mediana de riesgo medio | N88: Industria mediana y de riesgo medio | S88: --- | U88: 1,200 m2 | W88: --- | X88: 20 | Z88: 0.7 | AB88: 10.50 m3 | AD88: R | AE88: SEGÚN CUADRO 48 | AF88: 0.2 | AG88: 5 ** | AH88: --- | AI88: 12 *** | AL88: VARIA
A89: Fusión autorizada | F89: PLANOS ARQUITECTÓNICOS | L89: I3 | M89: Industria pesada de riesgo alto | N89: Industria pesada y de riesgo alto | S89: --- | U89: 1,500 m2 | W89: --- | X89: 30 | Z89: 0.7 | AB89: 10.50 m3 | AD89: R | AE89: SEGÚN CUADRO 48 | AF89: 0.2 | AG89: 5 ** | AH89: --- | AI89: 12 *** | AL89: VARIA
A90: Medición del terreno | F90: PREDIAL | L90: IJ | M90: Parque industrial jardín | N90: Parque industrial jardín | S90: 10,000 m2 | U90: 600 m2 | W90: --- | X90: 15 | Z90: 0.5 | AB90: 8 m3 | AD90: R | AE90: SEGÚN CUADRO 48 | AF90: 0.2 | AG90: 5 ** | AH90: 10 . | AI90: 12 | AL90: Abierta
A91: Medicion construcciones | F91: UNIDADES | G91: SERVICIOS BÁSICOS | H91: AGUA POTABLE | I91: DRENAJE | J91: ENERGÍA ELÉCTRICA | L91: EI-V | M91: Equipamiento vecinal | N91: Equipamiento vecinal
A92: Plano autorizado del fraccionamiento | F92: ml | G92: COMPLETOS | H92: ENTUBADA | I92: ENTUBADO | J92: CON CABLEADO AÉREO | L92: EI-B | M92: Equipamiento barrial | N92: Equipamiento barrial
A93: Plano proporcionado por el propietario | F93: m2 | G93: INCOMPLETOS | H93: DE POZO | I93: CON FOSA SÉPTICA | J93: SUBTERRÁNEO | L93: EI-D | M93: Equipamiento distrital | N93: Equipamiento distrital
A94: Plano arquitectónico | F94: pza | H94: CON PIPA | I94: NO TIENE | J94: AUTÓNOMO | L94: EI-C | M94: Equipamiento central | N94: Equipamiento central
A95: Plano autorizado del condominio | F95: lote | J95: NO TIENE | L95: EI-R | M95: Equipamiento regional | N95: Equipamiento regional
A96: Plano autorizado de subdivisión | F96: GAS | G96: ALUMBRADO EXTERIOR | H96: LÍNEAS TELEFÓNICAS | I96: VIALIDADES | J96: TRANSPORTE | L96: EV-V | M96: Espacios verdes, abiertos y recreativos vecinales | N96: Espacios verdes, abiertos y recreativos vecinales
A97: Plano de función | F97: CON TANQUE ESTACIONARIO | G97: CON CABLEADO AÉREO | H97: CON CABLEADO AÉREO | I97: DE ASFALTO | J97: URBANO | L97: EV-B | M97: Espacios verdes, abiertos y recreativos barriales | N97: Espacios verdes, abiertos y recreativos barriales
A98: Datos No Proporcionados | F98: CON CILINDROS | G98: SUBTERRÁNEO | H98: SUBTERRÁNEO | I98: DE CONCRETO HIDRÁULICO | J98: SUBURBANO | L98: EV-D | M98: Espacios verdes y abiertos distritales | N98: Espacios verdes, abiertos y recreativos distritales
A99: Medidas catastrales | F99: CON RED DE GAS NATURAL | G99: AUTÓNOMO | H99: CON ANTENA | I99: DE TERRACERÍA | J99: INTERBARRIAL | L99: EV-C | M99: Espacios verdes y abiertos centrales | N99: Espacios verdes, abiertos y recreativos centrales
A100: Traslado de dominio | I100: EMPEDRADO | L100: EV-R | M100: Espacios verdes y abiertos regionales | N100: Espacios, abiertos y recreativos regionales
...

Sheet Analisis Avance O.
D2: OPINIÓN DE VALOR
O3: ='OPI Constr'!E6 -> OPI-25-11-07-OF
A5: AVANCE DE OBRA
A7: ANALISIS FISICO
A9: SUPERFICIE DE TERRENO
E10: Superficie m2 | G10: Valor Unitario ($/m2) | I10: F.R. | K10: VR | N10: Valor ($)
E12: ='OPI Constr'!C108 -> 91.97 | G12: ='OPI Constr'!G108 -> 10500 | I12: =+'OPI Constr'!Z108 -> 1 | K12: =+'OPI Constr'!AC108 -> 10500 | N12: =+G12*E12*I12 -> 965685
E13: =+'OPI Constr'!C109 | G13: =+'OPI Constr'!E109 | I13: =+'OPI Constr'!Z109 | K13: =+'OPI Constr'!AC109 -> 0 | N13: =+G13*E13*I13 -> 0
E14: =+'OPI Constr'!C107 | G14: =+'OPI Constr'!G107 | I14: =+'OPI Constr'!Z110 | K14: =+'OPI Constr'!AC110 -> 0 | N14: =+G14*E14*I14 -> 0
M15: Valor de Terreno Redondeado | N15: =+ROUND(SUM(N12:N14),-3) -> 966000
A18: SUPERFICIE DE CONSTRUCCIÓN
A19: Tipo | B19: Superficie | C19: Indiviso | D19: P.U. | F19: V.R.N. | G19: Edad | H19: V.U.T. | I19: Fac. Homologados | N19: VUR | O19: Valor ($)
B20: (m2) | D20: $/m2 | F20: ($) | G20: (años) | H20: (años) | I20: Avan | K20: Fed | M20: F.V.R. | N20: (años)
A21: =+'OPI Constr'!A115 -> I.- | B21: ='OPI Constr'!K115 -> 16.08 | C21: 1 | D21: ='OPI Constr'!N115 -> 13500 | F21: =+B21*C21*D21 -> 217080 | G21: 30 | H21: =+'OPI Constr'!AP115 -> 70 | I21: =+'% Avance de Obra'!$I$53 -> 1 | K21: =+'OPI Constr'!Z115 -> 0.73 | M21: =ROUND(I21*K21,2) -> 0.73 | N21: =M21*H21 -> 51.1 | O21: =F21*M21 -> 158468.4
A22: =+'OPI Constr'!A116 -> II.- | B22: ='OPI Constr'!K116 -> 58.12 | C22: 1 | D22: ='OPI Constr'!N116 -> 13500 | F22: =+D22*B22 -> 784620 | G22: 0 | H22: =+'OPI Constr'!AP116 -> 70 | I22: =+'% Avance de Obra'!$I$53 -> 1 | K22: =+'OPI Constr'!Z116 -> 0.96 | M22: =ROUND(I22*K22,2) -> 0.96 | N22: =M22*H22 -> 67.2 | O22: =F22*M22 -> 753235.2
A23: =+'OPI Constr'!A117 -> III.- | B23: ='OPI Constr'!K117 -> 0 | C23: 1 | D23: ='OPI Constr'!N117 | F23: =+D23*B23 -> 0 | G23: 0 | H23: =+'OPI Constr'!AP117 -> 70 | I23: =+'% Avance de Obra'!$I$53 -> 1 | K23: =+'OPI Constr'!Z117 -> 0.96 | M23: =ROUND(I23*K23,2) -> 0.96 | N23: =M23*H23 -> 67.2 | O23: =F23*M23 -> 0
A24: =+'OPI Constr'!A118 -> IV.- | B24: ='OPI Constr'!K118 | C24: 1 | D24: ='OPI Constr'!N118 | F24: =+D24*B24 -> 0 | G24: 0 | H24: =+'OPI Constr'!AP118 -> 70 | I24: =+'% Avance de Obra'!$I$53 -> 1 | K24: =+'OPI Constr'!Z118 -> 0.96 | M24: =ROUND(I24*K24,2) -> 0.96 | N24: =M24*H24 -> 67.2 | O24: =F24*M24 -> 0
B25: =SUM(B21:B24) -> 74.2 | D25: =SUM(D21:E24) -> 27000 | O25: =SUM(O21:O24) -> 911703.6
N27: Total Construcciones redondeado | O27: =+ROUND(O25,-3) -> 912000
A28: ELEMENTOS ADICIONALES
A29: Tipo | B29: Superficie | C29: Indiviso | D29: P.U. | F29: V.R.N. | G29: Edad | H29: V.U.T. | I29: Fac. Homologados | N29: VUR | O29: Valor ($)
B30: (m2) | D30: $/m2 | F30: ($) | G30: (años) | H30: (años) | I30: Fco | K30: Fed | M30: F.V.R. | N30: (años)
C31: 1 | F31: =+D31*B31 -> 0 | G31: 0 | H31: 70 | I31: 1 | K31: 1 | M31: =ROUND(I31*K31,2) -> 1 | N31: =M31*H31 -> 70 | O31: =F31*M31 -> 0
B32: 0 | C32: 0 | F32: =+D32*B32 -> 0 | G32: 0 | K32: 1 | M32: =ROUND(I32*K32,2) -> 0 | N32: =M32*H32 -> 0 | O32: =F32*M32 -> 0
O33: =SUM(O31:O32) -> 0
N35: Total Construcciones redondeado | O35: =+ROUND(O33,-3) -> 0
N38: RESULTADO DEL ENFOQUE DE COSTOS (a+b+c) | O38: =+N15+O27+O35 -> 1878000
A41: ANÁLISIS DE MERCADO
A43: Justificación del factor de avance de obra para no afectar al terreno en el estudio de mercado
A44: =+A46+A48 -> 1967700 | C44: Valor físico de mi sujeto al 100%
A46: =+(B21*D21)+(B22*D22)+(B23*D23)+(B24*D24) -> 1001700 | B46: =+A46/A44 -> 0.5090715 | C46: (Sup. constr x valor unitario construcción) | N46: Valor Unitario Homologado | O46: =+'OPI Constr'!E213 -> 32793.328
A48: =+N15 -> 966000 | B48: =+A48/A44 -> 0.4909285 | C48: Valor Terreno | N48: Nivel de Oferta y Demanda del Sujeto | O48: 1
B50: =+(B46*'% Avance de Obra'!I53)+B48 -> 1 | C50: % construcción por avance más % terreno | N50: Valor Unitario de Mercado | O50: =+O46*O48 -> 32793.328
N52: VALOR UNITARIO DE MERCADO ($/m2) avance obra: | O52: =+(O50*B50)*1.0475 -> 34351.011
N53: Superficie Vendible | O53: =+B25 -> 74.2
N55: VALOR DE MERCADO CON AVANCE DE OBRA | O55: =+ROUND(O52*O53,-3) -> 2549000

Sheet % Avance de Obra
H2: 3314189492
H3: avaluos@avaluosyarquitectura.com.mx
H4: avaluosyarquitectura2@gmail.com
H5: www.avaluosyarquitectura.com.mx
D6: Cálculo por partida del porcentaje faltante en una vivienda con deterioro
D8: Tipo de Inmueble | E8: Casa en más de un nivel
D10: Tipo de vivienda M2 construcción | E10: Tipo 8: hasta 120M2 | I10: =+BIMSA!L46 -> Deterioro resultante 0 %
D12: Partidas | E12: % partida | F12: Conceptos | G12: % concepto | H12: % avance real (captura) | I12: Resultante
C13: 1 | D13: Cimentación | E13: =VLOOKUP(C13,BIMSA!$A$6:$AH$18,'Catálogo Bimsa'!$D$8,0) -> 0.11486941 | F13: Acero | G13: 0.4 | H13: 1 | I13: =H13*G13*$E$13 -> 0.045947762
F14: Concreto | G14: 0.6 | H14: 1 | I14: =H14*G14*$E$13 -> 0.068921644
C15: 2 | D15: Estructura (columnas, trabes y losas) | E15: =VLOOKUP(C15,BIMSA!$A$6:$AH$18,'Catálogo Bimsa'!$D$8,0) -> 0.16694748 | F15: Muros | G15: 0.3 | H15: 1 | I15: =H15*G15*$E$15 -> 0.050084244
F16: Castillos | G16: 0.2 | H16: 1 | I16: =H16*G16*$E$15 -> 0.033389496
F17: Losa y trabes | G17: 0.5 | H17: 1 | I17: =H17*G17*$E$15 -> 0.08347374
C18: 3 | D18: Albañilería | E18: =VLOOKUP(C18,BIMSA!$A$6:$AH$18,'Catálogo Bimsa'!$D$8,0) -> 0.1058782 | F18: Pretiles, bases, tinacos | G18: =+'Catálogo Bimsa'!E29 -> 0.15 | H18: 1 | I18: =H18*G18*$E$18 -> 0.01588173
F19: Albañilería en azotea | G19: =+'Catálogo Bimsa'!E30 -> 0.1 | H19: 1 | I19: =H19*G19*$E$18 -> 0.01058782
F20: Huellas | G20: =+'Catálogo Bimsa'!E31 -> 0.2 | H20: 1 | I20: =H20*G20*$E$18 -> 0.02117564
F21: Lavadero | G21: =+'Catálogo Bimsa'!E32 -> 0.05 | H21: 1 | I21: =H21*G21*$E$18 -> 0.00529391
F22: Bardas posteriores | G22: =+'Catálogo Bimsa'!E33 -> 0.18 | H22: 1 | I22: =H22*G22*$E$18 -> 0.019058076
F23: Escaleras | G23: =+'Catálogo Bimsa'!E34 -> 0.15 | H23: 1 | I23: =H23*G23*$E$18 -> 0.01588173
F24: Registros | G24: =+'Catálogo Bimsa'!E35 -> 0.05 | H24: 1 | I24: =H24*G24*$E$18 -> 0.00529391
F25: Firme en patio de servicio | G25: =+'Catálogo Bimsa'!E36 -> 0.12 | H25: 1 | I25: =H25*G25*$E$18 -> 0.012705384
C26: 4 | D26: Instalación hidráulica | E26: =VLOOKUP(C26,BIMSA!$A$6:$AH$18,'Catálogo Bimsa'!$D$8,0) -> 0.037886648 | F26: Tubería hidráulica | G26: 1 | H26: 1 | I26: =H26*G26*E26 -> 0.037886648
C27: 5 | D27: Instalación sanitaria | E27: =VLOOKUP(C27,BIMSA!$A$6:$AH$18,'Catálogo Bimsa'!$D$8,0) -> 0.020794683 | F27: Tubería sanitaria | G27: 1 | H27: 1 | I27: =H27*G27*E27 -> 0.020794683
C28: 6 | D28: Instalación eléctrica | E28: =VLOOKUP(C28,BIMSA!$A$6:$AH$18,'Catálogo Bimsa'!$D$8,0) -> 0.021095112 | F28: Ductos y chalupas | G28: 0.3 | H28: 1 | I28: =H28*G28*$E$28 -> 0.0063285337
F29: Cableado | G29: 0.6 | H29: 1 | I29: =H29*G29*$E$28 -> 0.012657067
F30: Accesorios | G30: 0.1 | H30: 1 | I30: =H30*G30*$E$28 -> 0.0021095112
C31: 7 | D31: Instalación de gas | E31: =VLOOKUP(C31,BIMSA!$A$6:$AH$18,'Catálogo Bimsa'!$D$8,0) -> 0.0051692472 | F31: Tubería y accesorios | G31: 1 | H31: 1 | I31: =H31*G31*E31 -> 0.0051692472
C32: 8 | D32: Acabados interiores | E32: =VLOOKUP(C32,BIMSA!$A$6:$AH$18,'Catálogo Bimsa'!$D$8,0) -> 0.23078877 | F32: Aplanado interior | G32: 0.35 | H32: 1 | I32: =H32*G32*$E$32 -> 0.080776068
F33: Azulejos y lambrines | G33: 0.15 | H33: 1 | I33: =H33*G33*$E$32 -> 0.034618315
F34: Pintura interior | G34: 0.2 | H34: 1 | I34: =H34*G34*$E$32 -> 0.046157753
F35: Piso cerámico o alfombra | G35: 0.3 | H35: 1 | I35: =H35*G35*$E$32 -> 0.06923663
C36: 9 | D36: Acabados exteriores | E36: =VLOOKUP(C36,BIMSA!$A$6:$AH$18,'Catálogo Bimsa'!$D$8,0) -> 0.088617435 | F36: Aplanados exteriores | G36: 0.5 | H36: 1 | I36: =H36*G36*$E$36 -> 0.044308718
F37: Pintura exterior | G37: 0.3 | H37: 1 | I37: =H37*G37*$E$36 -> 0.026585231
F38: Impermeabilización | G38: 0.2 | H38: 1 | I38: =H38*G38*$E$36 -> 0.017723487
C39: 10 | D39: Puertas internas, externas | E39: =VLOOKUP(C39,BIMSA!$A$6:$AH$18,'Catálogo Bimsa'!$D$8,0) -> 0.028732838 | F39: Marcos | G39: 0.15 | H39: 1 | I39: =H39*G39*$E$39 -> 0.0043099256
F40: Puertas | G40: 0.75 | H40: 1 | I40: =H40*G40*$E$39 -> 0.021549628
F41: Chapas | G41: 0.1 | H41: 1 | I41: =H41*G41*$E$39 -> 0.0028732838
C42: 11 | D42: Cancelería | E42: =VLOOKUP(C42,BIMSA!$A$6:$AH$18,'Catálogo Bimsa'!$D$8,0) -> 0.035936953 | F42: Marcos | G42: 0.15 | H42: 1 | I42: =H42*G42*$E$42 -> 0.005390543
F43: Ventanas | G43: 0.5 | H43: 1 | I43: =H43*G43*$E$42 -> 0.017968477
F44: Vidrio | G44: 0.3 | H44: 1 | I44: =H44*G44*$E$42 -> 0.010781086
F45: Sellado | G45: 0.05 | H45: 1 | I45: =H45*G45*$E$42 -> 0.0017968477
C46: 12 | D46: Mobiliario fijo | E46: =VLOOKUP(C46,BIMSA!$A$6:$AH$18,'Catálogo Bimsa'!$D$8,0) -> 0.091296524 | F46: WC | G46: 0.25 | H46: 1 | I46: =H46*G46*$E$46 -> 0.022824131
F47: Lavabo | G47: 0.15 | H47: 1 | I47: =H47*G47*$E$46 -> 0.013694479
F48: Tarja | G48: 0.1 | H48: 1 | I48: =H48*G48*$E$46 -> 0.0091296524
F49: Calentador | G49: 0.3 | H49: 1 | I49: =H49*G49*$E$46 -> 0.027388957
F50: Tinaco | G50: 0.2 | H50: 1 | I50: =H50*G50*$E$46 -> 0.018259305
C51: 13 | D51: Guarda | E51: =VLOOKUP(C51,BIMSA!$A$6:$AH$18,'Catálogo Bimsa'!$D$8,0) -> 0.051986707 | F51: Closets | G51: 1 | H51: 1 | I51: =H51*G51*E51 -> 0.051986707
C52: 14 | D52: Otros (vivienda residencial) | E52: =VLOOKUP(C52,BIMSA!$A$6:$AH$19,'Catálogo Bimsa'!$D$8,0) -> 0 | F52: Accesos, equipos, accesorias | G52: 1 | H52: 1 | I52: =H52*G52*E52 -> 0
D53: Total | E53: =SUM(E13:E52) -> 1 | I53: =SUM(I13:I52) -> 1

Sheet Hoja 16
A1: S | B1: Correo
A2: Erika Tena | B2: erikatenafotografia@gmail.com | D2: ="["&""""&B2&"""" -> ["erikatenafotografia@gmail.com" | E2: =IFERROR(__xludf.DUMMYFUNCTION("JOIN("","",D2:D30)"),"[""erikatenafotografia@gmail.com"",""pedrucus@gmail.com"",""avaluosyarquitectura2@gmail.com"",""omavaluo@gmail.com"",""manuelbaltazaralba@gmail.com"",""arq.yaelcastro@gmail.com"",""arq.masg89@gmail.com"",""tomas.nassim.arq@hotmail.com"",""Arq.macias@gmail"&".com"",""ana.vazquezocejo@gmail.com"",""curso.appsheet.avaluos@gmail.com"",""lucasentorno@gmail.com"",""da.arquitectos@gmail.com"",""alan.pipo2@hotmail.com"",""velascoraarq8@gmail.com"",""befren_@hotmail.com"",""castanedalive1@gmail.com"",""julia@gmail.co"&"m"",""3313822640hi@gmail.com"",""karla@gmail.com"",""3313822640hi@gmail.com"",""pedro@gmail.com"",""pruebaexterno@gmail.com"",""Jesus@gmail.com"",""tomas@gmail.com"",""alicia@gmail.com"",""paticha1970@gmail.com"",""juan.arteaga@amasg.com.mx"",""jmanuel@gm"&"ail.com""]") -> ["erikatenafotografia@gmail.com","pedrucus@gmail.com","avaluosyarquitectura2@gmail.com","omavaluo@gmail.com","manuelbaltazaralba@gmail.com","arq.yaelcastro@gmail.com","arq.masg89@gmail.com","tomas.nassim.arq@hotmail.com","Arq.macias@gmail.com","ana.vazquezocejo@gmail.com","curso.appsheet.avaluos@gmail.com","lucasentorno@gmail.com","da.arquitectos@gmail.com","alan.pipo2@hotmail.com","velascoraarq8@gmail.com","befren_@hotmail.com","castanedalive1@gmail.com","julia@gmail.com","3313822640hi@gmail.com","karla@gmail.com","3313822640hi@gmail.com","pedro@gmail.com","pruebaexterno@gmail.com","Jesus@gmail.com","tomas@gmail.com","alicia@gmail.com","paticha1970@gmail.com","juan.arteaga@amasg.com.mx","jmanuel@gmail.com"]
A3: Pedro Vergara | B3: pedrucus@gmail.com | D3: =""""&B3&"""" -> "pedrucus@gmail.com"
A4: Oficina | B4: avaluosyarquitectura2@gmail.com | D4: =""""&B4&"""" -> "avaluosyarquitectura2@gmail.com" | E4: ["erikatenafotografia@gmail.com","pedrucus@gmail.com","avaluosyarquitectura2@gmail.com","omavaluo@gmail.com","manuelbaltazaralba@gmail.com","arq.yaelcastro@gmail.com","arq.masg89@gmail.com","tomas.nassim.arq@hotmail.com","Arq.macias@gmail.com","ana.vazquezocejo@gmail.com","curso.appsheet.avaluos@gmail.com","lucasentorno@gmail.com","da.arquitectos@gmail.com","alan.pipo2@hotmail.com","velascoraarq8@gmail.com","befren_@hotmail.com","castanedalive1@gmail.com","julia@gmail.com","3313822640hi@gmail.com","karla@gmail.com","3313822640hi@gmail.com","pedro@gmail.com","pruebaexterno@gmail.com","Jesus@gmail.com","tomas@gmail.com","alicia@gmail.com","paticha1970@gmail.com","juan.arteaga@amasg.com.mx","jmanuel@gmail.com"]
A5: Omar Sánchez | B5: omavaluo@gmail.com | D5: =""""&B5&"""" -> "omavaluo@gmail.com"
A6: Manuel Baltazar | B6: manuelbaltazaralba@gmail.com | D6: =""""&B6&"""" -> "manuelbaltazaralba@gmail.com"
A7: Yael Castro Acevedo | B7: arq.yaelcastro@gmail.com | D7: =""""&B7&"""" -> "arq.yaelcastro@gmail.com"
A8: Miguel Silva | B8: arq.masg89@gmail.com | D8: =""""&B8&"""" -> "arq.masg89@gmail.com"
A9: Tomas Nassim | B9: tomas.nassim.arq@hotmail.com | D9: =""""&B9&"""" -> "tomas.nassim.arq@hotmail.com"
A10: Juan Ignacio Macias | B10: Arq.macias@gmail.com | D10: =""""&B10&"""" -> "Arq.macias@gmail.com"
A11: Juanita Vazquez Ocejo | B11: ana.vazquezocejo@gmail.com | D11: =""""&B11&"""" -> "ana.vazquezocejo@gmail.com"
A12: Programador | B12: curso.appsheet.avaluos@gmail.com | D12: =""""&B12&"""" -> "curso.appsheet.avaluos@gmail.com"
A13: Lucas Alberto Sanchez | B13: lucasentorno@gmail.com | D13: =""""&B13&"""" -> "lucasentorno@gmail.com"
A14: Alejandro Damaso | B14: da.arquitectos@gmail.com | D14: =""""&B14&"""" -> "da.arquitectos@gmail.com"
A15: Alejandro Pantoja | B15: alan.pipo2@hotmail.com | D15: =""""&B15&"""" -> "alan.pipo2@hotmail.com"
A16: Roberto velazco | B16: velascoraarq8@gmail.com | D16: =""""&B16&"""" -> "velascoraarq8@gmail.com"
... A29: Juan Antonio Arteaga Calderón | B29: juan.arteaga@amasg.com.mx | D29: =""""&B29&"""" -> "juan.arteaga@amasg.com.mx"
A30: Juan Manuel Pirul | B30: jmanuel@gmail.com | D30: =""""&B30&""""&"]" -> "jmanuel@gmail.com"]

Sheet Catálogo Bimsa
C2: =VLOOKUP(D2,B3:C5,2,) -> 2 | D2: ='% Avance de Obra'!E8 -> Casa en más de un nivel
A3: 1 | B3: Casa en un nivel | C3: 1
A4: 2 | B4: Casa en más de un nivel | C4: 2
A5: 3 | B5: Departamento en condominio | C5: 3
C7: ='% Avance de Obra'!E10 -> Tipo 8: hasta 120M2 | G7: Valores finales para el catálogo de búsqueda
B8: =VLOOKUP(C7,B9:E24,4,) -> 8 | C8: =IF(C2<>3,B8,B8+12) -> 8 | D8: =VLOOKUP(C8,A9:C24,3,0) -> 18
A9: 1 | B9: Tipo 1: hasta 40M2 | C9: 4 | D9: 40 | E9: 1 | G9: =IF($C$2<>3,B9,B21) -> Tipo 1: hasta 40M2
A10: 2 | B10: Tipo 2: hasta 47M2 | C10: 6 | D10: 47 | E10: 2 | G10: =IF($C$2<>3,B10,B22) -> Tipo 2: hasta 47M2
A11: 3 | B11: Tipo 3: hasta 50M2 | C11: 8 | D11: 50 | E11: 3 | G11: =IF($C$2<>3,B11,B23) -> Tipo 3: hasta 50M2
A12: 4 | B12: Tipo 4: hasta 60M2 | C12: 10 | D12: 60 | E12: 4 | G12: =IF($C$2<>3,B12,B24) -> Tipo 4: hasta 60M2
A13: 5 | B13: Tipo 5: hasta 70M2 | C13: 12 | D13: 70 | E13: 5 | G13: =IF($C$2<>3,B13,"") -> Tipo 5: hasta 70M2
A14: 6 | B14: Tipo 6: hasta 90M2 | C14: 14 | D14: 90 | E14: 6 | G14: =IF($C$2<>3,B14,"") -> Tipo 6: hasta 90M2
A15: 7 | B15: Tipo 7: hasta 100M2 | C15: 16 | D15: 100 | E15: 7 | G15: =IF($C$2<>3,B15,"") -> Tipo 7: hasta 100M2
A16: 8 | B16: Tipo 8: hasta 120M2 | C16: 18 | D16: 120 | E16: 8 | G16: =IF($C$2<>3,B16,"") -> Tipo 8: hasta 120M2
A17: 9 | B17: Tipo 9: hasta 150M2 | C17: 20 | D17: 150 | E17: 9 | G17: =IF($C$2<>3,B17,"") -> Tipo 9: hasta 150M2
A18: 10 | B18: Tipo 10: hasta 200M2 | C18: 22 | D18: 200 | E18: 10 | G18: =IF($C$2<>3,B18,"") -> Tipo 10: hasta 200M2
A19: 11 | B19: Tipo 11: hasta 450M2 | C19: 24 | D19: 450 | E19: 11 | G19: =IF($C$2<>3,B19,"") -> Tipo 11: hasta 450M2
A20: 12 | B20: Tipo 12: hasta 700M2 | C20: 26 | D20: 700 | E20: 12 | G20: =IF($C$2<>3,B20,"") -> Tipo 12: hasta 700M2
A21: 13 | B21: DTipo 1: Hasta 50M2 | C21: 28 | D21: 50 | E21: 13
A22: 14 | B22: DTipo 2: Hasta 80M2 | C22: 30 | D22: 80 | E22: 14
A23: 15 | B23: DTipo 3: Hasta 100M2 | C23: 32 | D23: 100 | E23: 15
A24: 16 | B24: DTipo 4: Hasta 120M2 | C24: 34 | D24: 120 | E24: 16
C28: Sin escalera | D28: Con escalera | E28: Resultante
B29: Pretiles, bases, tinacos | C29: 0.2 | D29: 0.15 | E29: =IF($C$2=1,C29,D29) -> 0.15
B30: Albañilería en azotea | C30: 0.15 | D30: 0.1 | E30: =IF($C$2=1,C30,D30) -> 0.1
B31: Huellas | C31: 0.2 | D31: 0.2 | E31: =IF($C$2=1,C31,D31) -> 0.2
B32: Lavadero | C32: 0.05 | D32: 0.05 | E32: =IF($C$2=1,C32,D32) -> 0.05
B33: Bardas posteriores | C33: 0.2 | D33: 0.18 | E33: =IF($C$2=1,C33,D33) -> 0.18
B34: Escaleras | C34: 0 | D34: 0.15 | E34: =IF($C$2=1,C34,D34) -> 0.15
B35: Registros | C35: 0.05 | D35: 0.05 | E35: =IF($C$2=1,C35,D35) -> 0.05
B36: Firme en patio de servicio | C36: 0.15 | D36: 0.12 | E36: =IF($C$2=1,C36,D36) -> 0.12
C37: =SUM(C29:C36) -> 1 | D37: =SUM(D29:D36) -> 1 | E37: =IF($C$2=1,C37,D37) -> 1
B40: Catálogo de Ajuste de precios por Ciudades/ Estados, página 25 BIMSA | G40: 5 | H40: =VLOOKUP(G40,A41:E93,5,0) -> Campeche, Campeche / fajuste 0.967 | J40: =VLOOKUP(G40,A41:D93,4,0) -> 0.967
A41: 1 | B41: Acapulco | C41: Guerrero | D41: 1.036 | E41: =CONCATENATE(B41,","," ",C41," /"," fajuste"," ",D41) -> Acapulco, Guerrero / fajuste 1.036
A42: 2 | B42: Aguascalientes | C42: Aguascalientes | D42: 0.964 | E42: =CONCATENATE(B42,","," ",C42," /"," fajuste"," ",D42) -> Aguascalientes, Aguascalientes / fajuste 0.964
A43: 3 | B43: Altamira | C43: Tamaulipas | D43: 0.964 | E43: =CONCATENATE(B43,","," ",C43," /"," fajuste"," ",D43) -> Altamira, Tamaulipas / fajuste 0.964
A44: 4 | B44: Apodaca | C44: Nuevo León | D44: 1.052 | E44: =CONCATENATE(B44,","," ",C44," /"," fajuste"," ",D44) -> Apodaca, Nuevo León / fajuste 1.052
A45: 5 | B45: Campeche | C45: Campeche | D45: 0.967 | E45: =CONCATENATE(B45,","," ",C45," /"," fajuste"," ",D45) -> Campeche, Campeche / fajuste 0.967
A46: 6 | B46: Cancún | C46: Quintana Roo | D46: 1.112 | E46: =CONCATENATE(B46,","," ",C46," /"," fajuste"," ",D46) -> Cancún, Quintana Roo / fajuste 1.112
A47: 7 | B47: Chihuahua | C47: Chihuahua | D47: 0.992 | E47: =CONCATENATE(B47,","," ",C47," /"," fajuste"," ",D47) -> Chihuahua, Chihuahua / fajuste 0.992
A48: 8 | B48: Chilpancingo | C48: Guerrero | D48: 0.994 | E48: =CONCATENATE(B48,","," ",C48," /"," fajuste"," ",D48) -> Chilpancingo, Guerrero / fajuste 0.994
A49: 9 | B49: Ciudad Juárez | C49: Chihuahua | D49: 1.048 | E49: =CONCATENATE(B49,","," ",C49," /"," fajuste"," ",D49) -> Ciudad Juárez, Chihuahua / fajuste 1.048
A50: 10 | B50: Colima | C50: Colima | D50: 0.994 | E50: =CONCATENATE(B50,","," ",C50," /"," fajuste"," ",D50) -> Colima, Colima / fajuste 0.994
A51: 11 | B51: Cozumel | C51: Quintana Roo | D51: 1.24 | E51: =CONCATENATE(B51,","," ",C51," /"," fajuste"," ",D51) -> Cozumel , Quintana Roo / fajuste 1.24
A52: 12 | B52: Cuautitlán | C52: México | D52: 0.969 | E52: =CONCATENATE(B52,","," ",C52," /"," fajuste"," ",D52) -> Cuautitlán, México / fajuste 0.969
... A93: 53 | B93: Otras ciudades | C93: No incluidas | D93: 1 | E93: =CONCATENATE(B93,","," ",C93," /"," fajuste"," ",D93) -> Otras ciudades, No incluidas / fajuste 1
A98: Cuadro 2.
A99: TIPOS BÁSICOS DE ZONAS
A100: ZONIFICACION PRIMARIA | E100: ZONIFICACION SECUNDARIA
A101: (Plan Regional y Programa Municipal) | C101: (Plan de Centro de Población) | E101: (Plan Parcial de Desarrollo Urbano y/o de Urbanización)
A102: ÁMBITO RURAL
A103: P | B103: Piscícola | C103: P | D103: Piscícola | E103: P | F103: Piscícola
A104: AS | B104: Actividades silvestres | C104: AS | D104: Actividades silvestres | E104: AS | F104: Actividades silvestres
A105: F | B105: Forestal | C105: F | D105: Forestal | E105: F | F105: Forestal
A106: AE | B106: Actividades extractivas | C106: AE | D106: Actividades extractivas | E106: AE-M | F106: Actividades extractivas metálicas
E107: AE-N | F107: Actividades extractivas no metálicas
A108: AG | B108: Agropecuario | C108: AG | D108: Agropecuario | E108: AG | F108: Agropecuario
C109: GH | D109: Granjas y huertos | E109: GH | F109: Granjas y huertos
A110: TE | B110: Turístico ecológico | C110: TE | D110: Turístico ecológico | E110: TE | F110: Turístico ecológico
A111: TC | B111: Turístico campestre | C111: TC | D111: Turístico campestre | E111: TC | F111: Turístico campestre
A112: U | B112: AMBITO URBANO
A113: T | B113: Turístico | C113: TH | D113: Turístico hotelero | E113: TH-1 | F113: Turístico hotelero densidad mínima
E114: TH-2 | F114: Turístico hotelero densidad baja
E115: TH-3 | F115: Turístico hotelero densidad media
E116: TH-4 | F116: Turístico hotelero densidad alta
C117: HJ | D117: Habitacional Jardín | E117: HJ | F117: Habitacional jardín
C118: H1 | D118: Habitacional densidad mínima | E118: H1-U | F118: Unifamiliar
E119: H1-H | F119: Plurifamiliar horizontal
E120: H1-V | F120: Plurifamiliar vertical
C121: H2 | D121: Habitacional densidad baja | E121: H2-U | F121: Unifamiliar
E122: H2-H | F122: Plurifamiliar horizontal
E123: H2-V | F123: Plurifamiliar vertical
C124: H3 | D124: Habitacional densidad media | E124: H3-U | F124: Unifamiliar
E125: H3-H | F125: Plurifamiliar horizontal
E126: H3-V | F126: Plurifamiliar vertical
C127: H4 | D127: Habitacional densidad alta | E127: H4-U | F127: Unifamiliar
E128: H4-H | F128: Plurifamiliar horizontal
E129: H4-V | F129: Plurifamiliar vertical
C130: MB * 1,2,3,4 | D130: Mixto barrial
C131: MD * 1,2,3,4,5 | D131: Mixto distrital
C132: MC * 1,2,3,4,5 | D132: Mixto central
C133: MR | D133: Mixto regional
A134: CR | B134: Comercial regional | C134: CV * 1,2,3,4 | D134: Comercio vecinal | E134: CV * 1,2,3,4 | F134: Comercio vecinal
C135: CB * 1,2,3,4 | D135: Comercio barrial | E135: CB * 1,2,3,4 | F135: Comercio barrial
C136: CD * 1,2,3,4,5 | D136: Comercio distrital | E136: CD * 1,2,3,4,5 | F136: Comercio distrital
C137: CC * 1,2,3,4,5 | D137: Comercio central | E137: CC * 1,2,3,4,5 | F137: Comercio central
C138: CR | D138: Comercio regional | E138: CR | F138: Comercio regional
A139: SR | B139: Servicios regionales | C139: SV * 1,2,3,4 | D139: Servicios vecinales | E139: SV * 1,2,3,4 | F139: Servicios vecinales
C140: SB * 1,2,3,4 | D140: Servicios barriales | E140: SB * 1,2,3,4 | F140: Servicios barriales
C141: SD * 1,2,3,4,5 | D141: Servicios distritales | E141: SD * 1,2,3,4,5 | F141: Servicios distritales
C142: SC * 1,2,3,4,5 | D142: Servicios centrales | E142: SC * 1,2,3,4,5 | F142: Servicios centrales
C143: SR | D143: Servicios regionales | E143: SR | F143: Servicios regionales
A144: SI | B144: Servicios a la Industria y comercio | C144: SI | D144: Servicios a la industria y comercio | E144: SI | F144: Servicios a la industria y comercio
A145: I | B145: Industrial | C145: MFD | D145: Manufacturas domiciliarias | E145: MFD | F145: Manufacturas domiciliarias
C146: MFM | D146: Manufacturas menores | E146: MFM | F146: Manufacturas menores
C147: I1 | D147: Industria ligera de riesgo bajo | E147: I1 | F147: Industria ligera y de riesgo bajo
C148: I2 | D148: Industria mediana de riesgo medio | E148: I2 | F148: Industria mediana y de riesgo medio
C149: I3 | D149: Industria pesada de riesgo alto | E149: I3 | F149: Industria pesada y de riesgo alto
C150: IJ | D150: Parque industrial jardín | E150: IJ | F150: Parque industrial jardín
A151: EI-R | B151: Equipamiento regional | C151: EI-V | D151: Equipamiento vecinal | E151: EI-V | F151: Equipamiento vecinal
...

Sheet BIMSA
B1: Fuente: BIMSA OCTUBRE 2009
C2: CASA HABITACIÓN UNIFAMILIAR O DUPLEX | AA2: DEPARTAMENTO EN CONDOMINIO
A3: 1 | B3: 2 | C3: 3 | D3: 4 | E3: 5 | F3: 6 | G3: 7 | H3: 8 | I3: 9 | J3: 10 | K3: 11 | L3: 12 | M3: 13 | N3: 14 | O3: 15 | P3: 16 | Q3: 17 | R3: 18 | S3: 19 | T3: 20 | U3: 21 | V3: 22 | W3: 23 | X3: 24 | Y3: 25 | Z3: 26 | AA3: 27 | AB3: 28 | AC3: 29 | AD3: 30 | AE3: 31 | AF3: 32 | AG3: 33 | AH3: 34 | AI3: 35 | AJ3: 36 | AK3: 37 | AL3: 38 | AM3: 39 | AN3: 40 | AO3: 41 | AP3: 42 | AQ3: 43 | AR3: 44 | AS3: 45
B4: Partida | C4: Tipo 1: hasta 40M2 | E4: Tipo 2: hasta 47M2 | G4: Tipo 3: hasta 50M2 | I4: Tipo 4: hasta 60M2 | K4: Tipo 5: hasta 70M2 | M4: Tipo 6: hasta 90M2 | O4: Tipo 7: hasta 100M2 | Q4: Tipo 8: hasta 120M2 | S4: Tipo 9: hasta 150M2 | U4: Tipo 10: hasta 200M2 | W4: Tipo 11: hasta 450M2 | Y4: Tipo 12: hasta 700M2 | AA4: Depto 1: Hasta 50M2 | AC4: Depto 2: Hasta 80M2 | AE4: Depto 3: Hasta 100M2 | AG4: Depto 4: Hasta 120M2
A6: 1 | B6: Cimentación | C6: 22469 | D6: =C6/$C$20 -> 0.1560293 | E6: 26396 | F6: =E6/$E$20 -> 0.13889707 | G6: 28319 | H6: =G6/$G$20 -> 0.1494643 | I6: 34114 | J6: =I6/$I$20 -> 0.1329882 | K6: 42261 | L6: =K6/$K$20 -> 0.13422966 | M6: 71906 | N6: =M6/$M$20 -> 0.13976714 | O6: 73041 | P6: =O6/$O$20 -> 0.12643435 | Q6: 74176 | R6: =Q6/$Q$20 -> 0.11486941 | S6: 82258 | T6: =S6/$S$20 -> 0.11922175 | U6: 99253 | V6: =U6/$U$20 -> 0.12566343 | W6: 286211 | X6: =W6/$W$20 -> 0.11273462 | Y6: 389118 | Z6: =Y6/$Y$20 -> 0.092682053 | AA6: 259375 | AB6: =AA6/$AA$20 -> 0.16227398 | AC6: 341052 | AD6: =AC6/$AC$20 -> 0.11552763 | AE6: 899754 | AF6: =AE6/$AE$20 -> 0.080658728 | AG6: 1446434 | AH6: =AG6/$AG$20 -> 0.098251832
A7: 2 | B7: Estructura | C7: 18632 | D7: =C7/$C$20 -> 0.1293844 | E7: 20432 | F7: =E7/$E$20 -> 0.10751421 | G7: 21920 | H7: =G7/$G$20 -> 0.11569114 | I7: 24505 | J7: =I7/$I$20 -> 0.095528986 | K7: 30357 | L7: =K7/$K$20 -> 0.096420098 | M7: 61391 | N7: =M7/$M$20 -> 0.11932863 | O7: 100477 | P7: =O7/$O$20 -> 0.17392621 | Q7: 107805 | R7: =Q7/$Q$20 -> 0.16694748 | S7: 115133 | T7: =S7/$S$20 -> 0.16686958 | U7: 159729 | V7: =U7/$U$20 -> 0.20223161 | W7: 441591 | X7: =W7/$W$20 -> 0.17393669 | Y7: 705541 | Z7: =Y7/$Y$20 -> 0.16804925 | AA7: 247529 | AB7: =AA7/$AA$20 -> 0.15486271 | AC7: 557181 | AD7: =AC7/$AC$20 -> 0.18873896 | AE7: 2029025 | AF7: =AE7/$AE$20 -> 0.18189258 | AG7: 3618769 | AH7: =AG7/$AG$20 -> 0.2458119
A8: 3 | B8: Albañilería | C8: 14902 | D8: =C8/$C$20 -> 0.10348252 | E8: 19750 | F8: =E8/$E$20 -> 0.10392549 | G8: 19195 | H8: =G8/$G$20 -> 0.10130891 | I8: 38420 | J8: =I8/$I$20 -> 0.14977448 | K8: 42965 | L8: =K8/$K$20 -> 0.13646571 | M8: 59592 | N8: =M8/$M$20 -> 0.11583183 | O8: 68884 | P8: =O8/$O$20 -> 0.11923857 | Q8: 68370 | R8: =Q8/$Q$20 -> 0.1058782 | S8: 79938 | T8: =S8/$S$20 -> 0.11585923 | U8: 92134 | V8: =U8/$U$20 -> 0.11665012 | W8: 247380 | X8: =W8/$W$20 -> 0.09743962 | Y8: 371065 | Z8: =Y8/$Y$20 -> 0.0883821 | AA8: 166207 | AB8: =AA8/$AA$20 -> 0.10398485 | AC8: 389239 | AD8: =AC8/$AC$20 -> 0.13185045 | AE8: 1188436 | AF8: =AE8/$AE$20 -> 0.10653772 | AG8: 1094001 | AH8: =AG8/$AG$20 -> 0.074312138
A9: 4 | B9: Instalación hidráulica | C9: 4512 | D9: =C9/$C$20 -> 0.031332245 | E9: 17260 | F9: =E9/$E$20 -> 0.090822985 | G9: 16770 | H9: =G9/$G$20 -> 0.088510054 | I9: 18653 | J9: =I9/$I$20 -> 0.072715861 | K9: 16857 | L9: =K9/$K$20 -> 0.053541311 | M9: 26061 | N9: =M9/$M$20 -> 0.050656015 | O9: 27382 | P9: =O9/$O$20 -> 0.047398386 | Q9: 24465 | R9: =Q9/$Q$20 -> 0.037886648 | S9: 29046 | T9: =S9/$S$20 -> 0.042098215 | U9: 40114 | V9: =U9/$U$20 -> 0.050788016 | W9: 67881 | X9: =W9/$W$20 -> 0.026737403 | Y9: 62977 | Z9: =Y9/$Y$20 -> 0.015000174 | AA9: 38829 | AB9: =AA9/$AA$20 -> 0.024292767 | AC9: 37868 | AD9: =AC9/$AC$20 -> 0.01282737 | AE9: 229054 | AF9: =AE9/$AE$20 -> 0.020533617 | AG9: 213465 | AH9: =AG9/$AG$20 -> 0.014500024
A10: 5 | B10: Instalación sanitaria | C10: 5953 | D10: =C10/$C$20 -> 0.041338842 | E10: 7903 | F10: =E10/$E$20 -> 0.041585982 | G10: 7611 | H10: =G10/$G$20 -> 0.040169948 | I10: 6559 | J10: =I10/$I$20 -> 0.025569256 | K10: 6559 | L10: =K10/$K$20 -> 0.020832738 | M10: 9821 | N10: =M10/$M$20 -> 0.019089548 | O10: 11771 | P10: =O10/$O$20 -> 0.020375663 | Q10: 13428 | R10: =Q10/$Q$20 -> 0.020794683 | S10: 13721 | T10: =S10/$S$20 -> 0.019886718 | U10: 14306 | V10: =U10/$U$20 -> 0.018112713 | W10: 37510 | X10: =W10/$W$20 -> 0.014774679 | Y10: 45072 | Z10: =Y10/$Y$20 -> 0.010735472 | AA10: 44167 | AB10: =AA10/$AA$20 -> 0.027632405 | AC10: 56745 | AD10: =AC10/$AC$20 -> 0.019221747 | AE10: 157189 | AF10: =AE10/$AE$20 -> 0.014091257 | AG10: 147545 | AH10: =AG10/$AG$20 -> 0.01002228
A11: 6 | B11: Instalación eléctrica | C11: 3769 | D11: =C11/$C$20 -> 0.026172702 | E11: 4039 | F11: =E11/$E$20 -> 0.02125342 | G11: 3769 | H11: =G11/$G$20 -> 0.019892331 | I11: 9286 | J11: =I11/$I$20 -> 0.036200048 | K11: 9286 | L11: =K11/$K$20 -> 0.029494253 | M11: 13168 | N11: =M11/$M$20 -> 0.025595273 | O11: 13168 | P11: =O11/$O$20 -> 0.022793877 | Q11: 13622 | R11: =Q11/$Q$20 -> 0.021095112 | S11: 16347 | T11: =S11/$S$20 -> 0.023692747 | U11: 20433 | V11: =U11/$U$20 -> 0.025870058 | W11: 28607 | X11: =W11/$W$20 -> 0.011267909 | Y11: 51502 | Z11: =Y11/$Y$20 -> 0.012267002 | AA11: 35235 | AB11: =AA11/$AA$20 -> 0.022044236 | AC11: 64054 | AD11: =AC11/$AC$20 -> 0.021697591 | AE11: 233371 | AF11: =AE11/$AE$20 -> 0.020920616 | AG11: 261921 | AH11: =AG11/$AG$20 -> 0.017791491
A12: 7 | B12: Instalación gas | C12: 3338 | D12: =C12/$C$20 -> 0.023179751 | E12: 3338 | F12: =E12/$E$20 -> 0.017564723 | G12: 3338 | H12: =G12/$G$20 -> 0.017617565 | I12: 3338 | J12: =I12/$I$20 -> 0.013012681 | K12: 3338 | L12: =K12/$K$20 -> 0.010602177 | M12: 3338 | N12: =M12/$M$20 -> 0.0064882306 | O12: 3338 | P12: =O12/$O$20 -> 0.0057780955 | Q12: 3338 | R12: =Q12/$Q$20 -> 0.0051692472 | S12: 3338 | T12: =S12/$S$20 -> 0.0048379756 | U12: 3338 | V12: =U12/$U$20 -> 0.0042262152 | W12: 3338 | X12: =W12/$W$20 -> 0.0013147928 | Y12: 5006 | Z12: =Y12/$Y$20 -> 0.0011923539 | AA12: 26703 | AB12: =AA12/$AA$20 -> 0.016706321 | AC12: 26703 | AD12: =AC12/$AC$20 -> 0.0090453487 | AE12: 33379 | AF12: =AE12/$AE$20 -> 0.0029922709 | AG12: 26703 | AH12: =AG12/$AG$20 -> 0.001813853
A13: 8 | B13: Acabados interiores | C13: 13309 | D13: =C13/$C$20 -> 0.092420402 | E13: 29891 | F13: =E13/$E$20 -> 0.15728794 | G13: 29929 | H13: =G13/$G$20 -> 0.15796168 | I13: 43390 | J13: =I13/$I$20 -> 0.16914926 | K13: 71688 | L13: =K13/$K$20 -> 0.22769588 | M13: 99987 | N13: =M13/$M$20 -> 0.19434952 | O13: 112980 | P13: =O13/$O$20 -> 0.19556897 | Q13: 149030 | R13: =Q13/$Q$20 -> 0.23078877 | S13: 149030 | T13: =S13/$S$20 -> 0.21599866 | U13: 149030 | V13: =U13/$U$20 -> 0.1886857 | W13: 399427 | X13: =W13/$W$20 -> 0.15732887 | Y13: 982247 | Z13: =Y13/$Y$20 -> 0.23395646 | AA13: 237545 | AB13: =AA13/$AA$20 -> 0.14861638 | AC13: 519512 | AD13: =AC13/$AC$20 -> 0.175979 | AE13: 2564845 | AF13: =AE13/$AE$20 -> 0.22992633 | AG13: 2628948 | AH13: =AG13/$AG$20 -> 0.17857639
A14: 9 | B14: Acabados exteriores | C14: 15320 | D14: =C14/$C$20 -> 0.1063852 | E14: 18375 | F14: =E14/$E$20 -> 0.09669017 | G14: 19303 | H14: =G14/$G$20 -> 0.10187893 | I14: 27813 | J14: =I14/$I$20 -> 0.10842472 | K14: 35108 | L14: =K14/$K$20 -> 0.11151025 | M14: 47719 | N14: =M14/$M$20 -> 0.092753708 | O14: 52472 | P14: =O14/$O$20 -> 0.090829307 | Q14: 57224 | R14: =Q14/$Q$20 -> 0.088617435 | S14: 62923 | T14: =S14/$S$20 -> 0.091198305 | U14: 68622 | V14: =U14/$U$20 -> 0.086881767 | W14: 309804 | X14: =W14/$W$20 -> 0.12202759 | Y14: 461267 | Z14: =Y14/$Y$20 -> 0.10986686 | AA14: 158653 | AB14: =AA14/$AA$20 -> 0.099258811 | AC14: 199203 | AD14: =AC14/$AC$20 -> 0.067477834 | AE14: 550088 | AF14: =AE14/$AE$20 -> 0.04931281 | AG14: 1869599 | AH14: =AG14/$AG$20 -> 0.12699614
